Workbook

Sheet Executive Summary
A1: Pollo Campero Deal Economics
A2: Internal planning model | September 30 2026 | Installation for native SoC remains TBD
A4: Commercial Snapshot
A5: Metric | B5: Low case | C5: High case | D5: Status | E5: Notes
A6: One-time revenue excluding native SoC installation | B6: ='Fleet Economics'!F13 | C6: ='Fleet Economics'!G13 | D6: Planning range | E6: Outdoor range uses normalized dual-lane and single-lane rates.
A7: Target cost ceiling at 30% gross margin | B7: ='Fleet Economics'!F16 | C7: ='Fleet Economics'!G16 | D7: Planning range | E7: Maximum total delivery cost consistent with target margin.
A8: Annual recurring revenue | B8: ='Fleet Economics'!F20 | C8: ='Fleet Economics'!F20 | D8: Incomplete | E8: Enter site counts for the $90 and $120 monthly packages.
A9: Native SoC installation revenue | B9: ='Assumptions'!B12 | C9: ='Assumptions'!B12 | D9: TBD | E9: Held at zero until Cesar confirms pricing.
A12: Decision Items
A13: 1. Obtain the native SoC installation price from Cesar and enter it in Assumptions B10.
A14: 2. Confirm the outdoor single-lane and dual-lane location mix; 211 controllers cannot be converted into an exact site total without it.
A15: 3. Enter actual controller, labor, licensing, freight, and project-delivery costs before relying on gross profit outputs.
A16: 4. Confirm whether the 61 indoor locations are separate from, or overlap with, the sites used for recurring CMS pricing.

Sheet Assumptions
A1: Assumptions
A2: Blue font indicates editable inputs. Yellow cells require confirmation.
A4: Input | B4: Value | C4: Unit | D4: Status | E4: Source or rationale
A5: Native SoC displays | B5: 426 | C5: displays | D5: Confirmed | E5: Fleet analysis and product review email
A6: Native SoC setup and configuration fee | B6: 10 | C6: $ per display | D6: Confirmed | E6: Todd instruction, September 30 2026
A7: Indoor legacy displays | B7: 270 | C7: displays | D7: Confirmed | E7: Product review email
A8: Indoor MP30 controllers | B8: 149 | C8: controllers | D8: Confirmed | E8: Product review email
A9: Indoor locations | B9: 61 | C9: locations | D9: Confirmed | E9: Todd scope email
A10: Indoor installed sell price | B10: 3500 | C10: $ per location | D10: Confirmed | E10: RFP response workbook
A11: Outdoor MP30 controllers | B11: 211 | C11: controllers | D11: Confirmed | E11: Product review email
A12: Native SoC installation sell price | B12: 0 | C12: $ total | D12: TBD | E12: Pending Cesar response; intentionally excluded
A13: Single-lane installed sell price | B13: 3163 | C13: $ per site | D13: Confirmed | E13: RFP response workbook
A14: Controllers per single-lane site | B14: 4 | C14: controllers | D14: Confirmed | E14: Three menu displays plus one presell display
A15: Dual-lane installed sell price | B15: 6160 | C15: $ per site | D15: Confirmed | E15: RFP response workbook
A16: Controllers per dual-lane site | B16: 8 | C16: controllers | D16: Confirmed | E16: Six menu displays plus two presell displays
... A23: Actual outdoor MP30 delivery cost | B23: 0 | C23: $ total | D23: TBD | E23: Enter controller, labor, freight, and project cost

Sheet Fleet Economics
A1: Fleet Economics
A2: Formula-driven one-time and recurring revenue view
A4: Revenue component | B4: Quantity | C4: Rate | D4: Low revenue | E4: High revenue | F4: Low case total | G4: High case total | H4: Notes
A5: Native SoC setup and configuration | B5: ='Assumptions'!B5 | C5: ='Assumptions'!B6 | D5: =B5*C5 | E5: =B5*C5 | H5: Excludes installation
A6: Native SoC installation | B6: 1 | C6: ='Assumptions'!B12 | D6: =B6*C6 | E6: =B6*C6 | H6: Zero until confirmed
A7: Indoor shared MP30 installed | B7: ='Assumptions'!B9 | C7: ='Assumptions'!B10 | D7: =B7*C7 | E7: =B7*C7 | H7: 61 locations at $3,500
A8: Outdoor dedicated MP30 normalized | B8: ='Assumptions'!B11 | C8: ='Assumptions'!B15/'Assumptions'!B16 | D8: =B8*C8 | E8: =B8*('Assumptions'!B13/'Assumptions'!B14) | H8: Low uses dual-lane per-controller rate; high uses single-lane rate
A10: One-time revenue total | D10: =SUM(D5:D8) | E10: =SUM(E5:E8)
A13: Revenue range used in summary | F13: =D10 | G13: =E10
A15: Target cost ceiling
A16: Maximum total cost at target margin | F16: =F13*(1-'Assumptions'!B17) | G16: =G13*(1-'Assumptions'!B17)
A18: Recurring Revenue
A19: Revenue component | B19: Sites | C19: Monthly rate | D19: Monthly revenue | E19: Annual revenue | F19: Annual total | H19: Notes
A20: $90 DMB package | B20: ='Assumptions'!B18 | C20: 90 | D20: =B20*C20 | E20: =D20*12 | F20: =SUM(E20:E22) | H20: Standard indoor plus single-lane package
A21: $120 DMB package | B21: ='Assumptions'!B19 | C21: 120 | D21: =B21*C21 | E21: =D21*12 | H21: Standard indoor plus dual-lane package
A22: Optional managed content | B22: ='Assumptions'!B20 | C22: 100 | D22: =B22*C22 | E22: =D22*12 | H22: Optional base package per location
A24: Annual recurring revenue total | E24: =SUM(E20:E22)
A27: Actual Cost and Margin Check
A28: Metric | B28: Low case | C28: High case
A29: Revenue | B29: =D10 | C29: =E10
A30: Actual cost entered | B30: =SUM('Assumptions'!B21:B23) | C30: =SUM('Assumptions'!B21:B23)
A31: Gross profit | B31: =B29-B30 | C31: =C29-C30
A32: Gross margin | B32: =IF(B29=0,0,B31/B29) | C32: =IF(C29=0,0,C31/C29)

Sheet Outdoor Mix
A1: Outdoor Site Mix
A2: Enter whole site counts that explain the validated controller quantity
A4: Input or output | B4: Value | C4: Unit | D4: Status | E4: Explanation
A5: Single-lane sites | B5: 0 | C5: sites | D5: TBD | E5: Editable
A6: Dual-lane sites | B6: 0 | C6: sites | D6: TBD | E6: Editable
A7: Controllers represented | B7: =B5*'Assumptions'!B14+B6*'Assumptions'!B16 | C7: controllers | D7: =IF(B7='Assumptions'!B11,"Matches","Does not match") | E7: Must equal 211 after validation
A8: Controller variance | B8: =B7-'Assumptions'!B11 | C8: controllers | D8: =IF(B8=0,"OK","Resolve") | E8: A nonzero value indicates incomplete site mix or an exception
A9: Outdoor installed revenue | B9: =B5*'Assumptions'!B13+B6*'Assumptions'!B15 | C9: $ | D9: Planning output | E9: Exact only when mix and exceptions are confirmed

Sheet Sources
A1: Sources and Traceability
A2: Inputs used to construct the addendum and internal economics model
A4: Source | B4: Location | C4: Use | D4: Key facts | E4: Caution
A5: STOCK Menu Boards RFP.xlsx | B5: /Users/toddvahlsing/Downloads/STOCK Menu Boards RFP.xlsx | C5: Raw inventory | D5: 1,001 total displays; 908 active; 93 in stock | E5: Model labels include a missing value and several variants.
A6: Pollo Campero Digital Menu Board Stock Report.xlsx | B6: /Users/toddvahlsing/Downloads/Pollo_Campero_Digital_Menu_Board_Stock_Report.xlsx | C6: Fleet classification | D6: Model, platform, SoC, age, and inventory summary | E6: Model age is series age, not individual unit age.
A7: Pollo Campero SOW MenuBoards GP Genius Response.xlsx | B7: /Users/toddvahlsing/Documents/Genius Info/Accounts/Pollo Campero/Pollo Campero SOW MenuBoards - GP Genius Response.xlsx | C7: Commercial baseline | D7: $3,500 indoor; $3,163 single lane; $6,160 dual lane; recurring rates | E7: Pricing remains subject to site survey and assumptions.
A8: Pollo Campero RFP GP Genius Executive Summary.pdf | B8: /Users/toddvahlsing/Documents/Genius Info/Accounts/Pollo Campero/Pollo Campero RFP - GP Genius Executive Summary.pdf | C8: Scope and proposal context | D8: DMB solution, assumptions, warranty, and installation context | E8: Original proposal disclaimers continue to apply.
A9: Product review email screenshots | B9: User supplied screenshots dated September 28 and 29 2026 | C9: Approved deployment quantities | D9: 426 native SoC; 270 indoor displays / 149 MP30; 211 outdoor 1:1; 1 unidentified | E9: Installation and material assumptions remain subject to Cesar and Tim.
A10: Todd instruction | B10: User request dated September 30 2026 | C10: Revised SoC fee and pending price | D10: $10 one-time setup and configuration per SoC display | E10: Native SoC installation price must remain TBD pending Cesar.
