Workbook

Sheet Executive Summary
A1: Executive Summary — Worldpay Master Account Plan | 2026-09-04
A2: Research and account intelligence refreshed through 2026-09-04 | 30 opportunity accounts plus 2 managed/excluded accounts | Scores and tiers unchanged pending human review
A4: Portfolio Signal | B4: Current Read
A5: #1 priority | B5: Del Taco — complete extension, consolidate GP leads and validate the post-Yadav technology/consolidation event
A6: #2 priority | B6: Five Guys — centralize outreach through Todd and Avery, use FSTEC for relationship-led access, and validate the buying event before presenting any funding model
A7: Channel pilot | B7: RDS five-unit rebrand — qualify the clean-slate pilot, protection rules and reseller operating model before Genius World
A8: Scope verification | B8: Subway — replace the prior DMB assumption with reported global Genius KDS; verify product, sites, owner and commitments
A9: Watchlist guardrail | B9: Freddy's and Slim Chickens are RDS-led/no-direct-outreach; Papa Johns is deployment/adjacency watch, not POS displacement
A12: Rank | B12: Account | C12: Score | D12: RM | E12: Opportunity Motion | F12: Immediate Action
A13: 1 | B13: DEL TACO LLC | C13: 83 | D13: Maggie Lenhart | E13: POS/payments + multi-brand consolidation | F13: Complete the extension, consolidate all GP leads, map Yadav technology governance and confirm any sourcing or vendor-consolidation event.
A14: 2 | B14: FIVE GUYS | C14: 82 | D14: Avery Churchwell | E14: Pre-RFP shaping + transaction-metered POS feasibility | F14: Centralize all Five Guys outreach through Todd and Avery; avoid generic prospecting. Use FSTEC only for a relationship-first conversation, validate whether MJ still engages former PAR account manager Chad Kaisel, and confirm PAR term, evaluation type, sponsor, scope and global gaps before presenting any commercial model.
A15: 3 | B15: Focus Brands (GoTo Foods) | C15: 81 | D15: Brian Wood | E15: DMB-led adjacency + payments defense | F15: Map DMB/CMS and buying center; quantify uncovered adjacencies and defend payments without positioning a near-term POS displacement.
A16: 4 | B16: SUBWAY | C16: 79 | D16: Stacie Davis | E16: Existing Genius KDS scope verification + relationship map | F16: Confirm the Genius product owner, KDS sites, deployment status, commitments and customer sponsor before proposing any additional adjacency.
A17: 5 | B17: THE STEAK N SHAKE CO | C17: 76 | D17: Maggie Lenhart | E17: Kiosk integration recovery + digital adjacency | F17: Name the kiosk vendor and owners; document certification, NCR reporting and mobile-app issues with dated remediation milestones.
A18: 6 | B18: CHOICE HOTELS | C18: 75 | D18: Brian Wood | E18: Payments win-back + hospitality adjacency | F18: Confirm whether the RFP remains active, current stage, decision dates, retained Worldpay estate, sponsor and restaurant/DMB scope.
A19: 7 | B19: RDS FIVE-UNIT REBRAND PILOT | C19: 74 | D19: RDS / Darren Heinze | E19: RDS-led Genius pilot and reseller proof | F19: Confirm entity/concept, authority, dates, budget and incumbent contracts; define scope, economics, support, success metrics and case-study rights before Genius World.
A20: 8 | B20: POLLO CAMPERO | C20: 72 | D20: Unassigned / Worldpay | E20: RFI qualification + international platform/payments/DMB | F20: Obtain NDA/RFI, confirm sponsor and deadlines, separate the stalled referral from the procurement stream, and apply country-by-country bid/no-bid gates.
A23: Executive conclusions
A24: 1. Del Taco remains #1. The Yadav acquisition is verified, but an active sourcing event is not; finish the extension, merge GP leads and validate post-acquisition governance.
A25: 2. Five Guys remains #2 for account shaping. Uncoordinated outreach has created relationship risk; centralize activity through Todd and Avery, use FSTEC carefully, and keep the transaction-metered concept internal until approved.
A26: 3. The RDS five-unit rebrand is the preferred near-term channel proof. Define entity, authority, stack, economics, support, protections and success metrics before expanding into protected accounts.
A27: 4. Subway requires urgent scope correction: current internal intelligence indicates proprietary POS plus a global Genius KDS deployment, not DMB.
A28: 5. Freddy's and Slim Chickens remain RDS-led. Slim Chickens now has an FSTEC relationship opening; Freddy's remains unresponsive. Little Caesars has active support contact but stalled commercial follow-up, and Red Robin warrants renewed qualification.
A29: 6. PAR's platform, ordering and payments-attachment strategy is the primary competitive pattern. Counter with modularity, integrations, payments economics and deployment proof.

Sheet Dashboard
A1: Worldpay Master Account Intelligence Dashboard — 2026-09-04
A2: Portfolio refreshed through 2026-09-04. Avery's latest account updates are incorporated; rankings and tiers remain unchanged pending review.
B4: Opportunities | D4: P1 Targets | F4: Excluded / Managed Elsewhere | H4: RM / Field Updates | J4: Evidence Events | L4: Open Conflicts
B5: 30 | D5: 4 | F5: 2 | H5: 28 | J5: 33 | L5: 10
A9: Top Opportunities | B9: Score | D9: RM / Route | E9: Opportunities | G9: Lifecycle | H9: Opportunities | J9: Opportunity Type | K9: Opportunities
A10: DEL TACO LLC | B10: 83 | D10: Avery Churchwell | E10: 11 | G10: Mature/Aging | H10: 4 | J10: POS-led | K10: 7
A11: FIVE GUYS | B11: 82 | D11: Brian Wood | E11: 8 | G11: Deploying/New | H11: 6 | J11: Adjacent-led | K11: 8
A12: Focus Brands (GoTo Foods) | B12: 81 | D12: Maggie Lenhart | E12: 6 | G12: Other/Mixed | H12: 6 | J12: Discovery/other | K12: 14
A13: SUBWAY | B13: 79 | D13: Stacie Davis | E13: 3 | G13: Established | H13: 11 | J13: Win-back | K13: 1
A14: THE STEAK N SHAKE CO | B14: 76 | D14: RDS / Darren Heinze | E14: 1 | G14: Proprietary | H14: 3
A15: CHOICE HOTELS | B15: 75 | D15: Unassigned / Worldpay | E15: 1
A16: RDS FIVE-UNIT REBRAND PILOT | B16: 74
A17: POLLO CAMPERO | B17: 72
A18: EAT'N PARK HOSPITALITY GRP INC | B18: 64
A19: FREDDY'S FROZEN CUSTARD LLC | B19: 63
A20: PAPA JOHN'S USA, INC. | B20: 62
A21: CRACKER BARREL OLD COUNTRY STORE, INC. | B21: 61
A25: Layer | B25: Named vendor / scope | C25: Unverified / gap
A26: POS | B26: 31 | C26: 1
A27: Payments | B27: 30 | C27: 2
A28: Digital | B28: 30 | C28: 2
A29: Loyalty/CRM | B29: 2 | C29: 30
A30: Back Office | B30: 3 | C30: 29
A31: Kiosk/DMB | B31: 13 | C31: 19
A32: KDS | B32: 1 | C32: 31
A33: Drive-Thru | B33: 1 | C33: 31
A34: Hardware | B34: 20 | C34: 12

Sheet Ranked Portfolio
A1: Ranked Worldpay Opportunity Portfolio — 2026-09-04 Master Plan
A2: Evidence and field intelligence refreshed through 2026-09-04. Scores and tiers remain judgment-based and unchanged pending human review.
A4: Rank | B4: Priority | C4: Account | D4: RM | E4: Tier | F4: Locations | G4: Score | H4: Strategic Value | I4: Active Trigger | J4: Access | K4: Lifecycle | L4: Deployment Health | M4: Whitespace | N4: Coordination | O4: Trigger / Current State | P4: Lifecycle Posture | Q4: Health | R4: Opportunity Type | S4: Immediate Next Action | T4: Key Vendors | U4: Field Intelligence | V4: Evidence Confidence
A5: 1 | B5: P1 | C5: DEL TACO LLC | D5: Maggie Lenhart | E5: Tier 2 | F5: 537 | G5: =(H5/5*'Scoring Model'!$B$5+I5/5*'Scoring Model'!$B$6+J5/5*'Scoring Model'!$B$7+K5/5*'Scoring Model'!$B$8+L5/5*'Scoring Model'!$B$9+M5/5*'Scoring Model'!$B$10+N5/5*'Scoring Model'!$B$11)*100 | H5: 4 | I5: 5 | J5: 4 | K5: 4 | L5: 3 | M5: 4 | N5: 5 | O5: Worldpay extension active; Yadav acquisition creates a verified ownership-change window; sourcing event unconfirmed | P5: Aging NCR estate; post-acquisition multi-brand governance | Q5: Active relationship; technology and synergy timing to verify | R5: POS/payments + multi-brand consolidation | S5: Complete the extension, consolidate all GP leads, map Yadav technology governance and confirm any sourcing or vendor-consolidation event. | T5: NCR; NCR Connected Payments; Olo; Olo Pay; Bite | U5: Yadav Enterprises completed the acquisition in Dec. 2025. Direct CIO access and the extension remain strong; cost/stack review is a hypothesis pending customer confirmation. | V5: High RM intelligence + verified ownership event
A6: 2 | B6: P1 | C6: FIVE GUYS | D6: Avery Churchwell | E6: Tier 1 | F6: 1500 | G6: =(H6/5*'Scoring Model'!$B$5+I6/5*'Scoring Model'!$B$6+J6/5*'Scoring Model'!$B$7+K6/5*'Scoring Model'!$B$8+L6/5*'Scoring Model'!$B$9+M6/5*'Scoring Model'!$B$10+N6/5*'Scoring Model'!$B$11)*100 | H6: 5 | I6: 5 | J6: 4 | K6: 5 | L6: 2 | M6: 2 | N6: 5 | O6: MJ Worsham remains the key influential contact. Multiple uncoordinated Genius outreach attempts have created account-ownership friction; MJ and Zerick were invited to the FSTEC happy hour but had not responded as of the September 4 Avery call. No formal RFI/RFP is confirmed. | P6: Mature U.S. PAR estate; global support gaps and modularity hypothesis | Q6: No verified failure; renewal dates and evaluation type require confirmation | R6: Pre-RFP shaping + transaction-metered POS feasibility | S6: Centralize all Five Guys outreach through Todd and Avery; avoid generic prospecting. Use FSTEC only for a relationship-first conversation, validate whether MJ still engages former PAR account manager Chad Kaisel, and confirm PAR term, evaluation type, sponsor, scope and global gaps before presenting any commercial model. | T6: PAR Brink; NCR (EMEA); CrunchTime; Olo; Worldpay/Global Payments; Verifone; LineTen | U6: Avery reported that her merchant questioned why multiple Genius people were contacting Five Guys without her knowledge. She emphasized that introductions should flow through the relationship owner. MJ is resistant to consolidating multiple lines of business with one vendor and will require a compelling reason to engage. Todd is internally exploring a capped per-card-swipe technology funding model, but it is not approved or customer-presented. | V6: High RM intelligence dated 2026-09-04 / buying event, dates and commercial model remain unconfirmed
A7: 3 | B7: P1 | C7: Focus Brands (GoTo Foods) | D7: Brian Wood | E7: Tier 2 | F7: 2600 | G7: =(H7/5*'Scoring Model'!$B$5+I7/5*'Scoring Model'!$B$6+J7/5*'Scoring Model'!$B$7+K7/5*'Scoring Model'!$B$8+L7/5*'Scoring Model'!$B$9+M7/5*'Scoring Model'!$B$10+N7/5*'Scoring Model'!$B$11)*100 | H7: 5 | I7: 5 | J7: 3 | K7: 2 | L7: 5 | M7: 4 | N7: 4 | O7: Qu established; DMB relationship development and defense against Qu Pay/platform expansion | P7: Deploying since 2024 | Q7: Schedule risk reported | R7: DMB-led adjacency + payments defense | S7: Map DMB/CMS and buying center; quantify uncovered adjacencies and defend payments without positioning a near-term POS displacement. | T7: Qu; FreedomPay; Olo; Monkey Media | U7: Qu remains established. Treat PAR/Qu-style platform consolidation and native-payments attachment as the competitive pattern to counter. | V7: High RM intelligence + public evidence
A8: 4 | B8: P1 | C8: SUBWAY | D8: Stacie Davis | E8: Tier 1 | F8: 20000 | G8: =(H8/5*'Scoring Model'!$B$5+I8/5*'Scoring Model'!$B$6+J8/5*'Scoring Model'!$B$7+K8/5*'Scoring Model'!$B$8+L8/5*'Scoring Model'!$B$9+M8/5*'Scoring Model'!$B$10+N8/5*'Scoring Model'!$B$11)*100 | H8: 5 | I8: 4 | J8: 4 | K8: 3 | L8: 3 | M8: 4 | N8: 4 | O8: Proprietary POS; internal report indicates a global Genius KDS deployment, replacing the prior DMB assumption | P8: Fragmented global/franchise estate; existing Genius relationship requires verification | Q8: Product, site coverage, ownership and commitments unresolved | R8: Existing Genius KDS scope verification + relationship map | S8: Confirm the Genius product owner, KDS sites, deployment status, commitments and customer sponsor before proposing any additional adjacency. | T8: Proprietary; FreedomPay; Ingenico; Genius KDS (reported internally, unverified) | U8: Ryan Hildebrand described proprietary POS plus a global Genius KDS deployment. Reconcile that internal view with prior DMB reporting. | V8: High internal intelligence / exact scope unresolved
A9: 5 | B9: P2 | C9: THE STEAK N SHAKE CO | D9: Maggie Lenhart | E9: Tier 2 | F9: 550 | G9: =(H9/5*'Scoring Model'!$B$5+I9/5*'Scoring Model'!$B$6+J9/5*'Scoring Model'!$B$7+K9/5*'Scoring Model'!$B$8+L9/5*'Scoring Model'!$B$9+M9/5*'Scoring Model'!$B$10+N9/5*'Scoring Model'!$B$11)*100 | H9: 4 | I9: 4 | J9: 3 | K9: 4 | L9: 4 | M9: 4 | N9: 3 | O9: Kiosk transition and NCR reporting integration problems | P9: Transitioning adjacent stack | Q9: Current implementation pain | R9: Kiosk integration recovery + digital adjacency | S9: Name the kiosk vendor and owners; document certification, NCR reporting and mobile-app issues with dated remediation milestones. | T9: NCR; NCR Connected Payments; QikServe; Olo; NovaDine | U9: Maggie reports a difficult kiosk-vendor transition and integration/reporting issues with NCR. | V9: High RM intelligence
A10: 6 | B10: P2 | C10: CHOICE HOTELS | D10: Brian Wood | E10: Tier 2 | G10: =(H10/5*'Scoring Model'!$B$5+I10/5*'Scoring Model'!$B$6+J10/5*'Scoring Model'!$B$7+K10/5*'Scoring Model'!$B$8+L10/5*'Scoring Model'!$B$9+M10/5*'Scoring Model'!$B$10+N10/5*'Scoring Model'!$B$11)*100 | H10: 3 | I10: 5 | J10: 3 | K10: 4 | L10: 4 | M10: 3 | N10: 5 | O10: Gateway/acquiring RFP was active in July; current stage and deadlines now require refresh | P10: Deconverting | Q10: Shift4 performance concern reported | R10: Payments win-back + hospitality adjacency | S10: Confirm whether the RFP remains active, current stage, decision dates, retained Worldpay estate, sponsor and restaurant/DMB scope. | T10: Shift4 | U10: Brian and Brendan report an active RFP, remaining Worldpay locations and a possible full win-back. | V10: High RM intelligence / status aging
A11: 7 | B11: P2 | C11: RDS FIVE-UNIT REBRAND PILOT | D11: RDS / Darren Heinze | E11: Channel pilot | F11: 5 | G11: =(H11/5*'Scoring Model'!$B$5+I11/5*'Scoring Model'!$B$6+J11/5*'Scoring Model'!$B$7+K11/5*'Scoring Model'!$B$8+L11/5*'Scoring Model'!$B$9+M11/5*'Scoring Model'!$B$10+N11/5*'Scoring Model'!$B$11)*100 | H11: 2 | I11: 4 | J11: 4 | K11: 4 | L11: 3 | M11: 5 | N11: 5 | O11: Five former Taco Cabana locations are rebranding and evaluating a clean-slate stack and digital menu boards | P11: Clean-slate conversion; opening and conversion dates unconfirmed | Q11: High channel access; commercial, support and account-protection model not yet defined | R11: RDS-led Genius pilot and reseller proof | S11: Confirm entity/concept, authority, dates, budget and incumbent contracts; define scope, economics, support, success metrics and case-study rights before Genius World. | T11: To be determined: Genius POS/payments; DMB; drive-thru; loyalty; back office; hardware | U11: RDS is authorized to resell Genius but lacks implementation experience. The pilot can create channel proof before any larger protected-account motion. | V11: High field confidence / customer facts require documentation
A12: 8 | B12: P2 | C12: POLLO CAMPERO | D12: Unassigned / Worldpay | E12: Emerging strategic | F12: 150 | G12: =(H12/5*'Scoring Model'!$B$5+I12/5*'Scoring Model'!$B$6+J12/5*'Scoring Model'!$B$7+K12/5*'Scoring Model'!$B$8+L12/5*'Scoring Model'!$B$9+M12/5*'Scoring Model'!$B$10+N12/5*'Scoring Model'!$B$11)*100 | H12: 4 | I12: 4 | J12: 3 | K12: 3 | L12: 3 | M12: 4 | N12: 4 | O12: Potential RFI and DMB dissatisfaction; Oracle migration and referral status require immediate qualification | P12: Mixed NCR/Oracle estate; international platform decision may be underway | Q12: Decision openness, scope, deadlines and sponsor unconfirmed | R12: RFI qualification + international platform/payments/DMB | S12: Obtain NDA/RFI, confirm sponsor and deadlines, separate the stalled referral from the procurement stream, and apply country-by-country bid/no-bid gates. | T12: Oracle Simphony; NCR Aloha; Fiserv; Olo Pay/Stripe; Valutec; DMB incumbent unverified | U12: Split estate, reported $200M+ card volume and international footprint create strategic fit, but the Oracle decision may already be advanced. | V12: Strong internal brief / customer procurement not confirmed
A13: 9 | B13: P3 | C13: EAT'N PARK HOSPITALITY GRP INC | D13: Avery Churchwell | E13: Tier 2 | F13: 137 | G13: =(H13/5*'Scoring Model'!$B$5+I13/5*'Scoring Model'!$B$6+J13/5*'Scoring Model'!$B$7+K13/5*'Scoring Model'!$B$8+L13/5*'Scoring Model'!$B$9+M13/5*'Scoring Model'!$B$10+N13/5*'Scoring Model'!$B$11)*100 | H13: 3 | I13: 3 | J13: 2 | K13: 3 | L13: 3 | M13: 5 | N13: 4 | O13: Multi-concept conversion noted by Worldpay | P13: Mixed / transitioning | Q13: Unknown | R13: Consolidation and payments | S13: Separate stacks by concept and validate Oracle/FreedomPay/Tillster/Olo/Nextep ownership. | T13: Oracle Simphony; FreedomPay; Tillster; Olo; Nextep | V13: Internal baseline only
A14: 10 | B14: P3 | C14: FREDDY'S FROZEN CUSTARD LLC | D14: Avery Churchwell | E14: Tier 2 | F14: 500 | G14: =(H14/5*'Scoring Model'!$B$5+I14/5*'Scoring Model'!$B$6+J14/5*'Scoring Model'!$B$7+K14/5*'Scoring Model'!$B$8+L14/5*'Scoring Model'!$B$9+M14/5*'Scoring Model'!$B$10+N14/5*'Scoring Model'!$B$11)*100 | H14: 4 | I14: 3 | J14: 4 | K14: 1 | L14: 3 | M14: 3 | N14: 5 | O14: Protected RDS account with no verified displacement event. Avery invited Freddy's contacts to the FSTEC happy hour but had received no response as of September 4. | P14: Established PAR via RDS; protected channel relationship | Q14: No verified displacement event; RDS has deep operational and CFO access | R14: RDS-led value review and modular watchlist | S14: Keep all activity RDS-led. Confirm whether RDS connected with Ryan after Genius World, identify any FSTEC attendance, and wait for a customer-defined business problem before advancing a value case. | T14: PAR Brink via RDS; Olo Pay; Creative Realities DMB; Neon entry reported, unverified | U14: Avery and Todd agreed that RDS is the strongest coordinated route into Freddy's. Todd had previously discussed Genius with RDS at the Freddy's show; an RDS contact attended Genius World, but follow-through with Ryan still needed confirmation. | V14: High RM/channel intelligence dated 2026-09-04 / no active customer buying trigger verified
A15: 11 | B15: P3 | C15: PAPA JOHN'S USA, INC. | D15: Brian Wood | E15: Tier 1 | F15: 3300 | G15: =(H15/5*'Scoring Model'!$B$5+I15/5*'Scoring Model'!$B$6+J15/5*'Scoring Model'!$B$7+K15/5*'Scoring Model'!$B$8+L15/5*'Scoring Model'!$B$9+M15/5*'Scoring Model'!$B$10+N15/5*'Scoring Model'!$B$11)*100 | H15: 5 | I15: 3 | J15: 3 | K15: 1 | L15: 2 | M15: 4 | N15: 2 | O15: PAR POS + OPS implementation begins in 2026; rollout through 2027; Linux-build dependency reported but unverified | P15: Newly selected / deploying | Q15: PAR reports milestones on track; watch implementation and technical dependencies | R15: DMB adjacency + implementation-risk watch | S15: Map DMB and adjacent owners; monitor implementation milestones and validate the reported Linux-build dependency without positioning POS displacement. | T15: PAR POS; PAR OPS; legacy Mainstreet Monetra; Ingenico | U15: PAR publicly reports development progress and implementation later in 2026. The Linux requirement is confidential field intelligence requiring technical validation. | V15: High public evidence + unverified technical-risk lead
A16: 12 | B16: P3 | C16: CRACKER BARREL OLD COUNTRY STORE, INC. | D16: Brian Wood | E16: Tier 2 | F16: 600 | G16: =(H16/5*'Scoring Model'!$B$5+I16/5*'Scoring Model'!$B$6+J16/5*'Scoring Model'!$B$7+K16/5*'Scoring Model'!$B$8+L16/5*'Scoring Model'!$B$9+M16/5*'Scoring Model'!$B$10+N16/5*'Scoring Model'!$B$11)*100 | H16: 4 | I16: 3 | J16: 3 | K16: 2 | L16: 3 | M16: 3 | N16: 3 | O16: Oracle Simphony rollout continuing in 2026 | P16: Deploying / transition | Q16: Early field adoption signals; verify | R16: Adjacent stack and deployment support | S16: Confirm rollout completion, FreedomPay scope, operational issues and remaining adjacent gaps. | T16: Oracle Simphony; FreedomPay; Olo | V16: Mixed / see ledger
A17: 13 | B17: P3 | C17: MILLLER'S ALE HOUSE | D17: Avery Churchwell | E17: Tier 2 | F17: 112 | G17: =(H17/5*'Scoring Model'!$B$5+I17/5*'Scoring Model'!$B$6+J17/5*'Scoring Model'!$B$7+K17/5*'Scoring Model'!$B$8+L17/5*'Scoring Model'!$B$9+M17/5*'Scoring Model'!$B$10+N17/5*'Scoring Model'!$B$11)*100 | H17: 3 | I17: 3 | J17: 2 | K17: 4 | L17: 3 | M17: 3 | N17: 4 | O17: Digital payments moved direct to Olo | P17: Established POS; recent digital payment change | Q17: Unknown | R17: In-store POS/payments and guest experience | S17: Confirm lost scope, NCR renewal, Ziosk footprint and remaining payments opportunity. | T17: NCR; Ziosk; Olo Pay | V17: Internal baseline only
A18: 14 | B18: P3 | C18: LAROSA'S INC | D18: Maggie Lenhart | E18: Tier 2 | F18: 76 | G18: =(H18/5*'Scoring Model'!$B$5+I18/5*'Scoring Model'!$B$6+J18/5*'Scoring Model'!$B$7+K18/5*'Scoring Model'!$B$8+L18/5*'Scoring Model'!$B$9+M18/5*'Scoring Model'!$B$10+N18/5*'Scoring Model'!$B$11)*100 | H18: 2 | I18: 3 | J18: 2 | K18: 4 | L18: 3 | M18: 4 | N18: 3 | O18: Possible EMV modernization gap | P18: Mature / niche POS | Q18: Unknown | R18: EMV, payments and enterprise modernization | S18: Validate POS.Cloud contract, non-EMV exposure, franchise scope and replacement appetite. | T18: Point of Sale.Cloud; Mainstreet Monetra; triPOS | V18: Internal baseline only
A19: 15 | B19: P3 | C19: CHURCHS CHICKEN 558 | D19: Maggie Lenhart | E19: Tier 2 | F19: 832 | G19: =(H19/5*'Scoring Model'!$B$5+I19/5*'Scoring Model'!$B$6+J19/5*'Scoring Model'!$B$7+K19/5*'Scoring Model'!$B$8+L19/5*'Scoring Model'!$B$9+M19/5*'Scoring Model'!$B$10+N19/5*'Scoring Model'!$B$11)*100 | H19: 4 | I19: 2 | J19: 2 | K19: 3 | L19: 2 | M19: 4 | N19: 3 | O19: Qu vs Oracle decision not officially communicated to Worldpay | P19: Established | Q19: Decision believed to favor Qu; verify | R19: DMB/drive-thru adjacency after POS verification | S19: Use Maggie to confirm the final POS decision and current payments integration before positioning an adjacency. | T19: Qu; Aurus; Olo; Bite | U19: Maggie reports Qu is assumed but not officially confirmed; leadership changes delayed clarity. | V19: High RM intelligence / unresolved
A20: 16 | B20: P3 | C20: GOLDEN CORRAL | D20: Maggie Lenhart | E20: Tier 2 | F20: 640 | G20: =(H20/5*'Scoring Model'!$B$5+I20/5*'Scoring Model'!$B$6+J20/5*'Scoring Model'!$B$7+K20/5*'Scoring Model'!$B$8+L20/5*'Scoring Model'!$B$9+M20/5*'Scoring Model'!$B$10+N20/5*'Scoring Model'!$B$11)*100 | H20: 4 | I20: 2 | J20: 2 | K20: 3 | L20: 2 | M20: 4 | N20: 3 | O20: No dated public trigger found | P20: Established / date unknown | Q20: Unknown | R20: Franchise payments + adjacent discovery | S20: Verify Qu start date, Aurus/Olo scopes, franchise penetration and contract dates. | T20: Qu; Aurus; Olo | V20: Internal baseline only
A21: 17 | B21: P3 | C21: Red Robin | D21: Avery Churchwell | E21: Tier 2 | F21: 500 | G21: =(H21/5*'Scoring Model'!$B$5+I21/5*'Scoring Model'!$B$6+J21/5*'Scoring Model'!$B$7+K21/5*'Scoring Model'!$B$8+L21/5*'Scoring Model'!$B$9+M21/5*'Scoring Model'!$B$10+N21/5*'Scoring Model'!$B$11)*100 | H21: 4 | I21: 2 | J21: 2 | K21: 4 | L21: 2 | M21: 3 | N21: 3 | O21: Avery sees signs that Red Robin may be in a better operating position and considers it a renewed prospecting possibility; no customer-confirmed buying event was disclosed. | P21: Mature mixed stack | Q21: Customer pressure; limited capital | R21: Pay-at-table replacement + payment savings | S21: Validate the improved-business-condition signal with current public results and direct RM knowledge, then confirm NCR term, Ziosk dissatisfaction, decision ownership and whether a pay-at-table/payment-savings discussion is timely. | T21: NCR Aloha; Ziosk; Olo; Monkey Media | U21: On September 4 Avery said recent reading suggested Red Robin was in a better spot and should be reconsidered as a possibility. This is a directional RM assessment, not a confirmed customer initiative. | V21: Medium RM assessment dated 2026-09-04 / customer trigger unverified
A22: 18 | B22: P3 | C22: BOB EVANS RESTAURANTS, LLC | D22: Brian Wood | E22: Tier 2 | F22: 450 | G22: =(H22/5*'Scoring Model'!$B$5+I22/5*'Scoring Model'!$B$6+J22/5*'Scoring Model'!$B$7+K22/5*'Scoring Model'!$B$8+L22/5*'Scoring Model'!$B$9+M22/5*'Scoring Model'!$B$10+N22/5*'Scoring Model'!$B$11)*100 | H22: 3 | I22: 2 | J22: 2 | K22: 4 | L22: 2 | M22: 4 | N22: 3 | O22: No dated primary-source trigger verified | P22: Established NCR estate | Q22: Unknown | R22: Aging POS and adjacent modernization | S22: Confirm earliest Aloha deployment/renewal and Connected Payments term. | T22: NCR Aloha; NCR Connected Payments | V22: Internal baseline only
A23: 19 | B23: P3 | C23: GRAETERS | D23: Maggie Lenhart | E23: Tier 2 | F23: 67 | G23: =(H23/5*'Scoring Model'!$B$5+I23/5*'Scoring Model'!$B$6+J23/5*'Scoring Model'!$B$7+K23/5*'Scoring Model'!$B$8+L23/5*'Scoring Model'!$B$9+M23/5*'Scoring Model'!$B$10+N23/5*'Scoring Model'!$B$11)*100 | H23: 2 | I23: 3 | J23: 3 | K23: 3 | L23: 2 | M23: 4 | N23: 3 | O23: Product segmentation clarified | P23: PAR non-enterprise deployment | Q23: No adverse signal | R23: Enterprise upgrade or adjacent stack | S23: Confirm PAR product/SKU, reseller, site coverage and enterprise gaps; test migration economics without misclassifying current state. | T23: PAR Brink (non-enterprise); Olo | U23: Graeter's is a PAR customer but not PAR Enterprise. | V23: Mixed / see ledger
A24: 20 | B24: P3 | C24: STARBUCKS CORPORATION | D24: Stacie Davis | E24: Tier 1 | F24: 10000 | G24: =(H24/5*'Scoring Model'!$B$5+I24/5*'Scoring Model'!$B$6+J24/5*'Scoring Model'!$B$7+K24/5*'Scoring Model'!$B$8+L24/5*'Scoring Model'!$B$9+M24/5*'Scoring Model'!$B$10+N24/5*'Scoring Model'!$B$11)*100 | H24: 5 | I24: 2 | J24: 2 | K24: 2 | L24: 2 | M24: 3 | N24: 4 | O24: Only partial Worldpay volume reported | P24: Proprietary / mature | Q24: Unknown | R24: Payments share expansion and hardware | S24: Quantify the 20% Worldpay footprint, renewal dates, licensed-store scope and Verifone lifecycle. | T24: Proprietary/VF PWC; Verifone | V24: Internal baseline only
A25: 21 | B25: P3 | C25: LITTLE CAESARS ENTERPRISE INC | D25: Avery Churchwell | E25: Tier 1 | F25: 4200 | G25: =(H25/5*'Scoring Model'!$B$5+I25/5*'Scoring Model'!$B$6+J25/5*'Scoring Model'!$B$7+K25/5*'Scoring Model'!$B$8+L25/5*'Scoring Model'!$B$9+M25/5*'Scoring Model'!$B$10+N25/5*'Scoring Model'!$B$11)*100 | H25: 5 | I25: 2 | J25: 2 | K25: 1 | L25: 2 | M25: 4 | N25: 3 | O25: Relationship is active enough for technical-support interaction, but commercial follow-up is stalled: Avery reported three open items and no response to repeated emails for roughly a week and a half. | P25: Proprietary / entrenched | Q25: Unknown | R25: Payments, DMB, franchise and data adjacency | S25: Use the existing technical-support interaction to re-establish responsiveness, consolidate the three outstanding requests into one owner/action list, and map CaesarVision, payments renewal, DMB and franchise exceptions without leading with generic POS displacement. | T25: CaesarVision; Verifone; Mashgin | U25: Avery reported three items awaiting follow-up and no response to emails for approximately 1.5 weeks, despite participating in a technical-support call with the account earlier that week. | V25: High RM interaction evidence dated 2026-09-04 / commercial trigger unverified
A26: 22 | B26: P3 | C26: BLACK BEAR DINER | D26: Avery Churchwell | E26: Tier 2 | F26: 217 | G26: =(H26/5*'Scoring Model'!$B$5+I26/5*'Scoring Model'!$B$6+J26/5*'Scoring Model'!$B$7+K26/5*'Scoring Model'!$B$8+L26/5*'Scoring Model'!$B$9+M26/5*'Scoring Model'!$B$10+N26/5*'Scoring Model'!$B$11)*100 | H26: 3 | I26: 3 | J26: 2 | K26: 2 | L26: 3 | M26: 3 | N26: 4 | O26: Transitioned toward Toast; Olo catering evidence | P26: Recently changed / deploying | Q26: Unknown | R26: Retain payments + adjacent gaps | S26: Confirm Toast deployment scope and whether Worldpay became unmanaged; map Olo modules and remaining corporate/franchise gaps. | T26: Toast; Olo | V26: Mixed / see ledger
A27: 23 | B27: P3 | C27: DOMINO'S PIZZA | D27: Stacie Davis | E27: Tier 1 | F27: 7000 | G27: =(H27/5*'Scoring Model'!$B$5+I27/5*'Scoring Model'!$B$6+J27/5*'Scoring Model'!$B$7+K27/5*'Scoring Model'!$B$8+L27/5*'Scoring Model'!$B$9+M27/5*'Scoring Model'!$B$10+N27/5*'Scoring Model'!$B$11)*100 | H27: 5 | I27: 2 | J27: 2 | K27: 1 | L27: 2 | M27: 3 | N27: 3 | O27: Proprietary estate; no open trigger verified | P27: Proprietary / entrenched | Q27: Unknown | R27: Payments, hardware and franchise adjacency | S27: Confirm ACI/Cybersource tenure, processor split and franchise technology control. | T27: Proprietary; ACI/Cybersource; Ingenico | V27: Internal baseline only
A28: 24 | B28: P3 | C28: FIREHOUSE RESTAURANT | D28: Brian Wood | E28: Tier 2 | F28: 1200 | G28: =(H28/5*'Scoring Model'!$B$5+I28/5*'Scoring Model'!$B$6+J28/5*'Scoring Model'!$B$7+K28/5*'Scoring Model'!$B$8+L28/5*'Scoring Model'!$B$9+M28/5*'Scoring Model'!$B$10+N28/5*'Scoring Model'!$B$11)*100 | H28: 4 | I28: 2 | J28: 2 | K28: 2 | L28: 2 | M28: 3 | N28: 3 | O28: Toast relationship appears strategic | P28: Established / strategic | Q28: No adverse signal | R28: Franchise payments and adjacent whitespace | S28: Confirm Toast modules and RBI governance; focus only on uncovered layers/franchise exceptions. | T28: Toast; eGiftify | V28: Internal baseline only
A29: 25 | B29: P3 | C29: BOYNE USA INC | D29: Avery Churchwell | E29: Tier 2 | F29: 17 | G29: =(H29/5*'Scoring Model'!$B$5+I29/5*'Scoring Model'!$B$6+J29/5*'Scoring Model'!$B$7+K29/5*'Scoring Model'!$B$8+L29/5*'Scoring Model'!$B$9+M29/5*'Scoring Model'!$B$10+N29/5*'Scoring Model'!$B$11)*100 | H29: 2 | I29: 2 | J29: 2 | K29: 3 | L29: 2 | M29: 4 | N29: 3 | O29: No trigger verified | P29: Established mixed hospitality stack | Q29: Unknown | R29: Resort commerce consolidation | S29: Map Agilysys, RTP, Mashgin and Flaik by venue/property; confirm renewal dates. | T29: Agilysys; RTP; FreedomPay; Mashgin; Flaik | V29: Internal baseline only
A30: 26 | B30: P3 | C30: SLIM CHICKENS | D30: Avery Churchwell | E30: Tier 2 | F30: 250 | G30: =(H30/5*'Scoring Model'!$B$5+I30/5*'Scoring Model'!$B$6+J30/5*'Scoring Model'!$B$7+K30/5*'Scoring Model'!$B$8+L30/5*'Scoring Model'!$B$9+M30/5*'Scoring Model'!$B$10+N30/5*'Scoring Model'!$B$11)*100 | H30: 3 | I30: 2 | J30: 2 | K30: 3 | L30: 1 | M30: 3 | N30: 2 | O30: Worldpay remains renewed through the reported three-year term. A Slim Chickens contact told Avery she plans to attend the FSTEC happy hour; RDS remains the required channel path. | P30: Established and expanding digital | Q30: Payments retained; Olo remains entrenched | R30: RDS-led relationship map; no active displacement trigger | S30: Avery to connect the attending Slim Chickens contact with Todd and the onsite Genius team for FSTEC; coordinate all follow-up with RDS and use the meeting to validate stakeholders and customer-defined modular needs, not to force a displacement pitch. | T30: PAR Brink; Olo Ordering/Dispatch/Rails/Switchboard/Sync | U30: Avery has a Slim Chickens contact expected at the FSTEC happy hour and will provide Genius attendee contact information because she will be in Europe. Todd is already working through RDS, which both parties agreed is the best joint route into Slim Chickens and Freddy's. | V30: High RM/channel intelligence dated 2026-09-04
A31: 27 | B31: P3 | C31: Barbara B Mann PAH | D31: Brian Wood | E31: Tier 2 | G31: =(H31/5*'Scoring Model'!$B$5+I31/5*'Scoring Model'!$B$6+J31/5*'Scoring Model'!$B$7+K31/5*'Scoring Model'!$B$8+L31/5*'Scoring Model'!$B$9+M31/5*'Scoring Model'!$B$10+N31/5*'Scoring Model'!$B$11)*100 | H31: 1 | I31: 2 | J31: 1 | K31: 3 | L31: 2 | M31: 5 | N31: 3 | O31: No trigger verified | P31: Unknown | Q31: Unknown | R31: Venue commerce discovery | S31: Resolve legal entity/venue scope and validate Cybersource/ecommerce footprint. | T31: Cybersource | V31: Internal baseline only
A32: 28 | B32: P3 | C32: STATION CASINO | D32: Avery Churchwell | E32: Tier 2 | F32: 18 | G32: =(H32/5*'Scoring Model'!$B$5+I32/5*'Scoring Model'!$B$6+J32/5*'Scoring Model'!$B$7+K32/5*'Scoring Model'!$B$8+L32/5*'Scoring Model'!$B$9+M32/5*'Scoring Model'!$B$10+N32/5*'Scoring Model'!$B$11)*100 | H32: 2 | I32: 2 | J32: 2 | K32: 3 | L32: 2 | M32: 3 | N32: 2 | O32: No trigger verified | P32: Established hospitality stack | Q32: Unknown | R32: Venue payments and commerce adjacency | S32: Validate Agilysys/FreedomPay contract dates and venue expansion plans. | T32: Agilysys; FreedomPay; OnDemand | V32: Internal baseline only
A33: 29 | B33: P3 | C33: LATRELLES MANAGEMENT CORP (Bullritos) | D33: Avery Churchwell | E33: Tier 2 | F33: 35 | G33: =(H33/5*'Scoring Model'!$B$5+I33/5*'Scoring Model'!$B$6+J33/5*'Scoring Model'!$B$7+K33/5*'Scoring Model'!$B$8+L33/5*'Scoring Model'!$B$9+M33/5*'Scoring Model'!$B$10+N33/5*'Scoring Model'!$B$11)*100 | H33: 1 | I33: 2 | J33: 2 | K33: 3 | L33: 2 | M33: 4 | N33: 2 | O33: No trigger verified | P33: Established NCR | Q33: Unknown | R33: Mid-market POS/payments modernization | S33: Validate current estate and buying authority. | T33: NCR Aloha; NCR Connected Payments | V33: Internal baseline only
A34: 30 | B34: P3 | C34: FESTIVA REAL ESTATE HOLDINGS | D34: Brian Wood | E34: Tier 2 | G34: =(H34/5*'Scoring Model'!$B$5+I34/5*'Scoring Model'!$B$6+J34/5*'Scoring Model'!$B$7+K34/5*'Scoring Model'!$B$8+L34/5*'Scoring Model'!$B$9+M34/5*'Scoring Model'!$B$10+N34/5*'Scoring Model'!$B$11)*100 | H34: 1 | I34: 2 | J34: 1 | K34: 3 | L34: 2 | M34: 4 | N34: 3 | O34: Formerly linked to Choice; no active trigger | P34: Established / unclear | Q34: Unknown | R34: Payments discovery | S34: Resolve entity relationship and current payment estate before pursuit. | T34: Shift4 and others | V34: Internal baseline only

Sheet Stack Intelligence
A1: Technology Stack Intelligence — 2026-08-14
A2: Vendor names are separated from verified deployment status. 'Unknown' means not yet verified, not whitespace.
A4: Account | B4: RM | C4: POS | D4: Payments / Gateway | E4: Digital / Ordering | F4: Loyalty / CRM | G4: Back Office / Labor / Inventory | H4: Kiosk / DMB | I4: KDS / Kitchen | J4: Drive-Thru | K4: Hardware | L4: Lifecycle | M4: Deployment Health | N4: Known Layers | O4: Unknown Layers | P4: Coverage % | Q4: Primary Opportunity | R4: Next Verification
A5: WENDY'S INTERNATIONAL INC | B5: Stacie Davis | C5: NCR Aloha | D5: ACI | E5: Yes | F5: Unknown | G5: Unknown | H5: Yes | I5: Unknown | J5: Unknown | K5: Ingenico, Variable | L5: Active decision / final stage | M5: 5 | N5: 4 | O5: 0.55555556 | P5: 0.55555556 | Q5: POS + payments platform capture | R5: War-room the decision: confirm owner, evaluation criteria, final meeting, commercials, product scope, franchise rollout and competitive gaps.
A6: DEL TACO LLC | B6: Maggie Lenhart | C6: NCR | D6: NCR Connected Payments | E6: OLO corporate | F6: Unknown | G6: Unknown | H6: Bite (Express) | I6: Unknown | J6: Unknown | K6: Worldpay extension; Yadav ownership-change integration window | L6: Strong access; sourcing event not confirmed | M6: 5 | N6: 4 | O6: 0.55555556 | P6: 0.44444444 | Q6: POS/payments + multi-brand consolidation | R6: Finish extension, consolidate leads, map Yadav governance and confirm sourcing event
A7: Dutch Bros | B7: Maggie Lenhart | C7: Genius (user intelligence); Xenial legacy baseline | D7: Verifone SCA Gateway | E7: Olo Order and Pay | F7: Paytronix / Dutch Rewards | G7: Unknown | H7: Unknown | I7: Unknown | J7: Core operating channel; vendor layer unknown | K7: Verifone e285 (Xenial iPads) | L7: Installed customer / expansion | M7: 5 | N7: 4 | O7: 0.55555556 | P7: 0.66666667 | Q7: Protect and expand Genius footprint | R7: Confirm Genius products, installed locations, adoption, support health, contract dates, attach rate and expansion path.
A8: Focus Brands (GoTo Foods) | B8: Brian Wood | C8: Qu (deploying) | D8: FreedomPay | E8: Olo / Qu integrations | F8: Unknown | G8: Qu integrates with third-party BOH; incumbent unknown | H8: DMB incumbent unknown | I8: Unknown | J8: Unknown | K8: Unknown | L8: Qu established since 2024 | M8: 3 | N8: 6 | O8: 0.33333333 | P8: 0.55555556 | Q8: DMB + multi-brand visual estate; payments defense | R8: Map DMB/CMS, screens, refresh timing and buying center by brand.
A9: SUBWAY | B9: Stacie Davis | C9: Proprietary POS | D9: FreedomPay | E9: Yes | F9: Unknown | G9: Unknown | H9: Genius KDS reported internally; exact sites/status unverified | I9: Unknown | J9: Unknown | K9: Fragmented global/franchise estate; existing Genius scope unresolved | L9: Product, ownership, locations and deployment status unverified | M9: 5 | N9: 4 | O9: 0.55555556 | P9: 0.55555556 | Q9: Verify existing Genius KDS relationship before any additional adjacency | R9: Confirm product owner, sites, status, commitments and sponsor
A10: FIVE GUYS | B10: Avery Churchwell | C10: PAR Brink (U.S.); NCR (EMEA) | D10: Worldpay; limited Global Payments EMEA; PAR Pay threat | E10: Olo Ordering + Engage | F10: Olo GDP/Marketing (not traditional points loyalty) | G10: CrunchTime (inventory, labor, ops) | H10: LineTen | I10: Unknown | J10: Unknown | K10: PAR renewal/evaluation window plausible; formal process and dates unconfirmed | L10: No verified failure; EMEA support gap requires validation | M10: 7 | N10: 2 | O10: 0.77777778 | P10: 0.77777778 | Q10: Pre-RFP shaping + internal transaction-metered POS feasibility | R10: Confirm evaluation type, renewal/notice dates, scope, sponsor and global requirements
A11: CHOICE HOTELS | B11: Brian Wood | C11: Shift4 | D11: Mixed acquirers; active Worldpay gateway/acquiring RFP | E11: Yes | F11: Unknown | G11: Unknown | H11: Unknown | I11: Unknown | J11: Unknown | K11: Unknown | L11: Deconversion incomplete; active win-back RFP | M11: 3 | N11: 6 | O11: 0.33333333 | P11: 0.22222222 | Q11: Payments win-back + hotel restaurant/DMB discovery | R11: Confirm RFP stage, retained properties, executive sponsor and venue technology scope.
A12: THE STEAK N SHAKE CO | B12: Maggie Lenhart | C12: NCR | D12: NCR Connected Payments | E12: Olo- moving to direct Express cert with NovaTab | F12: Unknown | G12: Unknown | H12: Kiosk vendor transition; integration problems | I12: Unknown | J12: Unknown | K12: Unknown | L12: Kiosk and mobile transition | M12: 4 | N12: 5 | O12: 0.44444444 | P12: 0.44444444 | Q12: Kiosk recovery + DMB/drive-thru/payments adjacency | R12: Identify kiosk vendor, certification issue, reporting gap, owners and remediation dates.
A13: FREDDY'S FROZEN CUSTARD LLC | B13: Avery Churchwell | C13: PAR Brink via RDS | D13: PAR Brink | E13: Olo / Olo Pay | F13: Unknown | G13: Creative Realities; Neon entry reported, unverified | H13: Unknown | I13: Unknown | J13: Unknown | K13: Protected PAR/RDS account; CIO reportedly reinforcing PAR | L13: No open event; RDS controls access | M13: 5 | N13: 4 | O13: 0.55555556 | P13: 0.44444444 | Q13: RDS-led modular value review only | R13: Prove RDS pilot and account protections before any Freddy's value discussion
A14: EAT'N PARK HOSPITALITY GRP INC | B14: Avery Churchwell | C14: FreedomPay, Tillster, Olo | D14: Oracle Simphony, PayMyTab, Catertrax | E14: Olo, Tillster (wallets), Nextep | F14: Unknown | G14: Unknown | H14: Unknown | I14: Unknown | J14: Unknown | K14: Desk 3500s, T650c | L14: Mixed / transitioning | M14: 4 | N14: 5 | O14: 0.44444444 | P14: 0.44444444 | Q14: Consolidation and payments | R14: Separate stacks by concept and validate Oracle/FreedomPay/Tillster/Olo/Nextep ownership.
A15: CRACKER BARREL OLD COUNTRY STORE, INC. | B15: Brian Wood | C15: RAFT 610 for POS, Express for OLO ISV for mobile, and eComm is on VAP. Moving to Oracle Symphony | D15: FreedomPay | E15: Yes | F15: Unknown | G15: Unknown | H15: Unknown | I15: Unknown | J15: Unknown | K15: Unknown | L15: Deploying / transition | M15: 3 | N15: 6 | O15: 0.33333333 | P15: 0.33333333 | Q15: Adjacent stack and deployment support | R15: Confirm rollout completion, FreedomPay scope, operational issues and remaining adjacent gaps.
A16: MILLLER'S ALE HOUSE | B16: Avery Churchwell | C16: NCR Connected Payments, Ziosk | D16: NCR, Ziosk | E16: OloPay | F16: Unknown | G16: Unknown | H16: Unknown | I16: Unknown | J16: Unknown | K16: Swipe Simple B250 & NCR Terminals | L16: Established POS; recent digital payment change | M16: 4 | N16: 5 | O16: 0.44444444 | P16: 0.44444444 | Q16: In-store POS/payments and guest experience | R16: Confirm lost scope, NCR renewal, Ziosk footprint and remaining payments opportunity.
... A34: FESTIVA REAL ESTATE HOLDINGS | B34: Brian Wood | C34: Shift4 & other | D34: Shift4 & other | E34: Yes | F34: Unknown | G34: Unknown | H34: Unknown | I34: Unknown | J34: Unknown | K34: Unknown | L34: Established / unclear | M34: 3 | N34: 6 | O34: 0.33333333 | P34: 0.33333333 | Q34: Payments discovery | R34: Resolve entity relationship and current payment estate before pursuit.
A35: POLLO CAMPERO | B35: Unassigned / Worldpay | C35: Oracle Simphony migration; NCR Aloha legacy | D35: Fiserv in-store; Olo Pay/Stripe digital | E35: Olo | F35: Current loyalty vendor unknown | G35: Unknown | H35: DMB incumbent/dissatisfaction reported | I35: Unknown | J35: Unknown | K35: Mixed estate / potential RFI | L35: Scope, decision openness and deadlines unverified | M35: 5 | N35: 4 | O35: 0.55555556 | P35: RFI qualification + international platform/payments/DMB | Q35: Obtain NDA/RFI and validate estate by country | R35: Confirm sponsor, deadlines, Oracle status, payment scope and DMB requirements
A36: RDS FIVE-UNIT REBRAND PILOT | B36: RDS / Darren Heinze | C36: To be determined | D36: Worldpay/Genius candidate | E36: Unknown | F36: Unknown | G36: Unknown | H36: Digital menu boards in evaluation | I36: Unknown | J36: Drive-thru sites | K36: Clean-slate rebrand / conversion | L36: Customer facts and commercial model unverified | M36: 4 | N36: 5 | O36: 0.44444444 | P36: RDS-led pilot and reseller proof | Q36: Confirm full phased-stack scope | R36: Confirm entity, authority, dates, budget, incumbent contracts and account-protection terms

Sheet Evidence Ledger
A1: Evidence Ledger — refreshed 2026-09-04
A2: Evidence type and confidence are explicit. User intelligence is high-priority field evidence but is not relabeled as public verification.
A4: Account | B4: Technology Layer | C4: Event Type | D4: Event Date | E4: Source / Publisher | F4: Evidence Summary | G4: Source URL or Reference | H4: Confidence | I4: Current-State Interpretation | J4: Research Date
A5: WENDY'S INTERNATIONAL INC | B5: Baseline stack | C5: Worldpay source | E5: Internal source | F5: Worldpay reports POS=NCR Aloha; ISV/payments=ACI; ecommerce=Yes. | G5: Worldpay_30_Account_Capture_Plan_v1.xlsx — Worldpay Source Snapshot | H5: Medium | I5: Baseline; requires current verification | J5: 2026-07-20
A6: WENDY'S INTERNATIONAL INC | B6: Field update | C6: User intelligence | D6: 46223 | E6: User-supplied | F6: Wendy’s is making a POS decision next week; Genius is in the mix. | G6: User field intelligence supplied for this analysis on 2026-07-20 | H6: High (user intelligence) | I6: Preserve separately from public verification | J6: 2026-07-20
A7: DEL TACO LLC | B7: Baseline stack | C7: Worldpay source | E7: Internal source | F7: Worldpay reports POS=NCR; ISV/payments=NCR Connected Payments; ecommerce=OLO corporate. | G7: Worldpay_30_Account_Capture_Plan_v1.xlsx — Worldpay Source Snapshot | H7: Medium | I7: Baseline; requires current verification | J7: 2026-07-20
A8: DEL TACO LLC | B8: Field update | C8: User intelligence | D8: 46223 | E8: User-supplied | F8: Del Taco has leads floating around Global Payments and status is needed. | G8: User field intelligence supplied for this analysis on 2026-07-20 | H8: High (user intelligence) | I8: Preserve separately from public verification | J8: 2026-07-20
A9: Dutch Bros | B9: Baseline stack | C9: Worldpay source | E9: Internal source | F9: Worldpay reports POS=Xenial Cloud POS; ISV/payments=Verifone SCA Gateway; ecommerce=OloPay, Braintree, Paytronix. | G9: Worldpay_30_Account_Capture_Plan_v1.xlsx — Worldpay Source Snapshot | H9: Medium | I9: Baseline; requires current verification | J9: 2026-07-20
A10: Dutch Bros | B10: Field update | C10: User intelligence | D10: 46223 | E10: User-supplied | F10: Dutch Bros is already a Genius customer. | G10: User field intelligence supplied for this analysis on 2026-07-20 | H10: High (user intelligence) | I10: Preserve separately from public verification | J10: 2026-07-20
A11: Focus Brands (GoTo Foods) | B11: Baseline stack | C11: Worldpay source | E11: Internal source | F11: Worldpay reports POS=FreedomPay (in-store), OLO (online), Monkey Media (catering), moving all to Qu; ISV/payments=FreedomPay; ecommerce=Yes. | G11: Worldpay_30_Account_Capture_Plan_v1.xlsx — Worldpay Source Snapshot | H11: Medium | I11: Baseline; requires current verification | J11: 2026-07-20
A12: Focus Brands (GoTo Foods) | B12: Field update | C12: User intelligence | D12: 46223 | E12: User-supplied | F12: Focus/GoTo Foods is a recent Qu win but deployment is taking longer than expected. | G12: User field intelligence supplied for this analysis on 2026-07-20 | H12: High (user intelligence) | I12: Preserve separately from public verification | J12: 2026-07-20
A13: SUBWAY | B13: Baseline stack | C13: Worldpay source | E13: Internal source | F13: Worldpay reports POS=Proprietary; ISV/payments=FreedomPay; ecommerce=Yes. | G13: Worldpay_30_Account_Capture_Plan_v1.xlsx — Worldpay Source Snapshot | H13: Medium | I13: Baseline; requires current verification | J13: 2026-07-20
A14: FIVE GUYS | B14: Baseline stack | C14: Worldpay source | E14: Internal source | F14: Worldpay reports POS=Par, Verifone SCA, Olo; ISV/payments=PAR; ecommerce=Olo. | G14: Worldpay_30_Account_Capture_Plan_v1.xlsx — Worldpay Source Snapshot | H14: Medium | I14: Baseline; requires current verification | J14: 2026-07-20
A15: FIVE GUYS | B15: Field update | C15: User intelligence | D15: 46223 | E15: User-supplied | F15: Five Guys is a very happy CrunchTime user; PAR signed a three-year POS extension about 2.25 years ago. | G15: User field intelligence supplied for this analysis on 2026-07-20 | H15: High (user intelligence) | I15: Preserve separately from public verification | J15: 2026-07-20
A16: CHOICE HOTELS | B16: Baseline stack | C16: Worldpay source | E16: Internal source | F16: Worldpay reports POS=Shift4; ISV/payments=unknown; ecommerce=Yes. | G16: Worldpay_30_Account_Capture_Plan_v1.xlsx — Worldpay Source Snapshot | H16: Medium | I16: Baseline; requires current verification | J16: 2026-07-20
A17: THE STEAK N SHAKE CO | B17: Baseline stack | C17: Worldpay source | E17: Internal source | F17: Worldpay reports POS=NCR; ISV/payments=NCR Connected Payments; ecommerce=Olo- moving to direct Express cert with NovaTab. | G17: Worldpay_30_Account_Capture_Plan_v1.xlsx — Worldpay Source Snapshot | H17: Medium | I17: Baseline; requires current verification | J17: 2026-07-20
A18: FREDDY'S FROZEN CUSTARD LLC | B18: Baseline stack | C18: Worldpay source | E18: Internal source | F18: Worldpay reports POS=PAR Brink (VAR -Verifone Classic); ISV/payments=PAR Brink; ecommerce=OloPay. | G18: Worldpay_30_Account_Capture_Plan_v1.xlsx — Worldpay Source Snapshot | H18: Medium | I18: Baseline; requires current verification | J18: 2026-07-20
A19: FREDDY'S FROZEN CUSTARD LLC | B19: Field update | C19: User intelligence | D19: 46223 | E19: User-supplied | F19: Freddy's is a PAR customer sold through RDS. | G19: User field intelligence supplied for this analysis on 2026-07-20 | H19: High (user intelligence) | I19: Preserve separately from public verification | J19: 2026-07-20
A20: EAT'N PARK HOSPITALITY GRP INC | B20: Baseline stack | C20: Worldpay source | E20: Internal source | F20: Worldpay reports POS=FreedomPay, Tillster, Olo; ISV/payments=Oracle Simphony, PayMyTab, Catertrax; ecommerce=Olo, Tillster (wallets), Nextep. | G20: Worldpay_30_Account_Capture_Plan_v1.xlsx — Worldpay Source Snapshot | H20: Medium | I20: Baseline; requires current verification | J20: 2026-07-20
A21: CRACKER BARREL OLD COUNTRY STORE, INC. | B21: Baseline stack | C21: Worldpay source | E21: Internal source | F21: Worldpay reports POS=RAFT 610 for POS, Express for OLO ISV for mobile, and eComm is on VAP. Moving to Oracle Symphony; ISV/payments=FreedomPay; ecommerce=Yes. | G21: Worldpay_30_Account_Capture_Plan_v1.xlsx — Worldpay Source Snapshot | H21: Medium | I21: Baseline; requires current verification | J21: 2026-07-20
A22: MILLLER'S ALE HOUSE | B22: Baseline stack | C22: Worldpay source | E22: Internal source | F22: Worldpay reports POS=NCR Connected Payments, Ziosk; ISV/payments=NCR, Ziosk; ecommerce=OloPay. | G22: Worldpay_30_Account_Capture_Plan_v1.xlsx — Worldpay Source Snapshot | H22: Medium | I22: Baseline; requires current verification | J22: 2026-07-20
A23: LAROSA'S INC | B23: Baseline stack | C23: Worldpay source | E23: Internal source | F23: Worldpay reports POS=Point of Sale.Cloud; ISV/payments=Mainstreet Monetray, TriPOS; ecommerce=Same as instore. | G23: Worldpay_30_Account_Capture_Plan_v1.xlsx — Worldpay Source Snapshot | H23: Medium | I23: Baseline; requires current verification | J23: 2026-07-20
A24: CHURCHS CHICKEN 558 | B24: Baseline stack | C24: Worldpay source | E24: Internal source | F24: Worldpay reports POS=QuPOS; ISV/payments=Aurus; ecommerce=Olo. | G24: Worldpay_30_Account_Capture_Plan_v1.xlsx — Worldpay Source Snapshot | H24: Medium | I24: Baseline; requires current verification | J24: 2026-07-20
A25: GOLDEN CORRAL | B25: Baseline stack | C25: Worldpay source | E25: Internal source | F25: Worldpay reports POS=QuPOS; ISV/payments=Aurus; ecommerce=Olo. | G25: Worldpay_30_Account_Capture_Plan_v1.xlsx — Worldpay Source Snapshot | H25: Medium | I25: Baseline; requires current verification | J25: 2026-07-20
A26: Red Robin | B26: Baseline stack | C26: Worldpay source | E26: Internal source | F26: Worldpay reports POS=Ziosk, NCR Aloha and Olo for eCom; ISV/payments=NCR, Ziosk; ecommerce=Monkey Media, Olo, Bounteous (wallet). | G26: Worldpay_30_Account_Capture_Plan_v1.xlsx — Worldpay Source Snapshot | H26: Medium | I26: Baseline; requires current verification | J26: 2026-07-20
A27: BOB EVANS RESTAURANTS, LLC | B27: Baseline stack | C27: Worldpay source | E27: Internal source | F27: Worldpay reports POS=NCR Aloha/Connected Payments; ISV/payments=NCR Connected Payments; ecommerce=Yes. | G27: Worldpay_30_Account_Capture_Plan_v1.xlsx — Worldpay Source Snapshot | H27: Medium | I27: Baseline; requires current verification | J27: 2026-07-20
A28: GRAETERS | B28: Baseline stack | C28: Worldpay source | E28: Internal source | F28: Worldpay reports POS=Brink; ISV/payments=Brink Software; ecommerce=Olo. | G28: Worldpay_30_Account_Capture_Plan_v1.xlsx — Worldpay Source Snapshot | H28: Medium | I28: Baseline; requires current verification | J28: 2026-07-20
A29: GRAETERS | B29: Field update | C29: User intelligence | D29: 46223 | E29: User-supplied | F29: Graeter's is a PAR customer but not PAR Enterprise. | G29: User field intelligence supplied for this analysis on 2026-07-20 | H29: High (user intelligence) | I29: Preserve separately from public verification | J29: 2026-07-20
A30: STARBUCKS CORPORATION | B30: Baseline stack | C30: Worldpay source | E30: Internal source | F30: Worldpay reports POS=VF PWC; ISV/payments=unknown; ecommerce=Yes. | G30: Worldpay_30_Account_Capture_Plan_v1.xlsx — Worldpay Source Snapshot | H30: Medium | I30: Baseline; requires current verification | J30: 2026-07-20
A31: LITTLE CAESARS ENTERPRISE INC | B31: Baseline stack | C31: Worldpay source | E31: Internal source | F31: Worldpay reports POS=CaesarVision; ISV/payments=CaesarVision (via Verifone SCA); ecommerce=CaesarVision (via eProtect). | G31: Worldpay_30_Account_Capture_Plan_v1.xlsx — Worldpay Source Snapshot | H31: Medium | I31: Baseline; requires current verification | J31: 2026-07-20
A32: PAPA JOHN'S USA, INC. | B32: Baseline stack | C32: Worldpay source | E32: Internal source | F32: Worldpay reports POS=Mainstreet Monetra; ISV/payments=Mainstreet Monetra; ecommerce=Yes. | G32: Worldpay_30_Account_Capture_Plan_v1.xlsx — Worldpay Source Snapshot | H32: Medium | I32: Baseline; requires current verification | J32: 2026-07-20
A33: BLACK BEAR DINER | B33: Baseline stack | C33: Worldpay source | E33: Internal source | F33: Worldpay reports POS=Toast / Olo; ISV/payments=Toast; ecommerce=Olo. | G33: Worldpay_30_Account_Capture_Plan_v1.xlsx — Worldpay Source Snapshot | H33: Medium | I33: Baseline; requires current verification | J33: 2026-07-20
A34: DOMINO'S PIZZA | B34: Baseline stack | C34: Worldpay source | E34: Internal source | F34: Worldpay reports POS=Proprietary; ISV/payments=ACI/Cybersource; ecommerce=Yes. | G34: Worldpay_30_Account_Capture_Plan_v1.xlsx — Worldpay Source Snapshot | H34: Medium | I34: Baseline; requires current verification | J34: 2026-07-20
A35: FIREHOUSE RESTAURANT | B35: Baseline stack | C35: Worldpay source | E35: Internal source | F35: Worldpay reports POS=Toast; ISV/payments=Toast; ecommerce=Yes, CP No. | G35: Worldpay_30_Account_Capture_Plan_v1.xlsx — Worldpay Source Snapshot | H35: Medium | I35: Baseline; requires current verification | J35: 2026-07-20
A36: BOYNE USA INC | B36: Baseline stack | C36: Worldpay source | E36: Internal source | F36: Worldpay reports POS=FreedomPay; ISV/payments=Agilysys, RTP; ecommerce=Flaik. | G36: Worldpay_30_Account_Capture_Plan_v1.xlsx — Worldpay Source Snapshot | H36: Medium | I36: Baseline; requires current verification | J36: 2026-07-20
A37: SLIM CHICKENS | B37: Baseline stack | C37: Worldpay source | E37: Internal source | F37: Worldpay reports POS=PAR Brink (VAR - Verifone Classic) and Olo; ISV/payments=PAR Brink; ecommerce=Olo. | G37: Worldpay_30_Account_Capture_Plan_v1.xlsx — Worldpay Source Snapshot | H37: Medium | I37: Baseline; requires current verification | J37: 2026-07-20
A38: Barbara B Mann PAH | B38: Baseline stack | C38: Worldpay source | E38: Internal source | F38: Worldpay reports POS=Cybersource; ISV/payments=unknown; ecommerce=Yes. | G38: Worldpay_30_Account_Capture_Plan_v1.xlsx — Worldpay Source Snapshot | H38: Medium | I38: Baseline; requires current verification | J38: 2026-07-20
A39: STATION CASINO | B39: Baseline stack | C39: Worldpay source | E39: Internal source | F39: Worldpay reports POS=FreedomPay; ISV/payments=Agilysys; ecommerce=OnDemand. | G39: Worldpay_30_Account_Capture_Plan_v1.xlsx — Worldpay Source Snapshot | H39: Medium | I39: Baseline; requires current verification | J39: 2026-07-20
A40: LATRELLES MANAGEMENT CORP (Bullritos) | B40: Baseline stack | C40: Worldpay source | E40: Internal source | F40: Worldpay reports POS=NCR Aloha/Connected Payments; ISV/payments=NCR Aloha; ecommerce=unknown. | G40: Worldpay_30_Account_Capture_Plan_v1.xlsx — Worldpay Source Snapshot | H40: Medium | I40: Baseline; requires current verification | J40: 2026-07-20
A41: FESTIVA REAL ESTATE HOLDINGS | B41: Baseline stack | C41: Worldpay source | E41: Internal source | F41: Worldpay reports POS=Shift4 & other; ISV/payments=Shift4 & other; ecommerce=Yes. | G41: Worldpay_30_Account_Capture_Plan_v1.xlsx — Worldpay Source Snapshot | H41: Medium | I41: Baseline; requires current verification | J41: 2026-07-20
A42: Focus Brands (GoTo Foods) | B42: POS | C42: Selection | D42: 45351 | E42: Qu press release | F42: Selected Qu as single POS platform across all seven brands. | G42: https://www.qubeyond.com/resource-center/goto-foods-selects-qu-as-its-single-pos-platform-across-all-seven-brands | H42: High | I42: Deploying | J42: 2026-07-20
A43: Focus Brands (GoTo Foods) | B43: POS | C43: Deployment milestone | D43: 45931 | E43: Qu event recap | F43: GoTo Foods CTO reported more than 2,000 Qu installs; exact event date should be treated as publication-period evidence. | G43: https://www.qubeyond.com/lessons-from-restaurant-leaders-who-know-their-brands/ | H43: Medium | I43: Deploying; field intelligence reports delay | J43: 2026-07-20
A44: PAPA JOHN'S USA, INC. | B44: POS / Back Office | C44: Selection | D44: 46034 | E44: PAR press release | F44: Selected PAR POS and PAR OPS across about 3,200 U.S. restaurants; full rollout planned by end of 2027. | G44: https://partech.com/news-coverage/papa-johns-partners-with-par-technology-to-power-pos-and-ops-transformation-across-3200-u-s-restaurants/ | H44: High | I44: Newly selected / deploying | J44: 2026-07-20
A45: FIVE GUYS | B45: POS | C45: Original selection | D45: 42005 | E45: Trade coverage of PAR announcement | F45: Five Guys selected PAR Brink POS and associated hardware/services after franchisee-led evaluation. | G45: https://www.fastcasual.com/news/why-five-guys-selected-new-pos-solution-2/ | H45: Medium | I45: Mature incumbent | J45: 2026-07-20
A46: FIVE GUYS | B46: Back Office | C46: Customer case study | D46: 45701 | E46: Crunchtime | F46: Crunchtime describes a relationship originating around 2015 and expanded to 1,900+ locations; strong operating outcomes. | G46: https://www.crunchtime.com/blog/ops-excellence-awards-finalist-spotlight-five-guys | H46: High | I46: Entrenched and positive | J46: 2026-07-20
A47: FIVE GUYS | B47: Digital / Guest Data | C47: Expansion | E47: Olo case study | F47: Longtime Olo ordering customer expanded to GDP and Marketing across 1,500 locations. | G47: https://www.olo.com/case-studies/five-guys-engage | H47: High | I47: Entrenched and expanding | J47: 2026-07-20
A48: Dutch Bros | B48: Digital Ordering / Payments | C48: Selection | D48: 45419 | E48: Olo press release | F48: Selected Olo Order and Pay for nationwide rollout, initially across 850+ locations. | G48: https://investors.olo.com/news/news-details/2024/Dutch-Bros-Partners-with-Olo-to-Offer-Mobile-App-Ordering-and-Payment/default.aspx | H48: High | I48: Established | J48: 2026-07-20
A49: Dutch Bros | B49: Loyalty / CRM | C49: Customer case study | E49: Paytronix case study | F49: Dutch Rewards app and loyalty experience run on Paytronix. | G49: https://www.paytronix.com/hubfs/media/dutch_bros_case-study_v3.pdf | H49: High | I49: Established | J49: 2026-07-20
A50: CHURCHS CHICKEN 558 | B50: POS | C50: Selection | D50: 44245 | E50: Qu / Business Wire release | F50: Selected Qu as enterprise POS for approximately 1,000 U.S. locations. | G50: https://www.businesswire.com/news/home/20210218005023/en/Churchs-Chicken-Selects-Qu-POS-as-Part-of-Global-Technology-Stack-Refresh | H50: High | I50: Established | J50: 2026-07-20
A51: SLIM CHICKENS | B51: Digital Ordering | C51: Original launch | D51: 42736 | E51: Olo case study | F51: Launched Olo Ordering in 2017, added Dispatch, Rails and Switchboard, then Sync in 2022. | G51: https://www.olo.com/case-studies/slim-chickens | H51: High | I51: Entrenched and expanding | J51: 2026-07-20
A52: FREDDY'S FROZEN CUSTARD LLC | B52: POS | C52: Current customer evidence | D52: 45436 | E52: PAR customer announcement | F52: PAR identifies Freddy’s as a Brink POS customer. | G52: https://partech.com/2024/05/24/congratulations-to-par-customers-2024-fast-casual-movers-and-shakers-honorees/ | H52: High | I52: Established | J52: 2026-07-20
A53: BLACK BEAR DINER | B53: Digital / Catering | C53: Current customer evidence | E53: Olo case-study directory | F53: Olo lists Black Bear Diner as a catering customer story. | G53: https://www.olo.com/case-studies | H53: Medium | I53: Current public evidence | J53: 2026-07-20
A54: CRACKER BARREL OLD COUNTRY STORE, INC. | B54: Digital / Catering | C54: Current customer evidence | E54: Olo case-study directory | F54: Olo lists Cracker Barrel as a Catering+ customer story. | G54: https://www.olo.com/case-studies | H54: Medium | I54: Current public evidence | J54: 2026-07-20
A55: FREDDY'S FROZEN CUSTARD LLC | B55: Digital / Catering | C55: Current customer evidence | E55: Olo case-study directory | F55: Olo lists Freddy’s as a Catering+ customer story. | G55: https://www.olo.com/case-studies | H55: Medium | I55: Current public evidence | J55: 2026-07-20
A56: SUBWAY | B56: POS | C56: Deployment report | D56: 46149 | E56: Payments Dive | F56: Reported Genius adoption at about 2,500 Subway stores; requires internal confirmation of scope and status. | G56: https://www.paymentsdive.com/news/global-payments-touts-genius-gains/819560/ | H56: Medium | I56: Partial deployment / expansion | J56: 2026-07-20
A57: Portfolio | B57: Genius product scope | C57: Product launch | D57: 45793 | E57: Global Payments press release | F57: Genius launched as unified POS platform; restaurant edition launched first. | G57: https://investors.globalpayments.com/news-events/press-releases/detail/473/global-payments-launches-new-genius-pos-platform | H57: High | I57: Current product baseline | J57: 2026-07-20
A58: Portfolio | B58: Operating model | C58: Leadership feedback | D58: 46237 | E58: Ryan Hildebrand JPR | F58: Keep Blue Sheets; add Refine stage, RM economics, event access, account history and a payments capability map. | G58: system/account_intelligence/2026-08-03-ryan-hildebrand-worldpay-development-plan-feedback.md | H58: High | I58: Update the master-plan operating cadence | J58: 46248
A59: SUBWAY | B59: Genius scope | C59: Internal leadership feedback | D59: 46237 | E59: Ryan Hildebrand JPR | F59: Proprietary POS plus a reported global Genius KDS deployment conflicts with the prior DMB interpretation. | G59: system/account_intelligence/2026-08-03-ryan-hildebrand-worldpay-development-plan-feedback.md | H59: High internal / scope unverified | I59: Replace DMB assumption; keep conflict urgent | J59: 46248
A60: FIVE GUYS | B60: Buying event | C60: Field validation | D60: 46245 | E60: Jeff Staley JPR + independent checks | F60: Capability evaluation is plausible, but no formal RFP was found; MJ Worsham remains active and influential. | G60: system/account_intelligence/2026-08-11-jeff-staley-jpr-intelligence.md | H60: Mixed / independently checked | I60: Treat RFP and spring 2027 timing as unconfirmed | J60: 46248
A61: FIVE GUYS | B61: Commercial model | C61: Internal concept | D61: 46244 | E61: Worldpay/Genius executive concept | F61: Transaction-metered POS is an internal feasibility concept and is not approved for customer presentation. | G61: system/account_intelligence/2026-08-10-worldpay-transaction-funded-pos-executive-summary.md | H61: High internal | I61: Secure sponsorship and feasibility approval first | J61: 46248
A62: DEL TACO LLC | B62: Ownership | C62: Verified public event | D62: 46013 | E62: Jack in the Box investor release | F62: Yadav Enterprises completed the acquisition; active technology shopping remains unconfirmed. | G62: https://investors.jackinthebox.com/news/news-details/2025/Jack-in-the-Box-Inc--Completes-Sale-of-Del-Taco-Holdings-Inc-/default.aspx | H62: High | I62: Use ownership change for neutral discovery | J62: 46248
A63: FREDDY'S FROZEN CUSTARD LLC | B63: Channel / leadership | C63: RDS field intelligence | D63: 46247 | E63: Darren Heinze JPR | F63: RDS is deeply embedded; the new CIO reportedly favors PAR; Todd committed to no direct outreach. | G63: tmp/jpr-2026-08-13/2026-08-13-darren-heinze-rds-jpr-intelligence.md | H63: High field / decision unverified | I63: Downgrade to protected RDS watchlist | J63: 46248
A64: RDS FIVE-UNIT REBRAND PILOT | B64: Channel pilot | C64: RDS field intelligence | D64: 46247 | E64: Darren Heinze JPR | F64: Five former Taco Cabana sites are rebranding and evaluating a clean-slate stack/DMB; customer details require confirmation. | G64: tmp/jpr-2026-08-13/2026-08-13-darren-heinze-rds-jpr-intelligence.md | H64: High field / documentation required | I64: Qualify as the preferred near-term channel pilot | J64: 46248
A65: SLIM CHICKENS | B65: Channel rule | C65: RDS field intelligence | D65: 46247 | E65: Darren Heinze JPR | F65: Remain RDS-led; no direct outreach and no new buying event surfaced. | G65: tmp/jpr-2026-08-13/2026-08-13-darren-heinze-rds-jpr-intelligence.md | H65: High field | I65: Keep as relationship-map account | J65: 46248
A66: PAPA JOHN'S USA, INC. | B66: POS / Back Office | C66: PAR earnings evidence | D66: 46240 | E66: PAR Q2 2026 earnings materials | F66: Development milestones achieved; implementation expected later in 2026. Linux dependency is separate unverified field intelligence. | G66: https://partech.com/investor-relations/ | H66: High public / field detail unverified | I66: Monitor deployment and validate technical dependency | J66: 46248
A67: Portfolio | B67: Competitive pattern | C67: PAR earnings evidence | D67: 46240 | E67: PAR Q2 2026 earnings call | F67: PAR uses POS/loyalty beachheads, multi-product bundles and mandatory payments attachment on ordering wins. | G67: https://partech.com/investor-relations/ | H67: High company-reported | I67: Add platform/payment-attachment defense to account plans | J67: 46248
A68: POLLO CAMPERO | B68: POS / payments / DMB | C68: Internal account brief | D68: 46244 | E68: Pollo Campero account brief | F68: Oracle migration, NCR legacy, Fiserv in-store, Olo Pay/Stripe digital and potential RFI/DMB issues require qualification. | G68: system/account_intelligence/2026-08-10-pollo-campero-comprehensive-account-brief.md | H68: Strong internal / procurement unconfirmed | I68: Add as emerging opportunity with bid/no-bid gates | J68: 46248
A69: CHOICE HOTELS | B69: Gateway / acquiring | C69: Evidence aging | D69: 46248 | E69: Master-plan review | F69: July active-RFP intelligence now requires a current-stage and deadline refresh. | G69: Worldpay master-plan review 2026-08-14 | H69: Review finding | I69: Do not retain 'active RFP' without refresh | J69: 46248
... A74: LITTLE CAESARS ENTERPRISE INC | B74: Relationship access | C74: RM field update | D74: 46269.5 | E74: Avery Churchwell | F74: Three follow-up items remained unanswered after roughly 1.5 weeks, although Avery participated in a technical-support call with the account earlier that week. | G74: Avery Churchwell account update call, 2026-09-04 | H74: High (RM interaction) | I74: Use the support interaction to recover responsiveness and consolidate open requests. | J74: 46269.5
A85: DEL TACO LLC | C85: vendor_relationship_formed | D85: 2019-09-10 | F85: Del Taco Partners With Postmates To Bring Mexican And American Favorites Directly To Your Door - PR Newswire. Del Taco Partners With Postmates To Bring Mexican And American Favorites Directly To Your Door - PR Newswire | H85: RBB-detected | J85: 2026-09-02

Sheet Conflict Register
A1: Conflict & Verification Register — 2026-08-14
A2: Conflicts are preserved until resolved; newer evidence does not erase the historical source.
A4: Account | B4: Issue | C4: Incoming / Legacy View | D4: Newer Evidence | E4: Evidence Type | F4: Resolution Action | G4: Status
A5: PAPA JOHN'S USA, INC. | B5: Stale Worldpay opportunity | C5: Worldpay: evaluating gateway/POS | D5: PAR selected Jan. 12, 2026; rollout through 2027 | E5: Verified public fact | F5: Supersede open POS opportunity; monitor deployment and adjacency | G5: RESOLVED
A6: Focus Brands (GoTo Foods) | B6: Scope and deployment health | C6: Worldpay: moving all to Qu | D6: Qu confirms seven-brand POS selection; >2,000 installs; user reports rollout delay | E6: Verified + user intelligence | F6: Validate rollout pace and sources of delay without overstating failure | G6: OPEN
A7: WENDY'S INTERNATIONAL INC | B7: Ownership boundary | C7: Worldpay: NCR Aloha; user reported active decision | D7: Not an opportunity owned by Todd | E7: User correction | F7: Retain for intelligence only; no Todd pursuit action | G7: EXCLUDED
A8: DEL TACO LLC | B8: Duplicate/unowned leads | C8: Worldpay: NCR/Olo stack | D8: User: leads exist across Global Payments | E8: User intelligence | F8: Inventory and merge leads; assign owner and next action | G8: URGENT
A9: Dutch Bros | B9: Ownership boundary | C9: Worldpay: Xenial POS; user: existing Genius customer | D9: Managed by a Global Payments account manager; not Todd-owned | E9: User correction + public context | F9: Retain for intelligence only; account manager owns activity | G9: EXCLUDED
A10: FREDDY'S FROZEN CUSTARD LLC | B10: Channel posture and buying event | C10: P2 adjacency/international opportunity | D10: RDS-protected account; new CIO reportedly reinforcing PAR; no direct outreach | E10: High RDS field intelligence | F10: Downgrade to watchlist; prove the smaller RDS pilot first | G10: REFRAMED
A11: GRAETERS | B11: Product edition | C11: Worldpay: Brink | D11: User: PAR, but not Enterprise | E11: User intelligence | F11: Confirm SKU, reseller and enterprise migration fit | G11: OPEN
A12: FIVE GUYS | B12: Buying-event certainty and timing | C12: Spring 2027 RFP assumed; MJ departure reported | D12: Capability evaluation plausible; no formal RFP found; MJ remains active | E12: Field intelligence + independent check | F12: Confirm evaluation type, expiration/notice dates, sponsor, scope and decision criteria | G12: URGENT
A13: SUBWAY | B13: Genius product scope | C13: Prior record alternated between partial Genius POS and DMB | D13: Ryan reports proprietary POS plus global Genius KDS deployment; exact sites/status remain unverified | E13: Internal leadership intelligence | F13: Confirm product owner, KDS sites, deployment status, commitments and sponsor | G13: URGENT
A14: CHOICE HOTELS | B14: RFP status aging | C14: Active RFP reported in July | D14: No August stage/deadline refresh found | E14: RM intelligence aging | F14: Confirm current stage, dates, sponsor and retained estate | G14: URGENT
A15: PAPA JOHN'S USA, INC. | B15: Linux technical dependency | C15: PAR rollout tracked; no technical dependency recorded | D15: RDS claims Linux build is required; public sources do not confirm | E15: Confidential field intelligence | F15: Validate with technical/product owners; do not persist as fact | G15: OPEN
... A17: RDS FIVE-UNIT REBRAND PILOT | B17: Customer identity and authority | C17: Not present in prior portfolio | D17: Clean-slate rebrand offered as pilot; entity, concept and authority unconfirmed | E17: High channel field intelligence | F17: Document entity, authority, dates, budget, scope and protection terms | G17: URGENT

Sheet RM Portfolio
A1: RM Portfolio Briefings — 2026-09-04
A2: Opportunity counts exclude Wendy's and Dutch Bros. Protected channel accounts remain governed by RDS engagement rules.
A4: RM | B4: Opportunity Accounts | C4: P1 Accounts | D4: Average Score | E4: Top Ranked Accounts | F4: Trigger Summary | G4: Workshop Focus | H4: Required Output
A5: Avery Churchwell | B5: 11 | C5: 1 | D5: 57.1 | E5: FIVE GUYS, Red Robin, EAT'N PARK, MILLER'S ALE HOUSE, BLACK BEAR | F5: Five Guys outreach governance/FSTEC opening | Slim Chickens RDS-led FSTEC contact | Little Caesars follow-up stall | Red Robin reassessment | G5: Centralize Five Guys outreach with Avery/Todd; coordinate Slim Chickens and Freddy's through RDS; recover Little Caesars follow-ups; qualify Red Robin timing. | H5: Named owner and coordinated contact plan for each account; FSTEC connection plan; verified buying trigger, renewal dates and dated next action.
A6: Brian Wood | B6: 8 | C6: 1 | D6: 59.6 | E6: GoTo Foods, CHOICE HOTELS, PAPA JOHN'S, CRACKER BARREL, BOB EVANS | F6: GoTo platform/payment defense | Choice RFP refresh | Papa Johns rollout watch | G6: GoTo DMB map; Choice status refresh; Papa Johns adjacency and implementation monitoring | H6: Named account owner, current scope, decision dates, buying-center map and warm introduction.
A7: Maggie Lenhart | B7: 6 | C7: 1 | D7: 65.2 | E7: DEL TACO, STEAK N SHAKE, CHURCH'S, LAROSA'S, GOLDEN CORRAL | F7: Del Taco extension/Yadav event | Steak 'n Shake remediation | Church's decision unresolved | G7: Complete Del Taco extension and lead consolidation; establish dated kiosk remediation | H7: Verified buying event, owner map, technical issue owners and customer introduction.
A8: Stacie Davis | B8: 3 | C8: 1 | D8: 63 | E8: SUBWAY, STARBUCKS, DOMINO'S | F8: Subway KDS scope conflict | Starbucks share recovery | Domino's reference posture | G8: Resolve Subway product/sites/owner before any new positioning | H8: Confirmed Genius KDS scope, customer sponsor, commitments and next relationship.
A9: RDS / Darren Heinze | B9: 1 | C9: 0 | D9: 74 | E9: RDS FIVE-UNIT REBRAND PILOT | F9: Clean-slate pilot; protected-account operating model | G9: Document entity, scope, economics, support, protections and case-study rights | H9: Qualified customer facts, signed engagement rules and a dated pilot plan.
A10: Unassigned / Worldpay | B10: 1 | C10: 0 | D10: 72 | E10: POLLO CAMPERO | F10: Potential RFI; Oracle migration; split payment stack | G10: Assign owner, obtain NDA/RFI and apply bid/no-bid gates | H10: Named owner, procurement documents, timeline, country scope and decision openness.

Sheet Scoring Model
A1: Portfolio Scoring Model — 2026-08-14
A2: Score 1–5, then Refine after every material signal. Unknown is not whitespace; unverified triggers must not be scored as active decisions.
A4: Dimension | B4: Weight | C4: 1 = Low | D4: 3 = Medium | E4: 5 = High | F4: Interpretation
A5: Strategic Value | B5: 0.2 | C5: Small/low leverage | D5: Meaningful footprint | E5: Transformational scale | F5: Account size, tier, franchise leverage
A6: Active Buying Trigger | B6: 0.2 | C6: No trigger | D6: Research/discovery signal | E6: Active decision or internal lead | F6: Time-sensitive commercial motion
A7: Relationship / Access | B7: 0.15 | C7: No path | D7: Named RM/internal route | E7: Active customer access | F7: Ability to influence outcome
A8: Incumbent Lifecycle | B8: 0.15 | C8: New/locked | D8: Established or unclear | E8: Decision window/aging | F8: Switchability, not just age
A9: Deployment Health | B9: 0.1 | C9: Healthy/positive | D9: Unknown/mixed | E9: Material issue reported | F9: Crack signal or implementation need
A10: Adjacent Whitespace | B10: 0.15 | C10: Stack entrenched | D10: Some gaps | E10: Many verified/qualifiable gaps | F10: Unknown is not automatically whitespace
A11: Internal Coordination | B11: 0.05 | C11: Simple | D11: Several owners | E11: Urgent cross-team alignment | F11: Need to merge leads/owners/actions
A13: Formula
A14: Total Score | B14: SUM of each (dimension score ÷ 5 × dimension weight)
A15: Priority Bands | B15: P1 ≥ 78 | P2 65–77.9 | P3 < 65

Sheet Worldpay Source Snapshot
A1: Merchant | B1: DIrect ID | C1: Superchain/Corp Chain | D1: Franchise Code | E1: National Bank | F1: CP/Ecom | G1: Owner | H1: Vertical | I1: 2022 Jan-Sep | J1: 2022 Forecast | K1: Tier | L1: # of Locations | M1: % Corporated Owned | N1: % Franchise Owned. | O1: Int'l? | P1: RM | Q1: CSM | R1: PCO? | S1: Franchise Relationship Manager | T1: Notes | U1: POS | V1: ISV | W1: Terminals | X1: Kiosk | Y1: Ecommerce-Worldpay | Z1: Ecommerce-Other | AA1: Tier Adj (Susan) | AB1: Vertical Adj (James) | AC1: Tier Adj (James) | AD1: James | AE1: Notes.1 | AF1: Missing | AG1: Unnamed: 32 | AH1: Unnamed: 33 | AI1: Unnamed: 34 | AJ1: Unnamed: 35 | AK1: Unnamed: 36 | AL1: Unnamed: 37 | AM1: Unnamed: 38 | AN1: Unnamed: 39 | AO1: Unnamed: 40 | AP1: Unnamed: 41 | AQ1: Unnamed: 42 | AR1: Unnamed: 43 | AS1: Unnamed: 44
A2: Barbara B Mann PAH | F2: CP | G2: Susan | H2: Hospitality | J2: 398196 | K2: Tier 2 | O2: No | P2: Brian Wood | Q2: Ashlee Strete | U2: Cybersource | Y2: Yes | Z2: No
A3: BLACK BEAR DINER | B3: DRCT - 000639- VREL | C3: S000000058 | D3: BLCKBR | F3: CP | G3: Susan | H3: Hospitality | I3: 249980.04 | J3: 333306.72 | K3: Tier 2 | L3: 217 | M3: 0.6 | N3: 0.4 | O3: 0 | P3: Avery Churchwell | Q3: Michelle Weddington | R3: Melissa Douglas | S3: Gaynor Baker | T3: CP is moving to Toast, will likely move to unmanaged | U3: Toast / Olo | V3: Toast | W3: Toast | Y3: Olo
A4: BOB EVANS RESTAURANTS, LLC | C4: 000131 | F4: CP | G4: Susan | H4: Hospitality | I4: 310354.07 | J4: 413805.43 | K4: Tier 2 | L4: 450 | M4: 1 | N4: 0 | O4: No | P4: Brian Wood | Q4: Ashlee Strete | R4: Melissa Douglas | U4: NCR Aloha/Connected Payments | V4: NCR Connected Payments | Y4: Yes | Z4: No
A5: BOYNE USA INC | B5: DRCT - 000723- VREL | C5: SCBYNHGLDS | F5: CP | G5: Susan | H5: Hospitality | I5: 252196.4 | J5: 336261.87 | K5: Tier 2 | L5: 17 | M5: 1 | N5: 0 | O5: 0.05 | P5: Avery Churchwell | Q5: Michelle Weddington | R5: Melissa Douglas | T5: 1 Canadian location | U5: FreedomPay | V5: Agilysys, RTP | W5: Swipe Simple B250 & FB Terminals | X5: Mashgin | Y5: Flaik | AF5: MISSING
A6: CHOICE HOTELS | D6: CH2019 | F6: CP | G6: Susan | H6: Hospitality | I6: 1422373.6 | J6: 1896498.1 | K6: Tier 2 | M6: 0 | N6: 1 | O6: No | P6: Brian Wood | Q6: Michelle Weddington | T6: Deconverting | U6: Shift4 | Y6: Yes | Z6: No
A7: CHURCHS CHICKEN 558 | B7: DRCT - 006011- VREL | C7: S000002085, S000002083, SC0CHURCHA | D7: CHRCKN | E7: N000089 | F7: CP | G7: Susan | H7: Hospitality | I7: 658127.71 | J7: 877503.61 | K7: Tier 2 | L7: 832 | M7: 0.2 | N7: 0.8 | P7: Maggie Lenhart | Q7: Michelle Weddington | R7: Melissa Douglas | S7: Gaynor Baker | U7: QuPOS | V7: Aurus | W7: Lane 3000 | X7: Pilot with Bite (Express) | Y7: Olo
A8: CRACKER BARREL OLD COUNTRY STORE, INC. | C8: 0F6695, 0XX626 | F8: CP | G8: Susan | H8: Hospitality | I8: 775765.35 | J8: 1034353.8 | K8: Tier 2 | L8: 600 | M8: 1 | N8: 0 | O8: No | P8: Brian Wood | Q8: Michelle Weddington | R8: Melissa Douglas | T8: In Conversion for new POS with FP | U8: RAFT 610 for POS, Express for OLO ISV for mobile, and eComm is on VAP. Moving to Oracle Symphony | V8: FreedomPay | Y8: Yes | Z8: No
A9: DEL TACO LLC | B9: DRCT - 006020- VREL | C9: S000001636 | D9: DLTACO | F9: CP | G9: Susan | H9: Hospitality | I9: 559666.28 | J9: 746221.7 | K9: Tier 2 | L9: 537 | M9: 0.3 | N9: 0.7 | P9: Maggie Lenhart | Q9: Michelle Weddington | R9: Melissa Douglas | S9: Gaynor Baker | U9: NCR | V9: NCR Connected Payments | X9: Bite (Express) | Y9: OLO corporate | Z9: We don't have all Franchise locations. Multiple acquirers utilized. OloPay
A10: DOMINO'S PIZZA | B10: DRCT - 001429- VREL | C10: SCNDMNOPZA | E10: NDMNPZA | F10: CP | G10: Susan | H10: Hospitality | I10: 6034262.6 | J10: 8045683.5 | K10: Tier 1 | L10: 7000 | M10: 0.05 | N10: 0.95 | O10: Yes | P10: Stacie Davis | Q10: Greg Cappel | R10: Melissa Douglas | S10: Gaynor Baker | U10: Proprietary | V10: ACI/Cybersource | W10: Ingenico, Variable | X10: Yes | Y10: Yes
A11: Dutch Bros | B11: DRCT - 007676- VREL | C11: S000005309 | D11: DUTCHB | E11: N001348 | F11: CP | G11: Susan | H11: Hospitality | J11: 1400000 | K11: Tier 1 | L11: 1316 | M11: 0.72 | N11: 0.28 | P11: Maggie Lenhart | Q11: Michelle Weddington | R11: Melissa Douglas | S11: Gaynor Baker | U11: Xenial Cloud POS | V11: Verifone SCA Gateway | W11: Verifone e285 (Xenial iPads) | Z11: OloPay, Braintree, Paytronix
A12: EAT'N PARK HOSPITALITY GRP INC | B12: DRCT - 00073880 | C12: 72452 | F12: CP | G12: Susan | H12: Hospitality | I12: 235629.41 | J12: 314172.54 | K12: Tier 2 | L12: 137 | M12: 1 | N12: 0 | O12: 0 | P12: Avery Churchwell | Q12: Ashlee Strete | R12: Melissa Douglas | T12: Four concepts under EAPK - VAR is based on concept. Parkhurst was on IP but is converting to Core | U12: FreedomPay, Tillster, Olo | V12: Oracle Simphony, PayMyTab, Catertrax | W12: Desk 3500s, T650c | Y12: Olo, Tillster (wallets), Nextep
A13: FESTIVA REAL ESTATE HOLDINGS | C13: SCFESTIVAG | F13: CP | G13: Susan | H13: Hospitality | I13: 383181.43 | J13: 510908.58 | K13: Tier 2 | O13: No | P13: Brian Wood | Q13: Michelle Weddington | T13: Formerly part of Choice Hotels | U13: Shift4 & other | V13: Shift4 & other | Y13: Yes | Z13: No
A14: FIREHOUSE RESTAURANT | C14: SCFHSUBSCO | D14: FHSUBS | E14: NFHSUBS | F14: CP | G14: Susan | H14: Hospitality | I14: 646798.6 | J14: 862398.13 | K14: Tier 2 | L14: 1200 | M14: 0.1 | N14: 0.9 | O14: No | P14: Brian Wood | Q14: Greg Cappel | R14: Melissa Douglas | S14: Gaynor Baker | T14: GC in-store eGiftify via Toast | U14: Toast | V14: Toast | Y14: Yes, CP No | Z14: No
A15: FIVE GUYS | B15: DRCT - 001783- VREL | C15: S5GUYSFRAN/ 0M9131 | D15: 5GUYS | E15: NB5GUYS | F15: CP | G15: Susan | H15: Hospitality | I15: 1965606.7 | J15: 2620809 | K15: Tier 1 | L15: 1500 | M15: 0.4 | N15: 0.6 | O15: 0 | P15: Avery Churchwell | Q15: Ashlee Strete | R15: Melissa Douglas | S15: Anne-Marie Cloutier | T15: Int'l stores, not with WP | U15: Par, Verifone SCA, Olo | V15: PAR | W15: M400s | X15: LineTen | Y15: Olo
A16: Focus Brands (GoTo Foods) | D16: ANTANN - Auntie Anne's CARVEL - Carvel CINBON – Cinnabon CSWIRL – Cinnabon Swirl JAMBA - Jamba MCADEL - McAlister's MOESSW - Moe's SCHLKY - Schlotzsky's | E16: NCARVEL - Carvel NANTANN - Auntie Anne's NCINBON - Cinnabon CCSWIRL - Cinnabon Swirl N0JAMBA - Jamba NMCADEL - McAlister's NMOESSW - Moe's NSCHLKY - Schlotzsky's | F16: CP | G16: Susan | H16: Hospitality | I16: 493273.22 | J16: 657697.62 | K16: Tier 2 | L16: 2600 | N16: YES | O16: No | P16: Brian Wood | Q16: Ashlee Strete | R16: Melissa Douglas | S16: Anne-Marie Cloutier | T16: FreedomPay | U16: FreedomPay (in-store), OLO (online), Monkey Media (catering), moving all to Qu | V16: FreedomPay | X16: 8 MIDs have Verifone | Y16: Yes | Z16: No | AS16: 110000000
A17: FREDDY'S FROZEN CUSTARD LLC | B17: DRCT - 001867- VREL | C17: S000000027 | D17: FREFRO | E17: N001420 | F17: CP | G17: Susan | H17: Hospitality | I17: 261286.77 | J17: 348382.37 | K17: Tier 2 | L17: 500 | M17: 0.1 | N17: 0.9 | O17: 0 | P17: Avery Churchwell | Q17: Deb Cunningham | R17: Melissa Douglas | T17: Beginning to move to franchise pod | U17: PAR Brink (VAR -Verifone Classic) | V17: PAR Brink | W17: P400s and E285 | Z17: OloPay
A18: GOLDEN CORRAL | B18: DRCT - 006011- VREL | C18: SCGDCRFRAN, SCGOLDENCR, SCGDCRHOME | D18: GOLCOR | E18: NGOLCOR | F18: CP | G18: Susan | H18: Hospitality | I18: 752621.45 | J18: 1003495.3 | K18: Tier 2 | L18: 640 | M18: 0.01 | N18: 0.99 | P18: Maggie Lenhart | Q18: Michelle Weddington | R18: Melissa Douglas | S18: Gaynor Baker | U18: QuPOS | V18: Aurus | Y18: Olo
A19: GRAETERS | B19: DRCT - 002101- VREL | C19: S000006768 | F19: CP | G19: Susan | H19: Hospitality | I19: 283860.71 | J19: 378480.95 | K19: Tier 2 | L19: 67 | M19: 1 | N19: 0 | P19: Maggie Lenhart | Q19: Ashlee Strete | R19: Melissa Douglas | U19: Brink | V19: Brink Software | Y19: Olo
A20: LAROSA'S INC | B20: DRCT - 002844- VREL | C20: SCLAROSAZZ | F20: CP | G20: Susan | H20: Hospitality | I20: 364928.69 | J20: 486571.59 | K20: Tier 2 | L20: 76 | M20: 0.26 | N20: 0.74 | P20: Maggie Lenhart | Q20: Ashlee Strete | R20: Melissa Douglas | U20: Point of Sale.Cloud | V20: Mainstreet Monetray, TriPOS | W20: Varies-majority are non-EMV through Montera | Y20: Same as instore
A21: LATRELLES MANAGEMENT CORP (Bullritos) | B21: DRCT - 010312- VREL | C21: S0LATRELLE | F21: CP | G21: Susan | H21: Hospitality | I21: 241138.57 | J21: 321518.09 | K21: Tier 2 | L21: 35 | M21: 1 | N21: 0 | O21: 0 | P21: Avery Churchwell | Q21: Michelle Weddington | R21: Melissa Douglas | U21: NCR Aloha/Connected Payments | V21: NCR Aloha
A22: LITTLE CAESARS ENTERPRISE INC | B22: DRCT - 002926- VREL | C22: SCLITCSARS/ 071106 | D22: LCEI | E22: NLITCSR | F22: CP | G22: Susan | H22: Hospitality | I22: 4946098.5 | J22: 6594798 | K22: Tier 1 | L22: 4200 | M22: 0.1 | N22: 0.9 | O22: 0 | P22: Avery Churchwell | Q22: Ashlee Strete | R22: Sam Merkle | S22: Anne-Marie Cloutier | T22: Int'l stores, not with WP | U22: CaesarVision | V22: CaesarVision (via Verifone SCA) | W22: M400s and P400s | X22: Mashgin | Y22: CaesarVision (via eProtect)
A23: MILLLER'S ALE HOUSE | B23: DRCT - 00235448 | C23: 02131A | F23: CP | G23: Susan | H23: Hospitality | I23: 182432 | J23: 243243 | K23: Tier 2 | L23: 112 | M23: 1 | N23: 0 | O23: 0 | P23: Avery Churchwell | Q23: Michelle Weddington | R23: Melissa Douglas | T23: CNP has moved to Olo direct | U23: NCR Connected Payments, Ziosk | V23: NCR, Ziosk | W23: Swipe Simple B250 & NCR Terminals | Z23: OloPay
A24: PAPA JOHN'S USA, INC. | C24: SCPAPACORP/0T3849 | D24: PAPAJN & PAPCAD | E24: NPAPASJ, NPAPCAD | F24: CP | G24: Susan | H24: Hospitality | I24: 2382458.3 | J24: 3176611.1 | K24: Tier 1 | L24: 3300 | M24: 0.15 | N24: 0.85 | O24: Yes | P24: Brian Wood | Q24: Ashlee Strete | R24: Melissa Douglas | S24: Anne-Marie Cloutier | T24: Evaluating Gateway/POS options | U24: Mainstreet Monetra | V24: Mainstreet Monetra | W24: Ingenico Lane 3000/ipp320/Lane 3600 | Y24: Yes | Z24: No
A25: Red Robin | B25: IPP - 004107- VREL, IPP - 007950- IPREL, DRCT - 006112- VREL | C25: SCREDROBIN/0N1781 | D25: RRGB | F25: CP | G25: Susan | H25: Hospitality | J25: 315000 | K25: Tier 2 | L25: 500 | M25: 0.9 | N25: 0.1 | O25: 0 | P25: Avery Churchwell | Q25: Ashlee Strete | R25: Melissa Douglas | U25: Ziosk, NCR Aloha and Olo for eCom | V25: NCR, Ziosk | Y25: Monkey Media, Olo, Bounteous (wallet)
A26: SLIM CHICKENS | B26: DRCT - 007749- VREL | C26: S000004054 | D26: SLMCKN | E26: N001421 | F26: CP | G26: Susan | H26: Hospitality | K26: Tier 2 | L26: 250 | M26: 0.8 | N26: 0.2 | O26: 0 | P26: Avery Churchwell | Q26: Deb Cunningham | R26: Melissa Douglas | U26: PAR Brink (VAR - Verifone Classic) and Olo | V26: PAR Brink | W26: P400 and E285 | X26: PAR - Lane 300s | Y26: Olo
A27: STARBUCKS CORPORATION | B27: DRCT - 02432125 | C27: NSTBKUS | E27: NSTBKUS | F27: CP | G27: Susan | H27: Hospitality | I27: 28197.935 | J27: 4000000 | K27: Tier 1 | L27: 10000 | M27: 1 | N27: Licensed | O27: yes | P27: Stacie Davis | Q27: Greg Cappel | R27: Melissa Douglas | T27: only 20% volume comes to WP | U27: VF PWC | W27: Verifone, Variable | X27: Yes | Y27: Yes
A28: STATION CASINO | B28: DRCT - 010469- VREL | C28: S000008464 | F28: CP | G28: Susan | H28: Hospitality | K28: Tier 2 | L28: 18 | M28: 1 | N28: 0 | O28: 0 | P28: Avery Churchwell | Q28: Kat Briggs | R28: Melissa Douglas | U28: FreedomPay | V28: Agilysys | W28: FP Terminals | Y28: OnDemand
A29: SUBWAY | C29: NSUBWAY | D29: SBWYFR/SUBCAN | E29: NSUBUSA/NSUBCAN | F29: CP | H29: Hospitality | K29: Tier 1 | L29: 20000 | M29: 0 | N29: 1 | O29: Yes | P29: Stacie Davis | Q29: Greg Cappel | R29: TBD | S29: Gaynor Baker | T29: Dual acquirers via FreedomPay | U29: Proprietary | V29: FreedomPay | W29: Ingenico Desk 3500 | X29: Yes | Y29: Yes
A30: THE STEAK N SHAKE CO | B30: DRCT - 004673- VREL | C30: SCSTKNSHKE | D30: SKNK | E30: NSTKSHK | F30: CP | G30: Susan | H30: Hospitality | I30: 514334.96 | J30: 685779.95 | K30: Tier 2 | L30: 550 | M30: 0.83 | N30: 0.17 | P30: Maggie Lenhart | Q30: Michelle Weddington | R30: Melissa Douglas | S30: Gaynor Baker | U30: NCR | V30: NCR Connected Payments | X30: NCR-Moving to QikServe (FreedomPay) | Y30: Olo- moving to direct Express cert with NovaTab | Z30: Moving mobile app to Direct Express Cert with NovaTab
A31: WENDY'S INTERNATIONAL INC | B31: DRCT - 005449- VREL | C31: NWENDYS | D31: WENDYS | E31: NWENDYS | F31: CP | G31: Susan | H31: Hospitality | I31: 3462603.7 | J31: 4616804.9 | K31: Tier 1 | L31: 6000 | M31: 0.05 | N31: 0.95 | O31: Yes | P31: Stacie Davis | Q31: Greg Cappel | R31: Stacey Johnson | S31: Gaynor Baker | T31: ~10% of stores are on Fiserv | U31: NCR Aloha | V31: ACI | W31: Ingenico, Variable | X31: Yes | Y31: Yes

Sheet 2026-08-14 Change Log
A1: Worldpay Master Account Plan — 2026-09-04 Change Log
A2: Material changes through 2026-09-04. Validation items remain explicit; scores and tiers require human approval to change.
A4: Priority | B4: Account / Theme | C4: Change | D4: New Status | E4: Confidence | F4: Immediate Next Action | G4: Owner / Route | H4: Review By
A5: P1 | B5: Del Taco | C5: Added verified Yadav ownership event; sourcing remains a hypothesis | D5: Active / validate event | E5: High ownership; event unverified | F5: Finish extension, merge GP leads and map Yadav governance | G5: Maggie Lenhart | H5: 46255
A6: P1 | B6: Five Guys | C6: Removed certainty around formal spring 2027 RFP; added internal pricing feasibility gate | D6: Account shaping / validate | E6: Mixed | F6: Confirm evaluation, sponsor, renewal/notice dates and internal approval | G6: Avery Churchwell | H6: 46255
A7: P1 | B7: Subway | C7: Changed reported Genius scope from DMB to KDS | D7: Urgent scope verification | E7: High internal / scope unverified | F7: Confirm product owner, sites, status, commitments and sponsor | G7: Stacie Davis | H7: 46252
A8: P2 | B8: RDS five-unit rebrand | C8: Added clean-slate reseller pilot | D8: Qualify pilot | E8: High field / customer facts unverified | F8: Document entity, authority, scope, economics, support and protections | G8: RDS / Darren Heinze | H8: 46255
A9: P2 | B9: Pollo Campero | C9: Added emerging RFI/international platform opportunity | D9: Qualification / bid-no-bid | E9: Strong internal / procurement unconfirmed | F9: Obtain NDA/RFI, assign owner and confirm Oracle/Worldpay scope | G9: Unassigned / Worldpay | H9: 46255
A10: P3 | B10: Freddy's | C10: Downgraded from active P2 to protected RDS watchlist | D10: RDS-led / no direct outreach | E10: High field | F10: Prove pilot and protection model before CFO value discussion | G10: RDS | H10: 46269
A11: P3 | B11: Papa John's | C11: Corrected rank; added implementation milestones and Linux-risk lead | D11: Deployment/adjacency watch | E11: High public; technical claim unverified | F11: Monitor rollout and validate technical dependency | G11: Brian Wood | H11: 46262
A12: P3 | B12: Slim Chickens | C12: Codified RDS-led/no-direct-outreach rule; no new trigger | D12: Relationship map | E12: High field | F12: Wait for RDS-validated customer problem | G12: RDS / Avery | H12: 46269
A13: Portfolio | B13: PAR competitive signal | C13: Added POS/loyalty beachhead, multi-product bundling and payments-attachment pattern | D13: Portfolio-wide threat | E13: High company-reported | F13: Update discovery and battlecards; counter with modularity and proof | G13: Todd / Genius | H13: 46262
A14: Data quality | B14: Dashboard and rankings | C14: Corrected P1 count, RM mapping, Papa Johns rank and stack verification wording | D14: Resolved | E14: Verified workbook issue | F14: Use Ranked Portfolio as the source of truth | G14: Todd | H14: 46248
A15: P1 | B15: Five Guys | C15: Added outreach-governance risk, FSTEC status and internal funding-model guardrail | D15: Account shaping / coordinated access | E15: High RM; buying event unverified | F15: Centralize outreach through Todd and Avery; validate event and scope | G15: Todd / Avery Churchwell | H15: 46276.5
A16: P3 | B16: Slim Chickens | C16: Added confirmed FSTEC relationship opening | D16: RDS-led relationship mapping | E16: High RM | F16: Connect attendee with Genius team and coordinate through RDS | G16: Avery / Todd / RDS | H16: 46276.5
... A19: P3 | B19: Little Caesars | C19: Added stalled follow-up and active support-contact signal | D19: Relationship recovery | E19: High RM interaction | F19: Consolidate three open items and use support channel to re-engage | G19: Avery Churchwell | H19: 46276.5
