Workbook

Sheet Executive Summary
A1: Worldpay Master Account Plan — Executive Overview
A2: Updated 2026-09-30 | Prepared for the WP BackBook ICP Review
A4: Portfolio accounts | C4: Previously scored | E4: Supplemental additions | G4: Meeting-focus additions
A5: =COUNTA('Ranked Portfolio'!C5:C500) -> 115 | C5: =COUNT('Ranked Portfolio'!G5:G500) -> 30 | E5: =COUNTIF('Ranked Portfolio'!B5:B500,"Unranked") -> 85 | G5: =COUNTIF('Added Accounts Overview'!A5:A200,"A*") -> 18
A7: Meeting objective
A8: Agree which supplemental accounts belong in the enterprise ICP, assign an owner/RM path, and separate corporate chain opportunities from single-franchise or local merchant records.
A10: What changed
A11: The plan now accommodates 115 accounts: the original 30 scored opportunities plus 85 supplemental Worldpay backbook accounts. The supplemental rows now distinguish brand footprint from the exact WP merchant/entity footprint, use normalized operating segments, and explicitly flag Worldpay relationship ownership as unconfirmed until the WP team names an owner.
A13: Priority added-account themes
A14: 1) Scale: Buffalo Wild Wings and Culver’s are the clearest large-system additions. 2) Portfolio leverage: McAlister’s, Moe’s, Jamba and Carvel sit within GoTo Foods. 3) Regional scale: Ruby Tuesday, Logan’s Roadhouse, Fazoli’s, Sarku Japan, Chuy’s and Tijuana Flats warrant qualification. 4) Long tail: many LLC/franchisee records require entity and buying-authority validation before pursuit.
A17: Competitive / technology read
A18: Buffalo Wild Wings renewed NCR Voyix for POS in July 2025, so near-term POS displacement should not be assumed. Culver’s is recorded in RBB with PAR Brink. Fazoli’s has a PAR/Olo/Punchh stack on file. GoTo Foods brands should be coordinated as a platform-level motion rather than four unrelated cold pursuits.
A21: Decisions needed today
A22: • For every supplemental row, name the Worldpay relationship owner—even if that person is not the formal RM. • Confirm the merchant/legal entity and whether WP coverage is enterprise, franchisee, or single-site. • Validate location scope before using brand-wide counts for legal entities or numbered stores. • Select 5–10 accounts for full discovery; keep unresolved merchant records in qualification. • Confirm how attrition and dyssynergy flags should affect pursuit.
A27: Research discipline
A28: “Meeting focus” is a research-priority label, not a forecast or approved opportunity score. Facts are sourced from the Worldpay workbook, RBB ecosystem intelligence and cited public sources. Unknown buying events, contract dates and account ownership remain explicit qualification gaps.

Sheet Dashboard
A1: Worldpay Portfolio Dashboard
A2: 115-account portfolio | scored opportunities plus supplemental qualification targets
B4: Total accounts | E4: Scored portfolio | H4: Supplemental | K4: A-priority additions
B5: =COUNTA('Ranked Portfolio'!C5:C500) -> 115 | E5: =COUNT('Ranked Portfolio'!G5:G500) -> 30 | H5: =COUNTIF('Ranked Portfolio'!B5:B500,"Unranked") -> 85 | K5: =COUNTIF('Added Accounts Overview'!A5:A200,"A*") -> 18
B7: WP owner confirmed | E7: Public footprints refreshed | H7: Needs WP owner | K7: Entity/site records
B8: =COUNTIFS('Added Accounts Overview'!Q5:Q200,"<>Unconfirmed — ask Worldpay",'Added Accounts Overview'!Q5:Q200,"<>") -> 0 | E8: =COUNTIF('Added Accounts Overview'!L5:L200,"Public footprint refreshed*") -> 7 | H8: =COUNTIF('Added Accounts Overview'!Q5:Q200,"Unconfirmed — ask Worldpay") -> 85 | K8: =COUNTIF('Added Accounts Overview'!N5:N200,"Legal entity*") -> 29
B11: Added-account meeting priority | E11: Added accounts by segment
B12: A — Meeting focus | C12: =COUNTIF('Added Accounts Overview'!A5:A200,"A*") -> 18 | E12: Coffee | F12: =COUNTIF('Added Accounts Overview'!D5:D200,"Coffee") -> 0
B13: B — Qualify | C13: =COUNTIF('Added Accounts Overview'!A5:A200,"B*") -> 29 | E13: Burger | F13: =COUNTIF('Added Accounts Overview'!D5:D200,"Burger") -> 1
B14: C — Validate / deprioritize | C14: =COUNTIF('Added Accounts Overview'!A5:A200,"C*") -> 38 | E14: Mexican | F14: =COUNTIF('Added Accounts Overview'!D5:D200,"Mexican") -> 1
E15: Sandwich | F15: =COUNTIF('Added Accounts Overview'!D5:D200,"Sandwich") -> 1
E16: Family Dining | F16: =COUNTIF('Added Accounts Overview'!D5:D200,"Family Dining") -> 3
E17: Full-Service Dining | F17: =COUNTIF('Added Accounts Overview'!D5:D200,"Full-Service Dining") -> 1
E18: Pizza | F18: =COUNTIF('Added Accounts Overview'!D5:D200,"Pizza") -> 2
E19: Dessert | F19: =COUNTIF('Added Accounts Overview'!D5:D200,"Dessert") -> 1
E20: Other | F20: =COUNTA('Added Accounts Overview'!B5:B200)-SUM(F12:F19) -> 75
B23: Brand footprint and WP merchant footprint are separate fields. No supplemental account should be treated as owned until Worldpay names the relationship owner and confirms enterprise vs. franchisee/site scope.

Sheet Added Accounts Overview
A1: Worldpay Supplemental Accounts — Meeting Overview
A2: Prepared 2026-09-30 for WP BackBook ICP Review. Priority is research/meeting triage, not an approved sales score.
A4: Meeting Priority | B4: Account | C4: Source Relevance | D4: Sub-segment | E4: Technomic Rank | F4: Approx. Units | G4: Parent / Platform | H4: Research Summary | I4: Known Technology | J4: Worldpay Posture | K4: Recommended Next Action | L4: Research Status | M4: Source References | N4: Account Type | O4: Location Scope | P4: Location Confidence | Q4: WP Relationship Owner | R4: Internal Clarification Needed
A5: A — Meeting focus | B5: Buffalo Wild Wings | C5: Yes | D5: Family Dining | E5: 28 | F5: 1323 | G5: Inspire Brands | H5: Technomic rank 28; ~1,323 units. Family Dining account from Worldpay backbook. Platform/owner: Inspire Brands. | I5: POS: NCR Voyix partnership renewed July 2025; kds_kitchen_ops: Jolt | J5: Source-marked synergy fit | K5: Confirm Worldpay RM, processing scope and renewal dates; map enterprise technology owner and POS/payments decision window. | L5: Meeting-ready | M5: RBB ecosystem intelligence, 2026-09-30 | https://www.ncrvoyix.com/newsroom/buffalo-wild-wings-renews-partnership-with-ncr-voyix-as-partner-for-pos-platform | N5: Brand / chain | O5: Brand/system footprint from existing RBB research | P5: Medium | Q5: Unconfirmed — ask Worldpay | R5: Who at Worldpay owns this relationship, what merchant IDs/legal entities are in scope, and is coverage enterprise, franchisee, or a single site?
A6: A — Meeting focus | B6: Culver'S | C6: Yes | D6: Burger | E6: 29 | F6: 997 | G6: Culver Franchising System | H6: Technomic rank 29; ~997 units. Burger account from Worldpay backbook. Platform/owner: Culver Franchising System. | I6: POS: PAR Technology (Brink); POS Hardware: PAR; kds_kitchen_ops: Jolt | J6: Source-marked synergy fit; WP dyssynergy flag present | K6: Confirm Worldpay RM, processing scope and renewal dates; map enterprise technology owner and POS/payments decision window. | L6: Meeting-ready | M6: RBB ecosystem intelligence, 2026-09-30 | https://www.culvers.com/stories/signature-stories/culvers-locations-by-state | N6: Brand / chain | O6: Brand/system footprint from existing RBB research | P6: Medium | Q6: Unconfirmed — ask Worldpay | R6: Who at Worldpay owns this relationship, what merchant IDs/legal entities are in scope, and is coverage enterprise, franchisee, or a single site?
A7: A — Meeting focus | B7: Mcalisters Deli | C7: Yes | D7: Sandwich | E7: 59 | F7: 560 | G7: GoTo Foods | H7: Technomic rank 59; ~560 units. Sandwich account from Worldpay backbook. Platform/owner: GoTo Foods. | I7: Loyalty: PAR Technology (Punchh) | J7: Source-marked synergy fit | K7: Confirm Worldpay RM, processing scope and renewal dates; map enterprise technology owner and POS/payments decision window. | L7: Meeting-ready | M7: RBB ecosystem intelligence, 2026-09-30 | https://development.gotofoods.com/wp-content/uploads/2025/03/GTF_Digital_IncentiveBrochure2025.pdf | N7: Brand / chain | O7: Brand/system footprint from existing RBB research | P7: Medium | Q7: Unconfirmed — ask Worldpay | R7: Who at Worldpay owns this relationship, what merchant IDs/legal entities are in scope, and is coverage enterprise, franchisee, or a single site?
A8: A — Meeting focus | B8: Moes Southwest Grill | C8: Yes | D8: Mexican | E8: 78 | F8: 596 | G8: GoTo Foods | H8: Technomic rank 78; ~596 units. Mexican account from Worldpay backbook. Platform/owner: GoTo Foods. | I8: Loyalty: PAR Technology (Punchh); kiosks: Nextep Systems | J8: Source-marked synergy fit | K8: Confirm Worldpay RM, processing scope and renewal dates; map enterprise technology owner and POS/payments decision window. | L8: Meeting-ready | M8: RBB ecosystem intelligence, 2026-09-30 | https://development.gotofoods.com/wp-content/uploads/2025/03/GTF_Digital_IncentiveBrochure2025.pdf | N8: Brand / chain | O8: Brand/system footprint from existing RBB research | P8: Medium | Q8: Unconfirmed — ask Worldpay | R8: Who at Worldpay owns this relationship, what merchant IDs/legal entities are in scope, and is coverage enterprise, franchisee, or a single site?
A9: A — Meeting focus | B9: Chuy'S | C9: Yes | D9: Casual Dining — Mexican | E9: 110 | F9: 104 | H9: Technomic rank 110; ~104 units. Mexican account from Worldpay backbook. | I9: Back Office: PAR Technology (Data Central) | J9: Source-marked synergy fit | K9: Confirm Worldpay RM, processing scope and renewal dates; map enterprise technology owner and POS/payments decision window. | L9: Meeting-ready | M9: RBB ecosystem intelligence, 2026-09-30 | N9: Brand / chain | O9: Brand/system footprint from existing RBB research | P9: Medium | Q9: Unconfirmed — ask Worldpay | R9: Who at Worldpay owns this relationship, what merchant IDs/legal entities are in scope, and is coverage enterprise, franchisee, or a single site?
A10: A — Meeting focus | B10: Ruby Tuesday | C10: Yes | D10: Casual Dining | E10: 159 | F10: 212 | H10: Technomic rank 159; ~212 units. Full-Service Dining account from Worldpay backbook. | I10: No non-Worldpay technology verified | J10: Source-marked synergy fit; WP dyssynergy flag present | K10: Confirm Worldpay RM, processing scope and renewal dates; map enterprise technology owner and POS/payments decision window. | L10: Meeting-ready | M10: RBB ecosystem intelligence, 2026-09-30 | https://www.rubytuesday.com/locations/ | N10: Brand / chain | O10: Brand/system footprint from existing RBB research | P10: Medium | Q10: Unconfirmed — ask Worldpay | R10: Who at Worldpay owns this relationship, what merchant IDs/legal entities are in scope, and is coverage enterprise, franchisee, or a single site?
A11: A — Meeting focus | B11: Fazolis | C11: Yes | D11: Fast Casual — Italian | E11: 165 | F11: 196 | G11: FAT Brands | H11: Technomic rank 165; ~196 units. Family Dining account from Worldpay backbook. Platform/owner: FAT Brands. | I11: Online Ordering: Olo — Olo (historical scoped evidence); POS: PAR Technology (Brink); POS Hardware: PAR Technology (Hardware / Break Fix); Loyalty: PAR Technology (Punchh); drive_thru_ai: ConverseNow | J11: Source-marked synergy fit | K11: Confirm Worldpay RM, processing scope and renewal dates; map enterprise technology owner and POS/payments decision window. | L11: Meeting-ready | M11: RBB ecosystem intelligence, 2026-09-30 | https://ir.fatbrands.com/news/news-details/2025/Fazolis-Debuts-First-International-Location-in-Canada/default.aspx | N11: Brand / chain | O11: Brand/system footprint from existing RBB research | P11: Medium | Q11: Unconfirmed — ask Worldpay | R11: Who at Worldpay owns this relationship, what merchant IDs/legal entities are in scope, and is coverage enterprise, franchisee, or a single site?
A12: A — Meeting focus | B12: La Madeleine | C12: Yes | D12: Fast Casual — Bakery Café | E12: 213 | F12: 91 | H12: Technomic rank 213; ~91 units. Full-Service Dining account from Worldpay backbook. | I12: Online Ordering: Olo | J12: Source-marked synergy fit | K12: Confirm Worldpay RM, processing scope and renewal dates; map enterprise technology owner and POS/payments decision window. | L12: Meeting-ready | M12: RBB ecosystem intelligence, 2026-09-30 | N12: Brand / chain | O12: Brand/system footprint from existing RBB research | P12: Medium | Q12: Unconfirmed — ask Worldpay | R12: Who at Worldpay owns this relationship, what merchant IDs/legal entities are in scope, and is coverage enterprise, franchisee, or a single site?
A13: A — Meeting focus | B13: Sarku Japan | C13: Yes | D13: Fast Casual — Asian | E13: 261 | F13: 137 | H13: Technomic rank 261; ~137 units. Asian account from Worldpay backbook. | I13: No non-Worldpay technology verified | J13: Source-marked synergy fit | K13: Confirm Worldpay RM, processing scope and renewal dates; map enterprise technology owner and POS/payments decision window. | L13: Meeting-ready | M13: RBB ecosystem intelligence, 2026-09-30 | N13: Brand / chain | O13: Brand/system footprint from existing RBB research | P13: Medium | Q13: Unconfirmed — ask Worldpay | R13: Who at Worldpay owns this relationship, what merchant IDs/legal entities are in scope, and is coverage enterprise, franchisee, or a single site?
A14: A — Meeting focus | B14: Ben & Jerry'S | C14: Yes | D14: Dessert | E14: 363 | F14: 148 | H14: Technomic rank 363; ~148 units. Dessert account from Worldpay backbook. | I14: No non-Worldpay technology verified | J14: Source-marked synergy fit | K14: Confirm Worldpay RM, processing scope and renewal dates; map enterprise technology owner and POS/payments decision window. | L14: Meeting-ready | M14: RBB ecosystem intelligence, 2026-09-30 | N14: Brand / chain | O14: Brand/system footprint from existing RBB research | P14: Medium | Q14: Unconfirmed — ask Worldpay | R14: Who at Worldpay owns this relationship, what merchant IDs/legal entities are in scope, and is coverage enterprise, franchisee, or a single site?
A15: A — Meeting focus | B15: Honey Dew Donuts | C15: Yes | D15: Coffee / Bakery | E15: 577 | F15: 108 | H15: Technomic rank 577; ~108 units. Coffee account from Worldpay backbook. | I15: Loyalty: PAR Technology (Punchh) | J15: Source-marked synergy fit | K15: Confirm Worldpay RM, processing scope and renewal dates; map enterprise technology owner and POS/payments decision window. | L15: Meeting-ready | M15: RBB ecosystem intelligence, 2026-09-30 | N15: Brand / chain | O15: Brand/system footprint from existing RBB research | P15: Medium | Q15: Unconfirmed — ask Worldpay | R15: Who at Worldpay owns this relationship, what merchant IDs/legal entities are in scope, and is coverage enterprise, franchisee, or a single site?
A16: A — Meeting focus | B16: American Blue Ribbon Holdings | C16: Yes | D16: Restaurant Group / Platform | G16: Multi-brand operator | H16: Scale not yet verified. Family Dining account from Worldpay backbook. Platform/owner: Multi-brand operator. | I16: No non-Worldpay technology verified | J16: Source-marked synergy fit | K16: Confirm Worldpay RM, processing scope and renewal dates; map enterprise technology owner and POS/payments decision window. | L16: Partial | M16: RBB ecosystem intelligence, 2026-09-30 | N16: Restaurant group / platform | O16: WP merchant/entity footprint—not safe to infer from brand | P16: Needs WP confirmation | Q16: Unconfirmed — ask Worldpay | R16: Who at Worldpay owns this relationship, what merchant IDs/legal entities are in scope, and is coverage enterprise, franchisee, or a single site?
A17: A — Meeting focus | B17: Aurify Brands, Llc | C17: Yes | D17: Restaurant Group / Platform | G17: Multi-brand operator | H17: Scale not yet verified. Foodservice account from Worldpay backbook. Platform/owner: Multi-brand operator. | I17: No non-Worldpay technology verified | J17: Source-marked synergy fit | K17: Confirm Worldpay RM, processing scope and renewal dates; map enterprise technology owner and POS/payments decision window. | L17: Partial | M17: RBB ecosystem intelligence, 2026-09-30 | N17: Restaurant group / platform | O17: WP merchant/entity footprint—not safe to infer from brand | P17: Needs WP confirmation | Q17: Unconfirmed — ask Worldpay | R17: Who at Worldpay owns this relationship, what merchant IDs/legal entities are in scope, and is coverage enterprise, franchisee, or a single site?
A18: A — Meeting focus | B18: Caribou Coffee #1243 | C18: Yes | D18: Coffee & Beverage | F18: 800 | G18: JAB beverage platform | H18: Public footprint refreshed 2026-09-30; distinguish brand footprint from the exact WP merchant/entity scope. | I18: No non-Worldpay technology verified | J18: Source-marked synergy fit | K18: Confirm Worldpay RM, processing scope and renewal dates; map enterprise technology owner and POS/payments decision window. | L18: Public footprint refreshed; WP ownership open | M18: RBB ecosystem intelligence, 2026-09-30 | https://www.cariboucoffee.com/about-us/ | N18: Legal entity / franchisee / site record | O18: Global brand footprint; WP row may be one merchant/site | P18: Medium | Q18: Unconfirmed — ask Worldpay | R18: Who at Worldpay owns this relationship, what merchant IDs/legal entities are in scope, and is coverage enterprise, franchisee, or a single site?
A19: A — Meeting focus | B19: Carvel | C19: Yes | D19: Dessert / Ice Cream | F19: 374 | G19: GoTo Foods | H19: Public footprint refreshed 2026-09-30; distinguish brand footprint from the exact WP merchant/entity scope. | I19: No non-Worldpay technology verified | J19: Source-marked synergy fit | K19: Confirm Worldpay RM, processing scope and renewal dates; map enterprise technology owner and POS/payments decision window. | L19: Public footprint refreshed; WP ownership open | M19: RBB ecosystem intelligence, 2026-09-30 | https://development.gotofoods.com/wp-content/uploads/2025/03/GTF_Digital_IncentiveBrochure2025.pdf | https://locations.carvel.com/ | N19: Brand / chain | O19: U.S. brand footprint | P19: High | Q19: Unconfirmed — ask Worldpay | R19: Who at Worldpay owns this relationship, what merchant IDs/legal entities are in scope, and is coverage enterprise, franchisee, or a single site?
A20: A — Meeting focus | B20: Coffee Bean & Tea Leaf Ma | C20: Yes | D20: Coffee & Beverage | F20: 193 | G20: Jollibee Foods Corporation | H20: Public footprint refreshed 2026-09-30; distinguish brand footprint from the exact WP merchant/entity scope. | I20: No non-Worldpay technology verified | J20: Source-marked synergy fit | K20: Confirm Worldpay RM, processing scope and renewal dates; map enterprise technology owner and POS/payments decision window. | L20: Public footprint refreshed; WP ownership open | M20: RBB ecosystem intelligence, 2026-09-30 | https://www.coffeebean.com/store/index.html | N20: Brand / chain | O20: U.S. brand footprint | P20: High | Q20: Unconfirmed — ask Worldpay | R20: Who at Worldpay owns this relationship, what merchant IDs/legal entities are in scope, and is coverage enterprise, franchisee, or a single site?
A21: A — Meeting focus | B21: Jamba Juice | C21: Yes | D21: Juice / Smoothie | F21: 720 | G21: GoTo Foods | H21: Public footprint refreshed 2026-09-30; distinguish brand footprint from the exact WP merchant/entity scope. | I21: No non-Worldpay technology verified | J21: Source-marked synergy fit | K21: Confirm Worldpay RM, processing scope and renewal dates; map enterprise technology owner and POS/payments decision window. | L21: Public footprint refreshed; WP ownership open | M21: RBB ecosystem intelligence, 2026-09-30 | https://development.gotofoods.com/wp-content/uploads/2025/03/GTF_Digital_IncentiveBrochure2025.pdf | https://locations.jamba.com/ | N21: Brand / chain | O21: U.S. brand footprint | P21: High | Q21: Unconfirmed — ask Worldpay | R21: Who at Worldpay owns this relationship, what merchant IDs/legal entities are in scope, and is coverage enterprise, franchisee, or a single site?
A22: A — Meeting focus | B22: Peet'S Coffee & Tea | C22: Yes | D22: Coffee & Beverage | G22: JDE Peet's / JAB | H22: Scale not yet verified. Coffee account from Worldpay backbook. Platform/owner: JDE Peet's / JAB. | I22: No non-Worldpay technology verified | J22: Source-marked synergy fit | K22: Confirm Worldpay RM, processing scope and renewal dates; map enterprise technology owner and POS/payments decision window. | L22: Partial | M22: RBB ecosystem intelligence, 2026-09-30 | N22: Brand / chain | O22: Brand footprint not yet verified | P22: Needs research | Q22: Unconfirmed — ask Worldpay | R22: Who at Worldpay owns this relationship, what merchant IDs/legal entities are in scope, and is coverage enterprise, franchisee, or a single site?
A23: B — Qualify | B23: Shoneys | C23: Yes | D23: Family Dining | E23: 383 | F23: 57 | H23: Technomic rank 383; ~57 units. Family Dining account from Worldpay backbook. | I23: No non-Worldpay technology verified | J23: Source-marked synergy fit | K23: Validate corporate scale, buying authority, current POS/payments stack and whether the Worldpay relationship is enterprise or franchise-level. | L23: Meeting-ready | M23: RBB ecosystem intelligence, 2026-09-30 | N23: Brand / chain | O23: Brand/system footprint from existing RBB research | P23: Medium | Q23: Unconfirmed — ask Worldpay | R23: Who at Worldpay owns this relationship, what merchant IDs/legal entities are in scope, and is coverage enterprise, franchisee, or a single site?
A24: B — Qualify | B24: Fuddruckers | C24: Yes | D24: Fast Casual — Burger | E24: 505 | F24: 52 | H24: Technomic rank 505; ~52 units. Burger account from Worldpay backbook. | I24: back_office_operations: Crunchtime | J24: Source-marked synergy fit | K24: Validate corporate scale, buying authority, current POS/payments stack and whether the Worldpay relationship is enterprise or franchise-level. | L24: Meeting-ready | M24: RBB ecosystem intelligence, 2026-09-30 | N24: Brand / chain | O24: Brand/system footprint from existing RBB research | P24: Medium | Q24: Unconfirmed — ask Worldpay | R24: Who at Worldpay owns this relationship, what merchant IDs/legal entities are in scope, and is coverage enterprise, franchisee, or a single site?
A25: B — Qualify | B25: Gold Star Chili | C25: Yes | D25: QSR — Chili / Sandwich | E25: 517 | F25: 59 | H25: Technomic rank 517; ~59 units. Burger account from Worldpay backbook. | I25: POS: PAR Technology (Brink); pos: PAR Technology | J25: Source-marked synergy fit | K25: Validate corporate scale, buying authority, current POS/payments stack and whether the Worldpay relationship is enterprise or franchise-level. | L25: Meeting-ready | M25: RBB ecosystem intelligence, 2026-09-30 | N25: Brand / chain | O25: Brand/system footprint from existing RBB research | P25: Medium | Q25: Unconfirmed — ask Worldpay | R25: Who at Worldpay owns this relationship, what merchant IDs/legal entities are in scope, and is coverage enterprise, franchisee, or a single site?
A26: B — Qualify | B26: Scramblers | C26: Yes | D26: Family Dining / Breakfast | E26: 985 | F26: 28 | H26: Technomic rank 985; ~28 units. Family Dining account from Worldpay backbook. | I26: No non-Worldpay technology verified | J26: Source-marked synergy fit | K26: Validate corporate scale, buying authority, current POS/payments stack and whether the Worldpay relationship is enterprise or franchise-level. | L26: Partial | M26: RBB ecosystem intelligence, 2026-09-30 | N26: Brand / chain | O26: Brand/system footprint from existing RBB research | P26: Medium | Q26: Unconfirmed — ask Worldpay | R26: Who at Worldpay owns this relationship, what merchant IDs/legal entities are in scope, and is coverage enterprise, franchisee, or a single site?
A27: B — Qualify | B27: Bennigan'S | C27: Yes | D27: Casual Dining | E27: 1399 | F27: 6 | H27: Technomic rank 1399; ~6 units. Full-Service Dining account from Worldpay backbook. | I27: No non-Worldpay technology verified | J27: Source-marked synergy fit | K27: Validate corporate scale, buying authority, current POS/payments stack and whether the Worldpay relationship is enterprise or franchise-level. | L27: Partial | M27: RBB ecosystem intelligence, 2026-09-30 | N27: Brand / chain | O27: Brand/system footprint from existing RBB research | P27: Medium | Q27: Unconfirmed — ask Worldpay | R27: Who at Worldpay owns this relationship, what merchant IDs/legal entities are in scope, and is coverage enterprise, franchisee, or a single site?
A28: B — Qualify | B28: Tom & Chee | C28: Yes | D28: Fast Casual — Sandwich | E28: 1499 | F28: 7 | H28: Technomic rank 1499; ~7 units. Sandwich account from Worldpay backbook. | I28: No non-Worldpay technology verified | J28: Source-marked synergy fit | K28: Validate corporate scale, buying authority, current POS/payments stack and whether the Worldpay relationship is enterprise or franchise-level. | L28: Partial | M28: RBB ecosystem intelligence, 2026-09-30 | N28: Brand / chain | O28: Brand/system footprint from existing RBB research | P28: Medium | Q28: Unconfirmed — ask Worldpay | R28: Who at Worldpay owns this relationship, what merchant IDs/legal entities are in scope, and is coverage enterprise, franchisee, or a single site?
A29: B — Qualify | B29: Avi Foodsystems | C29: Yes | D29: Contract Foodservice | H29: Scale not yet verified. Foodservice account from Worldpay backbook. | I29: No non-Worldpay technology verified | J29: Source-marked synergy fit | K29: Validate corporate scale, buying authority, current POS/payments stack and whether the Worldpay relationship is enterprise or franchise-level. | L29: Partial | M29: RBB ecosystem intelligence, 2026-09-30 | N29: Brand / chain | O29: Brand footprint not yet verified | P29: Needs research | Q29: Unconfirmed — ask Worldpay | R29: Who at Worldpay owns this relationship, what merchant IDs/legal entities are in scope, and is coverage enterprise, franchisee, or a single site?
A30: B — Qualify | B30: Chateau Restaurant | C30: Yes | D30: Casual Dining — Italian | H30: Scale not yet verified. Full-Service Dining account from Worldpay backbook. | I30: No non-Worldpay technology verified | J30: Source-marked synergy fit | K30: Validate corporate scale, buying authority, current POS/payments stack and whether the Worldpay relationship is enterprise or franchise-level. | L30: Partial | M30: RBB ecosystem intelligence, 2026-09-30 | N30: Brand / chain | O30: Brand footprint not yet verified | P30: Needs research | Q30: Unconfirmed — ask Worldpay | R30: Who at Worldpay owns this relationship, what merchant IDs/legal entities are in scope, and is coverage enterprise, franchisee, or a single site?
A31: B — Qualify | B31: Cocula Restaurant | C31: Yes | D31: Casual Dining — Mexican | H31: Scale not yet verified. Mexican account from Worldpay backbook. | I31: No non-Worldpay technology verified | J31: Source-marked synergy fit | K31: Validate corporate scale, buying authority, current POS/payments stack and whether the Worldpay relationship is enterprise or franchise-level. | L31: Partial | M31: RBB ecosystem intelligence, 2026-09-30 | N31: Brand / chain | O31: Brand footprint not yet verified | P31: Needs research | Q31: Unconfirmed — ask Worldpay | R31: Who at Worldpay owns this relationship, what merchant IDs/legal entities are in scope, and is coverage enterprise, franchisee, or a single site?
A32: B — Qualify | B32: Creole Cuisine Restaurant | C32: Yes | D32: Restaurant Group / Platform | H32: Scale not yet verified. Full-Service Dining account from Worldpay backbook. | I32: No non-Worldpay technology verified | J32: Source-marked synergy fit | K32: Validate corporate scale, buying authority, current POS/payments stack and whether the Worldpay relationship is enterprise or franchise-level. | L32: Partial | M32: RBB ecosystem intelligence, 2026-09-30 | N32: Restaurant group / platform | O32: WP merchant/entity footprint—not safe to infer from brand | P32: Needs WP confirmation | Q32: Unconfirmed — ask Worldpay | R32: Who at Worldpay owns this relationship, what merchant IDs/legal entities are in scope, and is coverage enterprise, franchisee, or a single site?
A33: B — Qualify | B33: Cyclone Anaya | C33: Yes | D33: Casual Dining — Mexican | H33: Scale not yet verified. Mexican account from Worldpay backbook. | I33: No non-Worldpay technology verified | J33: Source-marked synergy fit | K33: Validate corporate scale, buying authority, current POS/payments stack and whether the Worldpay relationship is enterprise or franchise-level. | L33: Partial | M33: RBB ecosystem intelligence, 2026-09-30 | N33: Brand / chain | O33: Brand footprint not yet verified | P33: Needs research | Q33: Unconfirmed — ask Worldpay | R33: Who at Worldpay owns this relationship, what merchant IDs/legal entities are in scope, and is coverage enterprise, franchisee, or a single site?
A34: B — Qualify | B34: David'S Pizza | C34: Yes | D34: Pizza | H34: Scale not yet verified. Pizza account from Worldpay backbook. | I34: No non-Worldpay technology verified | J34: Source-marked synergy fit | K34: Validate corporate scale, buying authority, current POS/payments stack and whether the Worldpay relationship is enterprise or franchise-level. | L34: Partial | M34: RBB ecosystem intelligence, 2026-09-30 | N34: Brand / chain | O34: Brand footprint not yet verified | P34: Needs research | Q34: Unconfirmed — ask Worldpay | R34: Who at Worldpay owns this relationship, what merchant IDs/legal entities are in scope, and is coverage enterprise, franchisee, or a single site?
A35: B — Qualify | B35: Dibella'S | C35: Yes | D35: Fast Casual — Sandwich | H35: Scale not yet verified. Sandwich account from Worldpay backbook. | I35: No non-Worldpay technology verified | J35: Source-marked synergy fit | K35: Validate corporate scale, buying authority, current POS/payments stack and whether the Worldpay relationship is enterprise or franchise-level. | L35: Entity validation needed | M35: RBB ecosystem intelligence, 2026-09-30 | N35: Brand / chain | O35: Brand footprint not yet verified | P35: Needs research | Q35: Unconfirmed — ask Worldpay | R35: Who at Worldpay owns this relationship, what merchant IDs/legal entities are in scope, and is coverage enterprise, franchisee, or a single site?
A36: B — Qualify | B36: Famous Dave'S Bbq | C36: Yes | D36: Casual Dining — Barbecue | H36: Scale not yet verified. Barbecue account from Worldpay backbook. | I36: No non-Worldpay technology verified | J36: Source-marked synergy fit | K36: Validate corporate scale, buying authority, current POS/payments stack and whether the Worldpay relationship is enterprise or franchise-level. | L36: Partial | M36: RBB ecosystem intelligence, 2026-09-30 | N36: Brand / chain | O36: Brand footprint not yet verified | P36: Needs research | Q36: Unconfirmed — ask Worldpay | R36: Who at Worldpay owns this relationship, what merchant IDs/legal entities are in scope, and is coverage enterprise, franchisee, or a single site?
A37: B — Qualify | B37: Frischs | C37: Yes | D37: Family Dining / Burger | H37: Scale not yet verified. Family Dining account from Worldpay backbook. | I37: No non-Worldpay technology verified | J37: Source-marked synergy fit | K37: Validate corporate scale, buying authority, current POS/payments stack and whether the Worldpay relationship is enterprise or franchise-level. | L37: Partial | M37: RBB ecosystem intelligence, 2026-09-30 | N37: Brand / chain | O37: Brand footprint not yet verified | P37: Needs research | Q37: Unconfirmed — ask Worldpay | R37: Who at Worldpay owns this relationship, what merchant IDs/legal entities are in scope, and is coverage enterprise, franchisee, or a single site?
A38: B — Qualify | B38: Hungry Howies | C38: Yes | D38: Pizza | F38: 500 | H38: Public footprint refreshed 2026-09-30; distinguish brand footprint from the exact WP merchant/entity scope. | I38: No non-Worldpay technology verified | J38: Source-marked synergy fit | K38: Validate corporate scale, buying authority, current POS/payments stack and whether the Worldpay relationship is enterprise or franchise-level. | L38: Public footprint refreshed; WP ownership open | M38: RBB ecosystem intelligence, 2026-09-30 | https://hungryhowies.com/about-us | N38: Brand / chain | O38: Approximate U.S. brand footprint | P38: High | Q38: Unconfirmed — ask Worldpay | R38: Who at Worldpay owns this relationship, what merchant IDs/legal entities are in scope, and is coverage enterprise, franchisee, or a single site?
A39: B — Qualify | B39: Hwy 55 Burgers Shakes & F | C39: Yes | D39: Fast Casual — Burger | H39: Scale not yet verified. Burger account from Worldpay backbook. | I39: No non-Worldpay technology verified | J39: Source-marked synergy fit | K39: Validate corporate scale, buying authority, current POS/payments stack and whether the Worldpay relationship is enterprise or franchise-level. | L39: Partial | M39: RBB ecosystem intelligence, 2026-09-30 | N39: Brand / chain | O39: Brand footprint not yet verified | P39: Needs research | Q39: Unconfirmed — ask Worldpay | R39: Who at Worldpay owns this relationship, what merchant IDs/legal entities are in scope, and is coverage enterprise, franchisee, or a single site?
A40: B — Qualify | B40: Jake N Joes | C40: Yes | D40: Casual Dining — Sports Bar | H40: Scale not yet verified. Full-Service Dining account from Worldpay backbook. | I40: No non-Worldpay technology verified | J40: Source-marked synergy fit | K40: Validate corporate scale, buying authority, current POS/payments stack and whether the Worldpay relationship is enterprise or franchise-level. | L40: Partial | M40: RBB ecosystem intelligence, 2026-09-30 | N40: Brand / chain | O40: Brand footprint not yet verified | P40: Needs research | Q40: Unconfirmed — ask Worldpay | R40: Who at Worldpay owns this relationship, what merchant IDs/legal entities are in scope, and is coverage enterprise, franchisee, or a single site?
A41: B — Qualify | B41: Jeff Ruby | C41: Yes | D41: Fine Dining — Steakhouse | H41: Scale not yet verified. Steakhouse account from Worldpay backbook. | I41: No non-Worldpay technology verified | J41: Source-marked synergy fit | K41: Validate corporate scale, buying authority, current POS/payments stack and whether the Worldpay relationship is enterprise or franchise-level. | L41: Partial | M41: RBB ecosystem intelligence, 2026-09-30 | N41: Brand / chain | O41: Brand footprint not yet verified | P41: Needs research | Q41: Unconfirmed — ask Worldpay | R41: Who at Worldpay owns this relationship, what merchant IDs/legal entities are in scope, and is coverage enterprise, franchisee, or a single site?
A42: B — Qualify | B42: Latrelle'S Galley Lp | C42: Yes | D42: Airport / Contract Foodservice | H42: Scale not yet verified. Full-Service Dining account from Worldpay backbook. | I42: No non-Worldpay technology verified | J42: Source-marked synergy fit | K42: Validate corporate scale, buying authority, current POS/payments stack and whether the Worldpay relationship is enterprise or franchise-level. | L42: Partial | M42: RBB ecosystem intelligence, 2026-09-30 | N42: Legal entity / franchisee / site record | O42: WP merchant/entity footprint—not safe to infer from brand | P42: Needs WP confirmation | Q42: Unconfirmed — ask Worldpay | R42: Who at Worldpay owns this relationship, what merchant IDs/legal entities are in scope, and is coverage enterprise, franchisee, or a single site?
A43: B — Qualify | B43: Luby'S Restaurants | C43: Yes | D43: Cafeteria / Family Dining | H43: Scale not yet verified. Full-Service Dining account from Worldpay backbook. | I43: No non-Worldpay technology verified | J43: Source-marked synergy fit | K43: Validate corporate scale, buying authority, current POS/payments stack and whether the Worldpay relationship is enterprise or franchise-level. | L43: Entity validation needed | M43: RBB ecosystem intelligence, 2026-09-30 | N43: Brand / chain | O43: Brand footprint not yet verified | P43: Needs research | Q43: Unconfirmed — ask Worldpay | R43: Who at Worldpay owns this relationship, what merchant IDs/legal entities are in scope, and is coverage enterprise, franchisee, or a single site?
A44: B — Qualify | B44: Lunchdrop | C44: Yes | D44: Corporate Catering / Marketplace | H44: Scale not yet verified. Sandwich account from Worldpay backbook. | I44: No non-Worldpay technology verified | J44: Source-marked synergy fit | K44: Validate corporate scale, buying authority, current POS/payments stack and whether the Worldpay relationship is enterprise or franchise-level. | L44: Partial | M44: RBB ecosystem intelligence, 2026-09-30 | N44: Brand / chain | O44: Brand footprint not yet verified | P44: Needs research | Q44: Unconfirmed — ask Worldpay | R44: Who at Worldpay owns this relationship, what merchant IDs/legal entities are in scope, and is coverage enterprise, franchisee, or a single site?
A45: B — Qualify | B45: Mark'S Feed Store | C45: Yes | D45: Casual Dining — Barbecue | H45: Scale not yet verified. Barbecue account from Worldpay backbook. | I45: No non-Worldpay technology verified | J45: Source-marked synergy fit | K45: Validate corporate scale, buying authority, current POS/payments stack and whether the Worldpay relationship is enterprise or franchise-level. | L45: Partial | M45: RBB ecosystem intelligence, 2026-09-30 | N45: Brand / chain | O45: Brand footprint not yet verified | P45: Needs research | Q45: Unconfirmed — ask Worldpay | R45: Who at Worldpay owns this relationship, what merchant IDs/legal entities are in scope, and is coverage enterprise, franchisee, or a single site?
A46: B — Qualify | B46: Orange Leaf | C46: Yes | D46: Dessert / Frozen Yogurt | H46: Scale not yet verified. Dessert account from Worldpay backbook. | I46: No non-Worldpay technology verified | J46: Source-marked synergy fit | K46: Validate corporate scale, buying authority, current POS/payments stack and whether the Worldpay relationship is enterprise or franchise-level. | L46: Entity validation needed | M46: RBB ecosystem intelligence, 2026-09-30 | N46: Brand / chain | O46: Brand footprint not yet verified | P46: Needs research | Q46: Unconfirmed — ask Worldpay | R46: Who at Worldpay owns this relationship, what merchant IDs/legal entities are in scope, and is coverage enterprise, franchisee, or a single site?
A47: B — Qualify | B47: Sam Choy'S | C47: Yes | D47: Casual Dining — Hawaiian | H47: Scale not yet verified. Full-Service Dining account from Worldpay backbook. | I47: No non-Worldpay technology verified | J47: Source-marked synergy fit | K47: Validate corporate scale, buying authority, current POS/payments stack and whether the Worldpay relationship is enterprise or franchise-level. | L47: Partial | M47: RBB ecosystem intelligence, 2026-09-30 | N47: Brand / chain | O47: Brand footprint not yet verified | P47: Needs research | Q47: Unconfirmed — ask Worldpay | R47: Who at Worldpay owns this relationship, what merchant IDs/legal entities are in scope, and is coverage enterprise, franchisee, or a single site?
A48: B — Qualify | B48: Siren Retail Corporation | C48: Yes | D48: Coffee & Beverage | H48: Scale not yet verified. Coffee account from Worldpay backbook. | I48: No non-Worldpay technology verified | J48: Source-marked synergy fit | K48: Validate corporate scale, buying authority, current POS/payments stack and whether the Worldpay relationship is enterprise or franchise-level. | L48: Partial | M48: RBB ecosystem intelligence, 2026-09-30 | N48: Legal entity / franchisee / site record | O48: WP merchant/entity footprint—not safe to infer from brand | P48: Needs WP confirmation | Q48: Unconfirmed — ask Worldpay | R48: Who at Worldpay owns this relationship, what merchant IDs/legal entities are in scope, and is coverage enterprise, franchisee, or a single site?
A49: B — Qualify | B49: Tibby New Orleans Kitchen | C49: Yes | D49: Casual Dining — Cajun / Creole | H49: Scale not yet verified. Full-Service Dining account from Worldpay backbook. | I49: No non-Worldpay technology verified | J49: Source-marked synergy fit | K49: Validate corporate scale, buying authority, current POS/payments stack and whether the Worldpay relationship is enterprise or franchise-level. | L49: Partial | M49: RBB ecosystem intelligence, 2026-09-30 | N49: Brand / chain | O49: Brand footprint not yet verified | P49: Needs research | Q49: Unconfirmed — ask Worldpay | R49: Who at Worldpay owns this relationship, what merchant IDs/legal entities are in scope, and is coverage enterprise, franchisee, or a single site?
A50: B — Qualify | B50: Uno'S | C50: Yes | D50: Casual Dining — Pizza | F50: 100 | H50: Public footprint refreshed 2026-09-30; distinguish brand footprint from the exact WP merchant/entity scope. | I50: No non-Worldpay technology verified | J50: Source-marked synergy fit | K50: Validate corporate scale, buying authority, current POS/payments stack and whether the Worldpay relationship is enterprise or franchise-level. | L50: Public footprint refreshed; WP ownership open | M50: RBB ecosystem intelligence, 2026-09-30 | https://unos.com/about/ | N50: Brand / chain | O50: Global brand footprint | P50: High | Q50: Unconfirmed — ask Worldpay | R50: Who at Worldpay owns this relationship, what merchant IDs/legal entities are in scope, and is coverage enterprise, franchisee, or a single site?
A51: B — Qualify | B51: Yum Yum Donuts | C51: Yes | D51: Bakery / Dessert | H51: Scale not yet verified. Dessert account from Worldpay backbook. | I51: No non-Worldpay technology verified | J51: Source-marked synergy fit | K51: Validate corporate scale, buying authority, current POS/payments stack and whether the Worldpay relationship is enterprise or franchise-level. | L51: Partial | M51: RBB ecosystem intelligence, 2026-09-30 | N51: Brand / chain | O51: Brand footprint not yet verified | P51: Needs research | Q51: Unconfirmed — ask Worldpay | R51: Who at Worldpay owns this relationship, what merchant IDs/legal entities are in scope, and is coverage enterprise, franchisee, or a single site?
A52: C — Validate / deprioritize | B52: Logan'S Roadhouse | C52: No | D52: Casual Dining — Steakhouse | E52: 132 | F52: 125 | H52: Technomic rank 132; ~125 units. Family Dining account from Worldpay backbook. | I52: Loyalty: PAR Technology (Punchh) | J52: Source marked not relevant | K52: Confirm entity identity and central buying authority before investing pursuit time; park if this is a single-location merchant. | L52: Meeting-ready | M52: RBB ecosystem intelligence, 2026-09-30 | https://logansroadhouse.com/locations/us/ | N52: Brand / chain | O52: Brand/system footprint from existing RBB research | P52: Medium | Q52: Unconfirmed — ask Worldpay | R52: Who at Worldpay owns this relationship, what merchant IDs/legal entities are in scope, and is coverage enterprise, franchisee, or a single site?
A53: C — Validate / deprioritize | B53: Tijuana Flats | C53: No | D53: Fast Casual — Mexican | E53: 311 | F53: 91 | H53: Technomic rank 311; ~91 units. Mexican account from Worldpay backbook. | I53: Loyalty: PAR Technology (Punchh) | J53: Source marked not relevant; WP attrition: Attrition; WP dyssynergy flag present | K53: Confirm entity identity and central buying authority before investing pursuit time; park if this is a single-location merchant. | L53: Meeting-ready | M53: RBB ecosystem intelligence, 2026-09-30 | N53: Brand / chain | O53: Brand/system footprint from existing RBB research | P53: Medium | Q53: Unconfirmed — ask Worldpay | R53: Who at Worldpay owns this relationship, what merchant IDs/legal entities are in scope, and is coverage enterprise, franchisee, or a single site?
A54: C — Validate / deprioritize | B54: Boston Market | C54: No | D54: QSR — Chicken | E54: 758 | F54: 16 | H54: Technomic rank 758; ~16 units. Chicken account from Worldpay backbook. | I54: No non-Worldpay technology verified | J54: Source marked not relevant; WP attrition: Attrition; WP dyssynergy flag present | K54: Confirm entity identity and central buying authority before investing pursuit time; park if this is a single-location merchant. | L54: Partial | M54: RBB ecosystem intelligence, 2026-09-30 | N54: Brand / chain | O54: Brand/system footprint from existing RBB research | P54: Medium | Q54: Unconfirmed — ask Worldpay | R54: Who at Worldpay owns this relationship, what merchant IDs/legal entities are in scope, and is coverage enterprise, franchisee, or a single site?
A55: C — Validate / deprioritize | B55: Oyster House | C55: No | D55: Full-Service Dining | E55: 1328 | F55: 6 | H55: Technomic rank 1328; ~6 units. Full-Service Dining account from Worldpay backbook. | I55: No non-Worldpay technology verified | J55: Source marked not relevant | K55: Confirm entity identity and central buying authority before investing pursuit time; park if this is a single-location merchant. | L55: Partial | M55: RBB ecosystem intelligence, 2026-09-30 | N55: Brand / chain | O55: Brand/system footprint from existing RBB research | P55: Medium | Q55: Unconfirmed — ask Worldpay | R55: Who at Worldpay owns this relationship, what merchant IDs/legal entities are in scope, and is coverage enterprise, franchisee, or a single site?
A56: C — Validate / deprioritize | B56: Amanda'S Fonda | C56: No | D56: Casual Dining — Mexican | H56: Scale not yet verified. Mexican account from Worldpay backbook. | I56: No non-Worldpay technology verified | J56: Source marked not relevant | K56: Confirm entity identity and central buying authority before investing pursuit time; park if this is a single-location merchant. | L56: Partial | M56: RBB ecosystem intelligence, 2026-09-30 | N56: Brand / chain | O56: Brand footprint not yet verified | P56: Needs research | Q56: Unconfirmed — ask Worldpay | R56: Who at Worldpay owns this relationship, what merchant IDs/legal entities are in scope, and is coverage enterprise, franchisee, or a single site?
A57: C — Validate / deprioritize | B57: Broadway On Deck Llc | C57: No | D57: Merchant / Legal Entity | H57: Scale not yet verified. Full-Service Dining account from Worldpay backbook. | I57: No non-Worldpay technology verified | J57: Source marked not relevant | K57: Confirm entity identity and central buying authority before investing pursuit time; park if this is a single-location merchant. | L57: Partial | M57: RBB ecosystem intelligence, 2026-09-30 | N57: Legal entity / franchisee / site record | O57: WP merchant/entity footprint—not safe to infer from brand | P57: Needs WP confirmation | Q57: Unconfirmed — ask Worldpay | R57: Who at Worldpay owns this relationship, what merchant IDs/legal entities are in scope, and is coverage enterprise, franchisee, or a single site?
A58: C — Validate / deprioritize | B58: Bruegger'S Enterprises In | C58: Yes | D58: Bakery / Breakfast | F58: 181 | H58: Public footprint refreshed 2026-09-30; distinguish brand footprint from the exact WP merchant/entity scope. | I58: No non-Worldpay technology verified | J58: Source-marked synergy fit | K58: Confirm entity identity and central buying authority before investing pursuit time; park if this is a single-location merchant. | L58: Public footprint refreshed; WP ownership open | M58: RBB ecosystem intelligence, 2026-09-30 | https://www.brueggers.com/wp-content/uploads/2024/06/BB-ESG-Report-2023.pdf | N58: Legal entity / franchisee / site record | O58: Brand footprint; reported Oct. 2023 | P58: Medium | Q58: Unconfirmed — ask Worldpay | R58: Who at Worldpay owns this relationship, what merchant IDs/legal entities are in scope, and is coverage enterprise, franchisee, or a single site?
A59: C — Validate / deprioritize | B59: Bun Two Llc / Cinnabon | C59: No | D59: Franchisee — Bakery / Dessert | H59: Scale not yet verified. Dessert account from Worldpay backbook. | I59: No non-Worldpay technology verified | J59: Source marked not relevant | K59: Confirm entity identity and central buying authority before investing pursuit time; park if this is a single-location merchant. | L59: Partial | M59: RBB ecosystem intelligence, 2026-09-30 | N59: Legal entity / franchisee / site record | O59: WP merchant/entity footprint—not safe to infer from brand | P59: Needs WP confirmation | Q59: Unconfirmed — ask Worldpay | R59: Who at Worldpay owns this relationship, what merchant IDs/legal entities are in scope, and is coverage enterprise, franchisee, or a single site?
A60: C — Validate / deprioritize | B60: D&C Foods Inc #5 | C60: Yes | D60: Merchant / Franchisee Entity | H60: Scale not yet verified. Pizza account from Worldpay backbook. | I60: No non-Worldpay technology verified | J60: Source-marked synergy fit | K60: Confirm entity identity and central buying authority before investing pursuit time; park if this is a single-location merchant. | L60: Partial | M60: RBB ecosystem intelligence, 2026-09-30 | N60: Legal entity / franchisee / site record | O60: WP merchant/entity footprint—not safe to infer from brand | P60: Needs WP confirmation | Q60: Unconfirmed — ask Worldpay | R60: Who at Worldpay owns this relationship, what merchant IDs/legal entities are in scope, and is coverage enterprise, franchisee, or a single site?
A61: C — Validate / deprioritize | B61: Down The Hatch | C61: No | D61: Casual Dining / Bar | H61: Scale not yet verified. Full-Service Dining account from Worldpay backbook. | I61: No non-Worldpay technology verified | J61: Source marked not relevant | K61: Confirm entity identity and central buying authority before investing pursuit time; park if this is a single-location merchant. | L61: Partial | M61: RBB ecosystem intelligence, 2026-09-30 | N61: Brand / chain | O61: Brand footprint not yet verified | P61: Needs research | Q61: Unconfirmed — ask Worldpay | R61: Who at Worldpay owns this relationship, what merchant IDs/legal entities are in scope, and is coverage enterprise, franchisee, or a single site?
A62: C — Validate / deprioritize | B62: Fontana Subway Sandwiches | C62: No | D62: Franchisee — Sandwich | H62: Scale not yet verified. Sandwich account from Worldpay backbook. | I62: No non-Worldpay technology verified | J62: Source marked not relevant | K62: Confirm entity identity and central buying authority before investing pursuit time; park if this is a single-location merchant. | L62: Partial | M62: RBB ecosystem intelligence, 2026-09-30 | N62: Legal entity / franchisee / site record | O62: WP merchant/entity footprint—not safe to infer from brand | P62: Needs WP confirmation | Q62: Unconfirmed — ask Worldpay | R62: Who at Worldpay owns this relationship, what merchant IDs/legal entities are in scope, and is coverage enterprise, franchisee, or a single site?
A63: C — Validate / deprioritize | B63: Forward Subway | C63: No | D63: Franchisee — Sandwich | H63: Scale not yet verified. Sandwich account from Worldpay backbook. | I63: No non-Worldpay technology verified | J63: Source marked not relevant | K63: Confirm entity identity and central buying authority before investing pursuit time; park if this is a single-location merchant. | L63: Partial | M63: RBB ecosystem intelligence, 2026-09-30 | N63: Legal entity / franchisee / site record | O63: WP merchant/entity footprint—not safe to infer from brand | P63: Needs WP confirmation | Q63: Unconfirmed — ask Worldpay | R63: Who at Worldpay owns this relationship, what merchant IDs/legal entities are in scope, and is coverage enterprise, franchisee, or a single site?
A64: C — Validate / deprioritize | B64: Friendly Ice Cream #7776 | C64: Yes | D64: Family Dining / Dessert | H64: Scale not yet verified. Dessert account from Worldpay backbook. | I64: No non-Worldpay technology verified | J64: Source-marked synergy fit | K64: Confirm entity identity and central buying authority before investing pursuit time; park if this is a single-location merchant. | L64: Partial | M64: RBB ecosystem intelligence, 2026-09-30 | N64: Legal entity / franchisee / site record | O64: WP merchant/entity footprint—not safe to infer from brand | P64: Needs WP confirmation | Q64: Unconfirmed — ask Worldpay | R64: Who at Worldpay owns this relationship, what merchant IDs/legal entities are in scope, and is coverage enterprise, franchisee, or a single site?
A65: C — Validate / deprioritize | B65: Gibsons Llc | C65: Yes | D65: Fine Dining — Steakhouse | H65: Scale not yet verified. Steakhouse account from Worldpay backbook. | I65: No non-Worldpay technology verified | J65: Source-marked synergy fit | K65: Confirm entity identity and central buying authority before investing pursuit time; park if this is a single-location merchant. | L65: Partial | M65: RBB ecosystem intelligence, 2026-09-30 | N65: Legal entity / franchisee / site record | O65: WP merchant/entity footprint—not safe to infer from brand | P65: Needs WP confirmation | Q65: Unconfirmed — ask Worldpay | R65: Who at Worldpay owns this relationship, what merchant IDs/legal entities are in scope, and is coverage enterprise, franchisee, or a single site?
A66: C — Validate / deprioritize | B66: Houlihan'S Restaurants Inc | C66: Yes | D66: Casual Dining | H66: Scale not yet verified. Family Dining account from Worldpay backbook. | I66: No non-Worldpay technology verified | J66: Source-marked synergy fit | K66: Confirm entity identity and central buying authority before investing pursuit time; park if this is a single-location merchant. | L66: Entity validation needed | M66: RBB ecosystem intelligence, 2026-09-30 | N66: Legal entity / franchisee / site record | O66: WP merchant/entity footprint—not safe to infer from brand | P66: Needs WP confirmation | Q66: Unconfirmed — ask Worldpay | R66: Who at Worldpay owns this relationship, what merchant IDs/legal entities are in scope, and is coverage enterprise, franchisee, or a single site?
A67: C — Validate / deprioritize | B67: International Coffee & Tea Llc | C67: Yes | D67: Coffee & Beverage | H67: Scale not yet verified. Coffee account from Worldpay backbook. | I67: No non-Worldpay technology verified | J67: Source-marked synergy fit | K67: Confirm entity identity and central buying authority before investing pursuit time; park if this is a single-location merchant. | L67: Partial | M67: RBB ecosystem intelligence, 2026-09-30 | N67: Legal entity / franchisee / site record | O67: WP merchant/entity footprint—not safe to infer from brand | P67: Needs WP confirmation | Q67: Unconfirmed — ask Worldpay | R67: Who at Worldpay owns this relationship, what merchant IDs/legal entities are in scope, and is coverage enterprise, franchisee, or a single site?
A68: C — Validate / deprioritize | B68: J&B Restaurant Partner Of | C68: Yes | D68: Family Dining | H68: Scale not yet verified. Family Dining account from Worldpay backbook. | I68: No non-Worldpay technology verified | J68: Source-marked synergy fit | K68: Confirm entity identity and central buying authority before investing pursuit time; park if this is a single-location merchant. | L68: Partial | M68: RBB ecosystem intelligence, 2026-09-30 | N68: Brand / chain | O68: Brand footprint not yet verified | P68: Needs research | Q68: Unconfirmed — ask Worldpay | R68: Who at Worldpay owns this relationship, what merchant IDs/legal entities are in scope, and is coverage enterprise, franchisee, or a single site?
A69: C — Validate / deprioritize | B69: Jb'S On The Beach | C69: No | D69: Casual Dining | H69: Scale not yet verified. Full-Service Dining account from Worldpay backbook. | I69: No non-Worldpay technology verified | J69: Source marked not relevant | K69: Confirm entity identity and central buying authority before investing pursuit time; park if this is a single-location merchant. | L69: Partial | M69: RBB ecosystem intelligence, 2026-09-30 | N69: Brand / chain | O69: Brand footprint not yet verified | P69: Needs research | Q69: Unconfirmed — ask Worldpay | R69: Who at Worldpay owns this relationship, what merchant IDs/legal entities are in scope, and is coverage enterprise, franchisee, or a single site?
A70: C — Validate / deprioritize | B70: Jy5, Inc | C70: No | D70: Merchant / Franchisee Entity | H70: Scale not yet verified. Sandwich account from Worldpay backbook. | I70: No non-Worldpay technology verified | J70: Source marked not relevant | K70: Confirm entity identity and central buying authority before investing pursuit time; park if this is a single-location merchant. | L70: Partial | M70: RBB ecosystem intelligence, 2026-09-30 | N70: Legal entity / franchisee / site record | O70: WP merchant/entity footprint—not safe to infer from brand | P70: Needs WP confirmation | Q70: Unconfirmed — ask Worldpay | R70: Who at Worldpay owns this relationship, what merchant IDs/legal entities are in scope, and is coverage enterprise, franchisee, or a single site?
... A89: C — Validate / deprioritize | B89: Wow Bao Llc | C89: Yes | D89: Fast Casual — Asian | H89: Scale not yet verified. Asian account from Worldpay backbook. | I89: No non-Worldpay technology verified | J89: Source-marked synergy fit | K89: Confirm entity identity and central buying authority before investing pursuit time; park if this is a single-location merchant. | L89: Partial | M89: RBB ecosystem intelligence, 2026-09-30 | N89: Legal entity / franchisee / site record | O89: WP merchant/entity footprint—not safe to infer from brand | P89: Needs WP confirmation | Q89: Unconfirmed — ask Worldpay | R89: Who at Worldpay owns this relationship, what merchant IDs/legal entities are in scope, and is coverage enterprise, franchisee, or a single site?

Sheet Ranked Portfolio
A1: Ranked Worldpay Opportunity Portfolio — 2026-09-04 Master Plan
A2: Existing scored accounts preserved. 85 supplemental Worldpay ABM targets appended unranked on 2026-09-28 pending qualification.
A4: Rank | B4: Priority | C4: Account | D4: RM | E4: Tier | F4: Locations | G4: Score | H4: Strategic Value | I4: Active Trigger | J4: Access | K4: Lifecycle | L4: Deployment Health | M4: Whitespace | N4: Coordination | O4: Trigger / Current State | P4: Lifecycle Posture | Q4: Health | R4: Opportunity Type | S4: Immediate Next Action | T4: Key Vendors | U4: Field Intelligence | V4: Evidence Confidence | W4: Region | X4: Geo | Y4: Sub-segment | Z4: Relevant to synergy | AA4: Dyssynergy with WP | AB4: WP Attrition | AC4: WP Rep | AD4: WP Products Used | AE4: Genius Rep | AF4: GP Products Used | AG4: Supplemental Source | AH4: Account Type | AI4: Location Scope | AJ4: Location Confidence | AK4: WP Relationship Owner | AL4: Internal Clarification Needed
A5: 1 | B5: P1 | C5: DEL TACO LLC | D5: Maggie Lenhart | E5: Tier 2 | F5: 537 | G5: =(H5/5*'Scoring Model'!$B$5+I5/5*'Scoring Model'!$B$6+J5/5*'Scoring Model'!$B$7+K5/5*'Scoring Model'!$B$8+L5/5*'Scoring Model'!$B$9+M5/5*'Scoring Model'!$B$10+N5/5*'Scoring Model'!$B$11)*100 -> 83 | H5: 4 | I5: 5 | J5: 4 | K5: 4 | L5: 3 | M5: 4 | N5: 5 | O5: Worldpay extension active; Yadav acquisition creates a verified ownership-change window; sourcing event unconfirmed | P5: Aging NCR estate; post-acquisition multi-brand governance | Q5: Active relationship; technology and synergy timing to verify | R5: POS/payments + multi-brand consolidation | S5: Complete the extension, consolidate all GP leads, map Yadav technology governance and confirm any sourcing or vendor-consolidation event. | T5: NCR; NCR Connected Payments; Olo; Olo Pay; Bite | U5: Yadav Enterprises completed the acquisition in Dec. 2025. Direct CIO access and the extension remain strong; cost/stack review is a hypothesis pending customer confirmation. | V5: High RM intelligence + verified ownership event
A6: 2 | B6: P1 | C6: FIVE GUYS | D6: Avery Churchwell | E6: Tier 1 | F6: 1500 | G6: =(H6/5*'Scoring Model'!$B$5+I6/5*'Scoring Model'!$B$6+J6/5*'Scoring Model'!$B$7+K6/5*'Scoring Model'!$B$8+L6/5*'Scoring Model'!$B$9+M6/5*'Scoring Model'!$B$10+N6/5*'Scoring Model'!$B$11)*100 -> 82 | H6: 5 | I6: 5 | J6: 4 | K6: 5 | L6: 2 | M6: 2 | N6: 5 | O6: MJ Worsham remains the key influential contact. Multiple uncoordinated Genius outreach attempts have created account-ownership friction; MJ and Zerick were invited to the FSTEC happy hour but had not responded as of the September 4 Avery call. No formal RFI/RFP is confirmed. | P6: Mature U.S. PAR estate; global support gaps and modularity hypothesis | Q6: No verified failure; renewal dates and evaluation type require confirmation | R6: Pre-RFP shaping + transaction-metered POS feasibility | S6: Centralize all Five Guys outreach through Todd and Avery; avoid generic prospecting. Use FSTEC only for a relationship-first conversation, validate whether MJ still engages former PAR account manager Chad Kaisel, and confirm PAR term, evaluation type, sponsor, scope and global gaps before presenting any commercial model. | T6: PAR Brink; NCR (EMEA); CrunchTime; Olo; Worldpay/Global Payments; Verifone; LineTen | U6: Avery reported that her merchant questioned why multiple Genius people were contacting Five Guys without her knowledge. She emphasized that introductions should flow through the relationship owner. MJ is resistant to consolidating multiple lines of business with one vendor and will require a compelling reason to engage. Todd is internally exploring a capped per-card-swipe technology funding model, but it is not approved or customer-presented. | V6: High RM intelligence dated 2026-09-04 / buying event, dates and commercial model remain unconfirmed
A7: 3 | B7: P1 | C7: Focus Brands (GoTo Foods) | D7: Brian Wood | E7: Tier 2 | F7: 2600 | G7: =(H7/5*'Scoring Model'!$B$5+I7/5*'Scoring Model'!$B$6+J7/5*'Scoring Model'!$B$7+K7/5*'Scoring Model'!$B$8+L7/5*'Scoring Model'!$B$9+M7/5*'Scoring Model'!$B$10+N7/5*'Scoring Model'!$B$11)*100 -> 81 | H7: 5 | I7: 5 | J7: 3 | K7: 2 | L7: 5 | M7: 4 | N7: 4 | O7: Qu established; DMB relationship development and defense against Qu Pay/platform expansion | P7: Deploying since 2024 | Q7: Schedule risk reported | R7: DMB-led adjacency + payments defense | S7: Map DMB/CMS and buying center; quantify uncovered adjacencies and defend payments without positioning a near-term POS displacement. | T7: Qu; FreedomPay; Olo; Monkey Media | U7: Qu remains established. Treat PAR/Qu-style platform consolidation and native-payments attachment as the competitive pattern to counter. | V7: High RM intelligence + public evidence
A8: 4 | B8: P1 | C8: SUBWAY | D8: Stacie Davis | E8: Tier 1 | F8: 20000 | G8: =(H8/5*'Scoring Model'!$B$5+I8/5*'Scoring Model'!$B$6+J8/5*'Scoring Model'!$B$7+K8/5*'Scoring Model'!$B$8+L8/5*'Scoring Model'!$B$9+M8/5*'Scoring Model'!$B$10+N8/5*'Scoring Model'!$B$11)*100 -> 79 | H8: 5 | I8: 4 | J8: 4 | K8: 3 | L8: 3 | M8: 4 | N8: 4 | O8: Proprietary POS; internal report indicates a global Genius KDS deployment, replacing the prior DMB assumption | P8: Fragmented global/franchise estate; existing Genius relationship requires verification | Q8: Product, site coverage, ownership and commitments unresolved | R8: Existing Genius KDS scope verification + relationship map | S8: Confirm the Genius product owner, KDS sites, deployment status, commitments and customer sponsor before proposing any additional adjacency. | T8: Proprietary; FreedomPay; Ingenico; Genius KDS (reported internally, unverified) | U8: Ryan Hildebrand described proprietary POS plus a global Genius KDS deployment. Reconcile that internal view with prior DMB reporting. | V8: High internal intelligence / exact scope unresolved
A9: 5 | B9: P2 | C9: THE STEAK N SHAKE CO | D9: Maggie Lenhart | E9: Tier 2 | F9: 550 | G9: =(H9/5*'Scoring Model'!$B$5+I9/5*'Scoring Model'!$B$6+J9/5*'Scoring Model'!$B$7+K9/5*'Scoring Model'!$B$8+L9/5*'Scoring Model'!$B$9+M9/5*'Scoring Model'!$B$10+N9/5*'Scoring Model'!$B$11)*100 -> 76 | H9: 4 | I9: 4 | J9: 3 | K9: 4 | L9: 4 | M9: 4 | N9: 3 | O9: Kiosk transition and NCR reporting integration problems | P9: Transitioning adjacent stack | Q9: Current implementation pain | R9: Kiosk integration recovery + digital adjacency | S9: Name the kiosk vendor and owners; document certification, NCR reporting and mobile-app issues with dated remediation milestones. | T9: NCR; NCR Connected Payments; QikServe; Olo; NovaDine | U9: Maggie reports a difficult kiosk-vendor transition and integration/reporting issues with NCR. | V9: High RM intelligence
A10: 6 | B10: P2 | C10: CHOICE HOTELS | D10: Brian Wood | E10: Tier 2 | G10: =(H10/5*'Scoring Model'!$B$5+I10/5*'Scoring Model'!$B$6+J10/5*'Scoring Model'!$B$7+K10/5*'Scoring Model'!$B$8+L10/5*'Scoring Model'!$B$9+M10/5*'Scoring Model'!$B$10+N10/5*'Scoring Model'!$B$11)*100 -> 75 | H10: 3 | I10: 5 | J10: 3 | K10: 4 | L10: 4 | M10: 3 | N10: 5 | O10: Gateway/acquiring RFP was active in July; current stage and deadlines now require refresh | P10: Deconverting | Q10: Shift4 performance concern reported | R10: Payments win-back + hospitality adjacency | S10: Confirm whether the RFP remains active, current stage, decision dates, retained Worldpay estate, sponsor and restaurant/DMB scope. | T10: Shift4 | U10: Brian and Brendan report an active RFP, remaining Worldpay locations and a possible full win-back. | V10: High RM intelligence / status aging
A11: 7 | B11: P2 | C11: RDS FIVE-UNIT REBRAND PILOT | D11: RDS / Darren Heinze | E11: Channel pilot | F11: 5 | G11: =(H11/5*'Scoring Model'!$B$5+I11/5*'Scoring Model'!$B$6+J11/5*'Scoring Model'!$B$7+K11/5*'Scoring Model'!$B$8+L11/5*'Scoring Model'!$B$9+M11/5*'Scoring Model'!$B$10+N11/5*'Scoring Model'!$B$11)*100 -> 74 | H11: 2 | I11: 4 | J11: 4 | K11: 4 | L11: 3 | M11: 5 | N11: 5 | O11: Five former Taco Cabana locations are rebranding and evaluating a clean-slate stack and digital menu boards | P11: Clean-slate conversion; opening and conversion dates unconfirmed | Q11: High channel access; commercial, support and account-protection model not yet defined | R11: RDS-led Genius pilot and reseller proof | S11: Confirm entity/concept, authority, dates, budget and incumbent contracts; define scope, economics, support, success metrics and case-study rights before Genius World. | T11: To be determined: Genius POS/payments; DMB; drive-thru; loyalty; back office; hardware | U11: RDS is authorized to resell Genius but lacks implementation experience. The pilot can create channel proof before any larger protected-account motion. | V11: High field confidence / customer facts require documentation
A12: 8 | B12: P2 | C12: POLLO CAMPERO | D12: Unassigned / Worldpay | E12: Emerging strategic | F12: 150 | G12: =(H12/5*'Scoring Model'!$B$5+I12/5*'Scoring Model'!$B$6+J12/5*'Scoring Model'!$B$7+K12/5*'Scoring Model'!$B$8+L12/5*'Scoring Model'!$B$9+M12/5*'Scoring Model'!$B$10+N12/5*'Scoring Model'!$B$11)*100 -> 72 | H12: 4 | I12: 4 | J12: 3 | K12: 3 | L12: 3 | M12: 4 | N12: 4 | O12: Potential RFI and DMB dissatisfaction; Oracle migration and referral status require immediate qualification | P12: Mixed NCR/Oracle estate; international platform decision may be underway | Q12: Decision openness, scope, deadlines and sponsor unconfirmed | R12: RFI qualification + international platform/payments/DMB | S12: Obtain NDA/RFI, confirm sponsor and deadlines, separate the stalled referral from the procurement stream, and apply country-by-country bid/no-bid gates. | T12: Oracle Simphony; NCR Aloha; Fiserv; Olo Pay/Stripe; Valutec; DMB incumbent unverified | U12: Split estate, reported $200M+ card volume and international footprint create strategic fit, but the Oracle decision may already be advanced. | V12: Strong internal brief / customer procurement not confirmed
A13: 9 | B13: P3 | C13: EAT'N PARK HOSPITALITY GRP INC | D13: Avery Churchwell | E13: Tier 2 | F13: 137 | G13: =(H13/5*'Scoring Model'!$B$5+I13/5*'Scoring Model'!$B$6+J13/5*'Scoring Model'!$B$7+K13/5*'Scoring Model'!$B$8+L13/5*'Scoring Model'!$B$9+M13/5*'Scoring Model'!$B$10+N13/5*'Scoring Model'!$B$11)*100 -> 64 | H13: 3 | I13: 3 | J13: 2 | K13: 3 | L13: 3 | M13: 5 | N13: 4 | O13: Multi-concept conversion noted by Worldpay | P13: Mixed / transitioning | Q13: Unknown | R13: Consolidation and payments | S13: Separate stacks by concept and validate Oracle/FreedomPay/Tillster/Olo/Nextep ownership. | T13: Oracle Simphony; FreedomPay; Tillster; Olo; Nextep | V13: Internal baseline only
A14: 10 | B14: P3 | C14: FREDDY'S FROZEN CUSTARD LLC | D14: Avery Churchwell | E14: Tier 2 | F14: 500 | G14: =(H14/5*'Scoring Model'!$B$5+I14/5*'Scoring Model'!$B$6+J14/5*'Scoring Model'!$B$7+K14/5*'Scoring Model'!$B$8+L14/5*'Scoring Model'!$B$9+M14/5*'Scoring Model'!$B$10+N14/5*'Scoring Model'!$B$11)*100 -> 63 | H14: 4 | I14: 3 | J14: 4 | K14: 1 | L14: 3 | M14: 3 | N14: 5 | O14: Protected RDS account with no verified displacement event. Avery invited Freddy's contacts to the FSTEC happy hour but had received no response as of September 4. | P14: Established PAR via RDS; protected channel relationship | Q14: No verified displacement event; RDS has deep operational and CFO access | R14: RDS-led value review and modular watchlist | S14: Keep all activity RDS-led. Confirm whether RDS connected with Ryan after Genius World, identify any FSTEC attendance, and wait for a customer-defined business problem before advancing a value case. | T14: PAR Brink via RDS; Olo Pay; Creative Realities DMB; Neon entry reported, unverified | U14: Avery and Todd agreed that RDS is the strongest coordinated route into Freddy's. Todd had previously discussed Genius with RDS at the Freddy's show; an RDS contact attended Genius World, but follow-through with Ryan still needed confirmation. | V14: High RM/channel intelligence dated 2026-09-04 / no active customer buying trigger verified
A15: 11 | B15: P3 | C15: PAPA JOHN'S USA, INC. | D15: Brian Wood | E15: Tier 1 | F15: 3300 | G15: =(H15/5*'Scoring Model'!$B$5+I15/5*'Scoring Model'!$B$6+J15/5*'Scoring Model'!$B$7+K15/5*'Scoring Model'!$B$8+L15/5*'Scoring Model'!$B$9+M15/5*'Scoring Model'!$B$10+N15/5*'Scoring Model'!$B$11)*100 -> 62 | H15: 5 | I15: 3 | J15: 3 | K15: 1 | L15: 2 | M15: 4 | N15: 2 | O15: PAR POS + OPS implementation begins in 2026; rollout through 2027; Linux-build dependency reported but unverified | P15: Newly selected / deploying | Q15: PAR reports milestones on track; watch implementation and technical dependencies | R15: DMB adjacency + implementation-risk watch | S15: Map DMB and adjacent owners; monitor implementation milestones and validate the reported Linux-build dependency without positioning POS displacement. | T15: PAR POS; PAR OPS; legacy Mainstreet Monetra; Ingenico | U15: PAR publicly reports development progress and implementation later in 2026. The Linux requirement is confidential field intelligence requiring technical validation. | V15: High public evidence + unverified technical-risk lead
A16: 12 | B16: P3 | C16: CRACKER BARREL OLD COUNTRY STORE, INC. | D16: Brian Wood | E16: Tier 2 | F16: 600 | G16: =(H16/5*'Scoring Model'!$B$5+I16/5*'Scoring Model'!$B$6+J16/5*'Scoring Model'!$B$7+K16/5*'Scoring Model'!$B$8+L16/5*'Scoring Model'!$B$9+M16/5*'Scoring Model'!$B$10+N16/5*'Scoring Model'!$B$11)*100 -> 61 | H16: 4 | I16: 3 | J16: 3 | K16: 2 | L16: 3 | M16: 3 | N16: 3 | O16: Oracle Simphony rollout continuing in 2026 | P16: Deploying / transition | Q16: Early field adoption signals; verify | R16: Adjacent stack and deployment support | S16: Confirm rollout completion, FreedomPay scope, operational issues and remaining adjacent gaps. | T16: Oracle Simphony; FreedomPay; Olo | V16: Mixed / see ledger
A17: 13 | B17: P3 | C17: MILLLER'S ALE HOUSE | D17: Avery Churchwell | E17: Tier 2 | F17: 112 | G17: =(H17/5*'Scoring Model'!$B$5+I17/5*'Scoring Model'!$B$6+J17/5*'Scoring Model'!$B$7+K17/5*'Scoring Model'!$B$8+L17/5*'Scoring Model'!$B$9+M17/5*'Scoring Model'!$B$10+N17/5*'Scoring Model'!$B$11)*100 -> 61 | H17: 3 | I17: 3 | J17: 2 | K17: 4 | L17: 3 | M17: 3 | N17: 4 | O17: Digital payments moved direct to Olo | P17: Established POS; recent digital payment change | Q17: Unknown | R17: In-store POS/payments and guest experience | S17: Confirm lost scope, NCR renewal, Ziosk footprint and remaining payments opportunity. | T17: NCR; Ziosk; Olo Pay | V17: Internal baseline only
A18: 14 | B18: P3 | C18: LAROSA'S INC | D18: Maggie Lenhart | E18: Tier 2 | F18: 76 | G18: =(H18/5*'Scoring Model'!$B$5+I18/5*'Scoring Model'!$B$6+J18/5*'Scoring Model'!$B$7+K18/5*'Scoring Model'!$B$8+L18/5*'Scoring Model'!$B$9+M18/5*'Scoring Model'!$B$10+N18/5*'Scoring Model'!$B$11)*100 -> 59 | H18: 2 | I18: 3 | J18: 2 | K18: 4 | L18: 3 | M18: 4 | N18: 3 | O18: Possible EMV modernization gap | P18: Mature / niche POS | Q18: Unknown | R18: EMV, payments and enterprise modernization | S18: Validate POS.Cloud contract, non-EMV exposure, franchise scope and replacement appetite. | T18: Point of Sale.Cloud; Mainstreet Monetra; triPOS | V18: Internal baseline only
A19: 15 | B19: P3 | C19: CHURCHS CHICKEN 558 | D19: Maggie Lenhart | E19: Tier 2 | F19: 832 | G19: =(H19/5*'Scoring Model'!$B$5+I19/5*'Scoring Model'!$B$6+J19/5*'Scoring Model'!$B$7+K19/5*'Scoring Model'!$B$8+L19/5*'Scoring Model'!$B$9+M19/5*'Scoring Model'!$B$10+N19/5*'Scoring Model'!$B$11)*100 -> 58 | H19: 4 | I19: 2 | J19: 2 | K19: 3 | L19: 2 | M19: 4 | N19: 3 | O19: Qu vs Oracle decision not officially communicated to Worldpay | P19: Established | Q19: Decision believed to favor Qu; verify | R19: DMB/drive-thru adjacency after POS verification | S19: Use Maggie to confirm the final POS decision and current payments integration before positioning an adjacency. | T19: Qu; Aurus; Olo; Bite | U19: Maggie reports Qu is assumed but not officially confirmed; leadership changes delayed clarity. | V19: High RM intelligence / unresolved
A20: 16 | B20: P3 | C20: GOLDEN CORRAL | D20: Maggie Lenhart | E20: Tier 2 | F20: 640 | G20: =(H20/5*'Scoring Model'!$B$5+I20/5*'Scoring Model'!$B$6+J20/5*'Scoring Model'!$B$7+K20/5*'Scoring Model'!$B$8+L20/5*'Scoring Model'!$B$9+M20/5*'Scoring Model'!$B$10+N20/5*'Scoring Model'!$B$11)*100 -> 58 | H20: 4 | I20: 2 | J20: 2 | K20: 3 | L20: 2 | M20: 4 | N20: 3 | O20: No dated public trigger found | P20: Established / date unknown | Q20: Unknown | R20: Franchise payments + adjacent discovery | S20: Verify Qu start date, Aurus/Olo scopes, franchise penetration and contract dates. | T20: Qu; Aurus; Olo | V20: Internal baseline only
A21: 17 | B21: P3 | C21: Red Robin | D21: Avery Churchwell | E21: Tier 2 | F21: 500 | G21: =(H21/5*'Scoring Model'!$B$5+I21/5*'Scoring Model'!$B$6+J21/5*'Scoring Model'!$B$7+K21/5*'Scoring Model'!$B$8+L21/5*'Scoring Model'!$B$9+M21/5*'Scoring Model'!$B$10+N21/5*'Scoring Model'!$B$11)*100 -> 58 | H21: 4 | I21: 2 | J21: 2 | K21: 4 | L21: 2 | M21: 3 | N21: 3 | O21: Avery sees signs that Red Robin may be in a better operating position and considers it a renewed prospecting possibility; no customer-confirmed buying event was disclosed. | P21: Mature mixed stack | Q21: Customer pressure; limited capital | R21: Pay-at-table replacement + payment savings | S21: Validate the improved-business-condition signal with current public results and direct RM knowledge, then confirm NCR term, Ziosk dissatisfaction, decision ownership and whether a pay-at-table/payment-savings discussion is timely. | T21: NCR Aloha; Ziosk; Olo; Monkey Media | U21: On September 4 Avery said recent reading suggested Red Robin was in a better spot and should be reconsidered as a possibility. This is a directional RM assessment, not a confirmed customer initiative. | V21: Medium RM assessment dated 2026-09-04 / customer trigger unverified
A22: 18 | B22: P3 | C22: BOB EVANS RESTAURANTS, LLC | D22: Brian Wood | E22: Tier 2 | F22: 450 | G22: =(H22/5*'Scoring Model'!$B$5+I22/5*'Scoring Model'!$B$6+J22/5*'Scoring Model'!$B$7+K22/5*'Scoring Model'!$B$8+L22/5*'Scoring Model'!$B$9+M22/5*'Scoring Model'!$B$10+N22/5*'Scoring Model'!$B$11)*100 -> 57 | H22: 3 | I22: 2 | J22: 2 | K22: 4 | L22: 2 | M22: 4 | N22: 3 | O22: No dated primary-source trigger verified | P22: Established NCR estate | Q22: Unknown | R22: Aging POS and adjacent modernization | S22: Confirm earliest Aloha deployment/renewal and Connected Payments term. | T22: NCR Aloha; NCR Connected Payments | V22: Internal baseline only
A23: 19 | B23: P3 | C23: GRAETERS | D23: Maggie Lenhart | E23: Tier 2 | F23: 67 | G23: =(H23/5*'Scoring Model'!$B$5+I23/5*'Scoring Model'!$B$6+J23/5*'Scoring Model'!$B$7+K23/5*'Scoring Model'!$B$8+L23/5*'Scoring Model'!$B$9+M23/5*'Scoring Model'!$B$10+N23/5*'Scoring Model'!$B$11)*100 -> 57 | H23: 2 | I23: 3 | J23: 3 | K23: 3 | L23: 2 | M23: 4 | N23: 3 | O23: Product segmentation clarified | P23: PAR non-enterprise deployment | Q23: No adverse signal | R23: Enterprise upgrade or adjacent stack | S23: Confirm PAR product/SKU, reseller, site coverage and enterprise gaps; test migration economics without misclassifying current state. | T23: PAR Brink (non-enterprise); Olo | U23: Graeter's is a PAR customer but not PAR Enterprise. | V23: Mixed / see ledger
A24: 20 | B24: P3 | C24: STARBUCKS CORPORATION | D24: Stacie Davis | E24: Tier 1 | F24: 10000 | G24: =(H24/5*'Scoring Model'!$B$5+I24/5*'Scoring Model'!$B$6+J24/5*'Scoring Model'!$B$7+K24/5*'Scoring Model'!$B$8+L24/5*'Scoring Model'!$B$9+M24/5*'Scoring Model'!$B$10+N24/5*'Scoring Model'!$B$11)*100 -> 57 | H24: 5 | I24: 2 | J24: 2 | K24: 2 | L24: 2 | M24: 3 | N24: 4 | O24: Only partial Worldpay volume reported | P24: Proprietary / mature | Q24: Unknown | R24: Payments share expansion and hardware | S24: Quantify the 20% Worldpay footprint, renewal dates, licensed-store scope and Verifone lifecycle. | T24: Proprietary/VF PWC; Verifone | V24: Internal baseline only
A25: 21 | B25: P3 | C25: LITTLE CAESARS ENTERPRISE INC | D25: Avery Churchwell | E25: Tier 1 | F25: 4200 | G25: =(H25/5*'Scoring Model'!$B$5+I25/5*'Scoring Model'!$B$6+J25/5*'Scoring Model'!$B$7+K25/5*'Scoring Model'!$B$8+L25/5*'Scoring Model'!$B$9+M25/5*'Scoring Model'!$B$10+N25/5*'Scoring Model'!$B$11)*100 -> 56 | H25: 5 | I25: 2 | J25: 2 | K25: 1 | L25: 2 | M25: 4 | N25: 3 | O25: Relationship is active enough for technical-support interaction, but commercial follow-up is stalled: Avery reported three open items and no response to repeated emails for roughly a week and a half. | P25: Proprietary / entrenched | Q25: Unknown | R25: Payments, DMB, franchise and data adjacency | S25: Use the existing technical-support interaction to re-establish responsiveness, consolidate the three outstanding requests into one owner/action list, and map CaesarVision, payments renewal, DMB and franchise exceptions without leading with generic POS displacement. | T25: CaesarVision; Verifone; Mashgin | U25: Avery reported three items awaiting follow-up and no response to emails for approximately 1.5 weeks, despite participating in a technical-support call with the account earlier that week. | V25: High RM interaction evidence dated 2026-09-04 / commercial trigger unverified
A26: 22 | B26: P3 | C26: BLACK BEAR DINER | D26: Avery Churchwell | E26: Tier 2 | F26: 217 | G26: =(H26/5*'Scoring Model'!$B$5+I26/5*'Scoring Model'!$B$6+J26/5*'Scoring Model'!$B$7+K26/5*'Scoring Model'!$B$8+L26/5*'Scoring Model'!$B$9+M26/5*'Scoring Model'!$B$10+N26/5*'Scoring Model'!$B$11)*100 -> 55 | H26: 3 | I26: 3 | J26: 2 | K26: 2 | L26: 3 | M26: 3 | N26: 4 | O26: Transitioned toward Toast; Olo catering evidence | P26: Recently changed / deploying | Q26: Unknown | R26: Retain payments + adjacent gaps | S26: Confirm Toast deployment scope and whether Worldpay became unmanaged; map Olo modules and remaining corporate/franchise gaps. | T26: Toast; Olo | V26: Mixed / see ledger
A27: 23 | B27: P3 | C27: DOMINO'S PIZZA | D27: Stacie Davis | E27: Tier 1 | F27: 7000 | G27: =(H27/5*'Scoring Model'!$B$5+I27/5*'Scoring Model'!$B$6+J27/5*'Scoring Model'!$B$7+K27/5*'Scoring Model'!$B$8+L27/5*'Scoring Model'!$B$9+M27/5*'Scoring Model'!$B$10+N27/5*'Scoring Model'!$B$11)*100 -> 53 | H27: 5 | I27: 2 | J27: 2 | K27: 1 | L27: 2 | M27: 3 | N27: 3 | O27: Proprietary estate; no open trigger verified | P27: Proprietary / entrenched | Q27: Unknown | R27: Payments, hardware and franchise adjacency | S27: Confirm ACI/Cybersource tenure, processor split and franchise technology control. | T27: Proprietary; ACI/Cybersource; Ingenico | V27: Internal baseline only
A28: 24 | B28: P3 | C28: FIREHOUSE RESTAURANT | D28: Brian Wood | E28: Tier 2 | F28: 1200 | G28: =(H28/5*'Scoring Model'!$B$5+I28/5*'Scoring Model'!$B$6+J28/5*'Scoring Model'!$B$7+K28/5*'Scoring Model'!$B$8+L28/5*'Scoring Model'!$B$9+M28/5*'Scoring Model'!$B$10+N28/5*'Scoring Model'!$B$11)*100 -> 52 | H28: 4 | I28: 2 | J28: 2 | K28: 2 | L28: 2 | M28: 3 | N28: 3 | O28: Toast relationship appears strategic | P28: Established / strategic | Q28: No adverse signal | R28: Franchise payments and adjacent whitespace | S28: Confirm Toast modules and RBI governance; focus only on uncovered layers/franchise exceptions. | T28: Toast; eGiftify | V28: Internal baseline only
A29: 25 | B29: P3 | C29: BOYNE USA INC | D29: Avery Churchwell | E29: Tier 2 | F29: 17 | G29: =(H29/5*'Scoring Model'!$B$5+I29/5*'Scoring Model'!$B$6+J29/5*'Scoring Model'!$B$7+K29/5*'Scoring Model'!$B$8+L29/5*'Scoring Model'!$B$9+M29/5*'Scoring Model'!$B$10+N29/5*'Scoring Model'!$B$11)*100 -> 50 | H29: 2 | I29: 2 | J29: 2 | K29: 3 | L29: 2 | M29: 4 | N29: 3 | O29: No trigger verified | P29: Established mixed hospitality stack | Q29: Unknown | R29: Resort commerce consolidation | S29: Map Agilysys, RTP, Mashgin and Flaik by venue/property; confirm renewal dates. | T29: Agilysys; RTP; FreedomPay; Mashgin; Flaik | V29: Internal baseline only
A30: 26 | B30: P3 | C30: SLIM CHICKENS | D30: Avery Churchwell | E30: Tier 2 | F30: 250 | G30: =(H30/5*'Scoring Model'!$B$5+I30/5*'Scoring Model'!$B$6+J30/5*'Scoring Model'!$B$7+K30/5*'Scoring Model'!$B$8+L30/5*'Scoring Model'!$B$9+M30/5*'Scoring Model'!$B$10+N30/5*'Scoring Model'!$B$11)*100 -> 48 | H30: 3 | I30: 2 | J30: 2 | K30: 3 | L30: 1 | M30: 3 | N30: 2 | O30: Worldpay remains renewed through the reported three-year term. A Slim Chickens contact told Avery she plans to attend the FSTEC happy hour; RDS remains the required channel path. | P30: Established and expanding digital | Q30: Payments retained; Olo remains entrenched | R30: RDS-led relationship map; no active displacement trigger | S30: Avery to connect the attending Slim Chickens contact with Todd and the onsite Genius team for FSTEC; coordinate all follow-up with RDS and use the meeting to validate stakeholders and customer-defined modular needs, not to force a displacement pitch. | T30: PAR Brink; Olo Ordering/Dispatch/Rails/Switchboard/Sync | U30: Avery has a Slim Chickens contact expected at the FSTEC happy hour and will provide Genius attendee contact information because she will be in Europe. Todd is already working through RDS, which both parties agreed is the best joint route into Slim Chickens and Freddy's. | V30: High RM/channel intelligence dated 2026-09-04
A31: 27 | B31: P3 | C31: Barbara B Mann PAH | D31: Brian Wood | E31: Tier 2 | G31: =(H31/5*'Scoring Model'!$B$5+I31/5*'Scoring Model'!$B$6+J31/5*'Scoring Model'!$B$7+K31/5*'Scoring Model'!$B$8+L31/5*'Scoring Model'!$B$9+M31/5*'Scoring Model'!$B$10+N31/5*'Scoring Model'!$B$11)*100 -> 46 | H31: 1 | I31: 2 | J31: 1 | K31: 3 | L31: 2 | M31: 5 | N31: 3 | O31: No trigger verified | P31: Unknown | Q31: Unknown | R31: Venue commerce discovery | S31: Resolve legal entity/venue scope and validate Cybersource/ecommerce footprint. | T31: Cybersource | V31: Internal baseline only
A32: 28 | B32: P3 | C32: STATION CASINO | D32: Avery Churchwell | E32: Tier 2 | F32: 18 | G32: =(H32/5*'Scoring Model'!$B$5+I32/5*'Scoring Model'!$B$6+J32/5*'Scoring Model'!$B$7+K32/5*'Scoring Model'!$B$8+L32/5*'Scoring Model'!$B$9+M32/5*'Scoring Model'!$B$10+N32/5*'Scoring Model'!$B$11)*100 -> 46 | H32: 2 | I32: 2 | J32: 2 | K32: 3 | L32: 2 | M32: 3 | N32: 2 | O32: No trigger verified | P32: Established hospitality stack | Q32: Unknown | R32: Venue payments and commerce adjacency | S32: Validate Agilysys/FreedomPay contract dates and venue expansion plans. | T32: Agilysys; FreedomPay; OnDemand | V32: Internal baseline only
A33: 29 | B33: P3 | C33: LATRELLES MANAGEMENT CORP (Bullritos) | D33: Avery Churchwell | E33: Tier 2 | F33: 35 | G33: =(H33/5*'Scoring Model'!$B$5+I33/5*'Scoring Model'!$B$6+J33/5*'Scoring Model'!$B$7+K33/5*'Scoring Model'!$B$8+L33/5*'Scoring Model'!$B$9+M33/5*'Scoring Model'!$B$10+N33/5*'Scoring Model'!$B$11)*100 -> 45 | H33: 1 | I33: 2 | J33: 2 | K33: 3 | L33: 2 | M33: 4 | N33: 2 | O33: No trigger verified | P33: Established NCR | Q33: Unknown | R33: Mid-market POS/payments modernization | S33: Validate current estate and buying authority. | T33: NCR Aloha; NCR Connected Payments | V33: Internal baseline only
A34: 30 | B34: P3 | C34: FESTIVA REAL ESTATE HOLDINGS | D34: Brian Wood | E34: Tier 2 | G34: =(H34/5*'Scoring Model'!$B$5+I34/5*'Scoring Model'!$B$6+J34/5*'Scoring Model'!$B$7+K34/5*'Scoring Model'!$B$8+L34/5*'Scoring Model'!$B$9+M34/5*'Scoring Model'!$B$10+N34/5*'Scoring Model'!$B$11)*100 -> 43 | H34: 1 | I34: 2 | J34: 1 | K34: 3 | L34: 2 | M34: 4 | N34: 3 | O34: Formerly linked to Choice; no active trigger | P34: Established / unclear | Q34: Unknown | R34: Payments discovery | S34: Resolve entity relationship and current payment estate before pursuit. | T34: Shift4 and others | V34: Internal baseline only
A35: 31 | B35: Unranked | C35: Buffalo Wild Wings | F35: 1323 | O35: Added from Worldpay ABM backbook; no verified active buying event. Technomic rank 28; ~1,323 units. Family Dining account from Worldpay backbook. Platform/owner: Inspire Brands. | P35: Worldpay relationship reported; incumbent technology lifecycle not yet verified. | Q35: Qualification required | R35: Enterprise cross-sell / platform qualification | S35: Confirm Worldpay RM, processing scope and renewal dates; map enterprise technology owner and POS/payments decision window. | T35: POS: NCR Voyix partnership renewed July 2025; kds_kitchen_ops: Jolt | V35: Meeting-ready; Worldpay source list + RBB ecosystem research | W35: US DIRECT | X35: US | Y35: Family Dining | Z35: Yes | AG35: ABM WP Target Account List.xlsx — ABM Target Accounts | AH35: Brand / chain | AI35: Brand/system footprint from existing RBB research | AJ35: Medium | AK35: Unconfirmed — ask Worldpay | AL35: Who at Worldpay owns this relationship, what merchant IDs/legal entities are in scope, and is coverage enterprise, franchisee, or a single site?
A36: 32 | B36: Unranked | C36: Coffee Bean & Tea Leaf Ma | F36: 193 | O36: Added from Worldpay ABM backbook; no verified active buying event. Scale not yet verified. Coffee account from Worldpay backbook. Platform/owner: Jollibee Foods Corporation. | P36: Worldpay relationship reported; incumbent technology lifecycle not yet verified. | Q36: Qualification required | R36: Enterprise cross-sell / platform qualification | S36: Confirm Worldpay RM, processing scope and renewal dates; map enterprise technology owner and POS/payments decision window. | V36: Meeting-ready; Worldpay source list + RBB ecosystem research | W36: US DIRECT | X36: US | Y36: Coffee & Beverage | Z36: Yes | AG36: ABM WP Target Account List.xlsx — ABM Target Accounts | https://www.coffeebean.com/store/index.html | AH36: Brand / chain | AI36: U.S. brand footprint | AJ36: High | AK36: Unconfirmed — ask Worldpay | AL36: Who at Worldpay owns this relationship, what merchant IDs/legal entities are in scope, and is coverage enterprise, franchisee, or a single site?
A37: 33 | B37: Unranked | C37: International Coffee & Tea Llc | O37: Added from Worldpay ABM backbook; no verified active buying event. | P37: Worldpay relationship reported; incumbent technology lifecycle not yet verified. | Q37: Qualification required | R37: Entity validation before pursuit | S37: Confirm entity identity and central buying authority before investing pursuit time; park if this is a single-location merchant. | V37: Partial; Worldpay source list + RBB ecosystem research | W37: US DIRECT | X37: US | Y37: Coffee & Beverage | Z37: Yes | AG37: ABM WP Target Account List.xlsx — ABM Target Accounts | AH37: Legal entity / franchisee / site record | AI37: WP merchant/entity footprint—not safe to infer from brand | AJ37: Needs WP confirmation | AK37: Unconfirmed — ask Worldpay | AL37: Who at Worldpay owns this relationship, what merchant IDs/legal entities are in scope, and is coverage enterprise, franchisee, or a single site?
A38: 34 | B38: Unranked | C38: Culver'S | F38: 997 | O38: Added from Worldpay ABM backbook; no verified active buying event. Technomic rank 29; ~997 units. Burger account from Worldpay backbook. Platform/owner: Culver Franchising System. | P38: Worldpay relationship reported; incumbent technology lifecycle not yet verified. | Q38: Qualification required | R38: Enterprise cross-sell / platform qualification | S38: Confirm Worldpay RM, processing scope and renewal dates; map enterprise technology owner and POS/payments decision window. | T38: POS: PAR Technology (Brink); POS Hardware: PAR; kds_kitchen_ops: Jolt | V38: Meeting-ready; Worldpay source list + RBB ecosystem research | W38: US DIRECT | X38: US | Y38: Burger | Z38: Yes | AA38: N | AG38: ABM WP Target Account List.xlsx — ABM Target Accounts | AH38: Brand / chain | AI38: Brand/system footprint from existing RBB research | AJ38: Medium | AK38: Unconfirmed — ask Worldpay | AL38: Who at Worldpay owns this relationship, what merchant IDs/legal entities are in scope, and is coverage enterprise, franchisee, or a single site?
A39: 35 | B39: Unranked | C39: Caribou Coffee #1243 | F39: 800 | O39: Added from Worldpay ABM backbook; no verified active buying event. Scale not yet verified. Coffee account from Worldpay backbook. Platform/owner: JAB beverage platform. | P39: Worldpay relationship reported; incumbent technology lifecycle not yet verified. | Q39: Qualification required | R39: Enterprise cross-sell / platform qualification | S39: Confirm Worldpay RM, processing scope and renewal dates; map enterprise technology owner and POS/payments decision window. | V39: Partial; Worldpay source list + RBB ecosystem research | W39: US DIRECT | X39: US | Y39: Coffee & Beverage | Z39: Yes | AG39: ABM WP Target Account List.xlsx — ABM Target Accounts | https://www.cariboucoffee.com/about-us/ | AH39: Legal entity / franchisee / site record | AI39: Global brand footprint; WP row may be one merchant/site | AJ39: Medium | AK39: Unconfirmed — ask Worldpay | AL39: Who at Worldpay owns this relationship, what merchant IDs/legal entities are in scope, and is coverage enterprise, franchisee, or a single site?
A40: 36 | B40: Unranked | C40: Jamba Juice | F40: 720 | O40: Added from Worldpay ABM backbook; no verified active buying event. Scale not yet verified. Coffee account from Worldpay backbook. Platform/owner: GoTo Foods. | P40: Worldpay relationship reported; incumbent technology lifecycle not yet verified. | Q40: Qualification required | R40: Enterprise cross-sell / platform qualification | S40: Confirm Worldpay RM, processing scope and renewal dates; map enterprise technology owner and POS/payments decision window. | V40: Meeting-ready; Worldpay source list + RBB ecosystem research | W40: US DIRECT | X40: US | Y40: Juice / Smoothie | Z40: Yes | AG40: ABM WP Target Account List.xlsx — ABM Target Accounts | https://locations.jamba.com/ | AH40: Brand / chain | AI40: U.S. brand footprint | AJ40: High | AK40: Unconfirmed — ask Worldpay | AL40: Who at Worldpay owns this relationship, what merchant IDs/legal entities are in scope, and is coverage enterprise, franchisee, or a single site?
A41: 37 | B41: Unranked | C41: Moes Southwest Grill | F41: 596 | O41: Added from Worldpay ABM backbook; no verified active buying event. Technomic rank 78; ~596 units. Mexican account from Worldpay backbook. Platform/owner: GoTo Foods. | P41: Worldpay relationship reported; incumbent technology lifecycle not yet verified. | Q41: Qualification required | R41: Enterprise cross-sell / platform qualification | S41: Confirm Worldpay RM, processing scope and renewal dates; map enterprise technology owner and POS/payments decision window. | T41: Loyalty: PAR Technology (Punchh); kiosks: Nextep Systems | V41: Meeting-ready; Worldpay source list + RBB ecosystem research | W41: US DIRECT | X41: US | Y41: Mexican | Z41: Yes | AG41: ABM WP Target Account List.xlsx — ABM Target Accounts | AH41: Brand / chain | AI41: Brand/system footprint from existing RBB research | AJ41: Medium | AK41: Unconfirmed — ask Worldpay | AL41: Who at Worldpay owns this relationship, what merchant IDs/legal entities are in scope, and is coverage enterprise, franchisee, or a single site?
A42: 38 | B42: Unranked | C42: American Blue Ribbon Holdings | O42: Added from Worldpay ABM backbook; no verified active buying event. Scale not yet verified. Family Dining account from Worldpay backbook. Platform/owner: Multi-brand operator. | P42: Worldpay relationship reported; incumbent technology lifecycle not yet verified. | Q42: Qualification required | R42: Enterprise cross-sell / platform qualification | S42: Confirm Worldpay RM, processing scope and renewal dates; map enterprise technology owner and POS/payments decision window. | V42: Partial; Worldpay source list + RBB ecosystem research | W42: US DIRECT | X42: US | Y42: Restaurant Group / Platform | Z42: Yes | AG42: ABM WP Target Account List.xlsx — ABM Target Accounts | AH42: Restaurant group / platform | AI42: WP merchant/entity footprint—not safe to infer from brand | AJ42: Needs WP confirmation | AK42: Unconfirmed — ask Worldpay | AL42: Who at Worldpay owns this relationship, what merchant IDs/legal entities are in scope, and is coverage enterprise, franchisee, or a single site?
A43: 39 | B43: Unranked | C43: Ben & Jerry'S | F43: 148 | O43: Added from Worldpay ABM backbook; no verified active buying event. Technomic rank 363; ~148 units. Dessert account from Worldpay backbook. | P43: Worldpay relationship reported; incumbent technology lifecycle not yet verified. | Q43: Qualification required | R43: Enterprise cross-sell / platform qualification | S43: Confirm Worldpay RM, processing scope and renewal dates; map enterprise technology owner and POS/payments decision window. | V43: Meeting-ready; Worldpay source list + RBB ecosystem research | W43: US DIRECT | X43: US | Y43: Dessert | Z43: Yes | AG43: ABM WP Target Account List.xlsx — ABM Target Accounts | AH43: Brand / chain | AI43: Brand/system footprint from existing RBB research | AJ43: Medium | AK43: Unconfirmed — ask Worldpay | AL43: Who at Worldpay owns this relationship, what merchant IDs/legal entities are in scope, and is coverage enterprise, franchisee, or a single site?
A44: 40 | B44: Unranked | C44: Mcalisters Deli | F44: 560 | O44: Added from Worldpay ABM backbook; no verified active buying event. Technomic rank 59; ~560 units. Sandwich account from Worldpay backbook. Platform/owner: GoTo Foods. | P44: Worldpay relationship reported; incumbent technology lifecycle not yet verified. | Q44: Qualification required | R44: Enterprise cross-sell / platform qualification | S44: Confirm Worldpay RM, processing scope and renewal dates; map enterprise technology owner and POS/payments decision window. | T44: Loyalty: PAR Technology (Punchh) | V44: Meeting-ready; Worldpay source list + RBB ecosystem research | W44: US DIRECT | X44: US | Y44: Sandwich | Z44: Yes | AG44: ABM WP Target Account List.xlsx — ABM Target Accounts | AH44: Brand / chain | AI44: Brand/system footprint from existing RBB research | AJ44: Medium | AK44: Unconfirmed — ask Worldpay | AL44: Who at Worldpay owns this relationship, what merchant IDs/legal entities are in scope, and is coverage enterprise, franchisee, or a single site?
A45: 41 | B45: Unranked | C45: Hungry Howies | F45: 500 | O45: Added from Worldpay ABM backbook; no verified active buying event. | P45: Worldpay relationship reported; incumbent technology lifecycle not yet verified. | Q45: Qualification required | R45: Qualification / relationship mapping | S45: Validate corporate scale, buying authority, current POS/payments stack and whether the Worldpay relationship is enterprise or franchise-level. | V45: Partial; Worldpay source list + RBB ecosystem research | W45: US DIRECT | X45: US | Y45: Pizza | Z45: Yes | AG45: ABM WP Target Account List.xlsx — ABM Target Accounts | https://hungryhowies.com/about-us | AH45: Brand / chain | AI45: Approximate U.S. brand footprint | AJ45: High | AK45: Unconfirmed — ask Worldpay | AL45: Who at Worldpay owns this relationship, what merchant IDs/legal entities are in scope, and is coverage enterprise, franchisee, or a single site?
A46: 42 | B46: Unranked | C46: Aurify Brands, Llc | O46: Added from Worldpay ABM backbook; no verified active buying event. Scale not yet verified. Foodservice account from Worldpay backbook. Platform/owner: Multi-brand operator. | P46: Worldpay relationship reported; incumbent technology lifecycle not yet verified. | Q46: Qualification required | R46: Enterprise cross-sell / platform qualification | S46: Confirm Worldpay RM, processing scope and renewal dates; map enterprise technology owner and POS/payments decision window. | V46: Partial; Worldpay source list + RBB ecosystem research | W46: US DIRECT | X46: US | Y46: Restaurant Group / Platform | Z46: Yes | AG46: ABM WP Target Account List.xlsx — ABM Target Accounts | AH46: Restaurant group / platform | AI46: WP merchant/entity footprint—not safe to infer from brand | AJ46: Needs WP confirmation | AK46: Unconfirmed — ask Worldpay | AL46: Who at Worldpay owns this relationship, what merchant IDs/legal entities are in scope, and is coverage enterprise, franchisee, or a single site?
A47: 43 | B47: Unranked | C47: Peet'S Coffee & Tea | O47: Added from Worldpay ABM backbook; no verified active buying event. Scale not yet verified. Coffee account from Worldpay backbook. Platform/owner: JDE Peet's / JAB. | P47: Worldpay relationship reported; incumbent technology lifecycle not yet verified. | Q47: Qualification required | R47: Enterprise cross-sell / platform qualification | S47: Confirm Worldpay RM, processing scope and renewal dates; map enterprise technology owner and POS/payments decision window. | V47: Partial; Worldpay source list + RBB ecosystem research | W47: US DIRECT | X47: US | Y47: Coffee & Beverage | Z47: Yes | AG47: ABM WP Target Account List.xlsx — ABM Target Accounts | AH47: Brand / chain | AI47: Brand footprint not yet verified | AJ47: Needs research | AK47: Unconfirmed — ask Worldpay | AL47: Who at Worldpay owns this relationship, what merchant IDs/legal entities are in scope, and is coverage enterprise, franchisee, or a single site?
A48: 44 | B48: Unranked | C48: Yum Yum Donuts | O48: Added from Worldpay ABM backbook; no verified active buying event. | P48: Worldpay relationship reported; incumbent technology lifecycle not yet verified. | Q48: Qualification required | R48: Qualification / relationship mapping | S48: Validate corporate scale, buying authority, current POS/payments stack and whether the Worldpay relationship is enterprise or franchise-level. | V48: Partial; Worldpay source list + RBB ecosystem research | W48: US DIRECT | X48: US | Y48: Bakery / Dessert | Z48: Yes | AG48: ABM WP Target Account List.xlsx — ABM Target Accounts | AH48: Brand / chain | AI48: Brand footprint not yet verified | AJ48: Needs research | AK48: Unconfirmed — ask Worldpay | AL48: Who at Worldpay owns this relationship, what merchant IDs/legal entities are in scope, and is coverage enterprise, franchisee, or a single site?
A49: 45 | B49: Unranked | C49: Boston Market | F49: 16 | O49: Added from Worldpay ABM backbook; no verified active buying event. | P49: Worldpay relationship reported; incumbent technology lifecycle not yet verified. | Q49: Qualification required | R49: Entity validation before pursuit | S49: Confirm entity identity and central buying authority before investing pursuit time; park if this is a single-location merchant. | V49: Partial; Worldpay source list + RBB ecosystem research | W49: US DIRECT | X49: US | Y49: QSR — Chicken | Z49: No | AA49: N | AB49: Attrition | AG49: ABM WP Target Account List.xlsx — ABM Target Accounts | AH49: Brand / chain | AI49: Brand/system footprint from existing RBB research | AJ49: Medium | AK49: Unconfirmed — ask Worldpay | AL49: Who at Worldpay owns this relationship, what merchant IDs/legal entities are in scope, and is coverage enterprise, franchisee, or a single site?
A50: 46 | B50: Unranked | C50: Carvel | F50: 374 | O50: Added from Worldpay ABM backbook; no verified active buying event. Scale not yet verified. Dessert account from Worldpay backbook. Platform/owner: GoTo Foods. | P50: Worldpay relationship reported; incumbent technology lifecycle not yet verified. | Q50: Qualification required | R50: Enterprise cross-sell / platform qualification | S50: Confirm Worldpay RM, processing scope and renewal dates; map enterprise technology owner and POS/payments decision window. | V50: Meeting-ready; Worldpay source list + RBB ecosystem research | W50: US DIRECT | X50: US | Y50: Dessert / Ice Cream | Z50: Yes | AG50: ABM WP Target Account List.xlsx — ABM Target Accounts | https://locations.carvel.com/ | AH50: Brand / chain | AI50: U.S. brand footprint | AJ50: High | AK50: Unconfirmed — ask Worldpay | AL50: Who at Worldpay owns this relationship, what merchant IDs/legal entities are in scope, and is coverage enterprise, franchisee, or a single site?
A51: 47 | B51: Unranked | C51: Sarku Japan | F51: 137 | O51: Added from Worldpay ABM backbook; no verified active buying event. Technomic rank 261; ~137 units. Asian account from Worldpay backbook. | P51: Worldpay relationship reported; incumbent technology lifecycle not yet verified. | Q51: Qualification required | R51: Enterprise cross-sell / platform qualification | S51: Confirm Worldpay RM, processing scope and renewal dates; map enterprise technology owner and POS/payments decision window. | V51: Meeting-ready; Worldpay source list + RBB ecosystem research | W51: US DIRECT | X51: US | Y51: Fast Casual — Asian | Z51: Yes | AG51: ABM WP Target Account List.xlsx — ABM Target Accounts | AH51: Brand / chain | AI51: Brand/system footprint from existing RBB research | AJ51: Medium | AK51: Unconfirmed — ask Worldpay | AL51: Who at Worldpay owns this relationship, what merchant IDs/legal entities are in scope, and is coverage enterprise, franchisee, or a single site?
A52: 48 | B52: Unranked | C52: Fazolis | F52: 196 | O52: Added from Worldpay ABM backbook; no verified active buying event. Technomic rank 165; ~196 units. Family Dining account from Worldpay backbook. Platform/owner: FAT Brands. | P52: Worldpay relationship reported; incumbent technology lifecycle not yet verified. | Q52: Qualification required | R52: Enterprise cross-sell / platform qualification | S52: Confirm Worldpay RM, processing scope and renewal dates; map enterprise technology owner and POS/payments decision window. | T52: Online Ordering: Olo — Olo (historical scoped evidence); POS: PAR Technology (Brink); POS Hardware: PAR Technology (Hardware / Break Fix); Loyalty: PAR Technology (Punchh); drive_thru_ai: ConverseNow | V52: Meeting-ready; Worldpay source list + RBB ecosystem research | W52: US DIRECT | X52: US | Y52: Fast Casual — Italian | Z52: Yes | AG52: ABM WP Target Account List.xlsx — ABM Target Accounts | AH52: Brand / chain | AI52: Brand/system footprint from existing RBB research | AJ52: Medium | AK52: Unconfirmed — ask Worldpay | AL52: Who at Worldpay owns this relationship, what merchant IDs/legal entities are in scope, and is coverage enterprise, franchisee, or a single site?
A53: 49 | B53: Unranked | C53: Ruby Tuesday | F53: 212 | O53: Added from Worldpay ABM backbook; no verified active buying event. Technomic rank 159; ~212 units. Full-Service Dining account from Worldpay backbook. | P53: Worldpay relationship reported; incumbent technology lifecycle not yet verified. | Q53: Qualification required | R53: Enterprise cross-sell / platform qualification | S53: Confirm Worldpay RM, processing scope and renewal dates; map enterprise technology owner and POS/payments decision window. | V53: Meeting-ready; Worldpay source list + RBB ecosystem research | W53: US DIRECT | X53: US | Y53: Casual Dining | Z53: Yes | AA53: N | AG53: ABM WP Target Account List.xlsx — ABM Target Accounts | AH53: Brand / chain | AI53: Brand/system footprint from existing RBB research | AJ53: Medium | AK53: Unconfirmed — ask Worldpay | AL53: Who at Worldpay owns this relationship, what merchant IDs/legal entities are in scope, and is coverage enterprise, franchisee, or a single site?
A54: 50 | B54: Unranked | C54: Orange Leaf | O54: Added from Worldpay ABM backbook; no verified active buying event. | P54: Worldpay relationship reported; incumbent technology lifecycle not yet verified. | Q54: Qualification required | R54: Qualification / relationship mapping | S54: Validate corporate scale, buying authority, current POS/payments stack and whether the Worldpay relationship is enterprise or franchise-level. | V54: Entity validation needed; Worldpay source list + RBB ecosystem research | W54: US DIRECT | X54: US | Y54: Dessert / Frozen Yogurt | Z54: Yes | AG54: ABM WP Target Account List.xlsx — ABM Target Accounts | AH54: Brand / chain | AI54: Brand footprint not yet verified | AJ54: Needs research | AK54: Unconfirmed — ask Worldpay | AL54: Who at Worldpay owns this relationship, what merchant IDs/legal entities are in scope, and is coverage enterprise, franchisee, or a single site?
A55: 51 | B55: Unranked | C55: Wow Bao Llc | O55: Added from Worldpay ABM backbook; no verified active buying event. | P55: Worldpay relationship reported; incumbent technology lifecycle not yet verified. | Q55: Qualification required | R55: Entity validation before pursuit | S55: Confirm entity identity and central buying authority before investing pursuit time; park if this is a single-location merchant. | V55: Partial; Worldpay source list + RBB ecosystem research | W55: US | X55: US | Y55: Fast Casual — Asian | Z55: Yes | AG55: ABM WP Target Account List.xlsx — ABM Target Accounts | AH55: Legal entity / franchisee / site record | AI55: WP merchant/entity footprint—not safe to infer from brand | AJ55: Needs WP confirmation | AK55: Unconfirmed — ask Worldpay | AL55: Who at Worldpay owns this relationship, what merchant IDs/legal entities are in scope, and is coverage enterprise, franchisee, or a single site?
A56: 52 | B56: Unranked | C56: Bruegger'S Enterprises In | F56: 181 | O56: Added from Worldpay ABM backbook; no verified active buying event. | P56: Worldpay relationship reported; incumbent technology lifecycle not yet verified. | Q56: Qualification required | R56: Entity validation before pursuit | S56: Confirm entity identity and central buying authority before investing pursuit time; park if this is a single-location merchant. | V56: Partial; Worldpay source list + RBB ecosystem research | W56: US DIRECT | X56: US | Y56: Bakery / Breakfast | Z56: Yes | AG56: ABM WP Target Account List.xlsx — ABM Target Accounts | https://www.brueggers.com/wp-content/uploads/2024/06/BB-ESG-Report-2023.pdf | AH56: Legal entity / franchisee / site record | AI56: Brand footprint; reported Oct. 2023 | AJ56: Medium | AK56: Unconfirmed — ask Worldpay | AL56: Who at Worldpay owns this relationship, what merchant IDs/legal entities are in scope, and is coverage enterprise, franchisee, or a single site?
A57: 53 | B57: Unranked | C57: Honey Dew Donuts | F57: 108 | O57: Added from Worldpay ABM backbook; no verified active buying event. Technomic rank 577; ~108 units. Coffee account from Worldpay backbook. | P57: Worldpay relationship reported; incumbent technology lifecycle not yet verified. | Q57: Qualification required | R57: Enterprise cross-sell / platform qualification | S57: Confirm Worldpay RM, processing scope and renewal dates; map enterprise technology owner and POS/payments decision window. | T57: Loyalty: PAR Technology (Punchh) | V57: Meeting-ready; Worldpay source list + RBB ecosystem research | W57: US DIRECT | X57: US | Y57: Coffee / Bakery | Z57: Yes | AG57: ABM WP Target Account List.xlsx — ABM Target Accounts | AH57: Brand / chain | AI57: Brand/system footprint from existing RBB research | AJ57: Medium | AK57: Unconfirmed — ask Worldpay | AL57: Who at Worldpay owns this relationship, what merchant IDs/legal entities are in scope, and is coverage enterprise, franchisee, or a single site?
A58: 54 | B58: Unranked | C58: Logan'S Roadhouse | F58: 125 | O58: Added from Worldpay ABM backbook; no verified active buying event. | P58: Worldpay relationship reported; incumbent technology lifecycle not yet verified. | Q58: Qualification required | R58: Entity validation before pursuit | S58: Confirm entity identity and central buying authority before investing pursuit time; park if this is a single-location merchant. | T58: Loyalty: PAR Technology (Punchh) | V58: Meeting-ready; Worldpay source list + RBB ecosystem research | W58: US DIRECT | X58: US | Y58: Casual Dining — Steakhouse | Z58: No | AG58: ABM WP Target Account List.xlsx — ABM Target Accounts | AH58: Brand / chain | AI58: Brand/system footprint from existing RBB research | AJ58: Medium | AK58: Unconfirmed — ask Worldpay | AL58: Who at Worldpay owns this relationship, what merchant IDs/legal entities are in scope, and is coverage enterprise, franchisee, or a single site?
A59: 55 | B59: Unranked | C59: Famous Dave'S Bbq | O59: Added from Worldpay ABM backbook; no verified active buying event. | P59: Worldpay relationship reported; incumbent technology lifecycle not yet verified. | Q59: Qualification required | R59: Qualification / relationship mapping | S59: Validate corporate scale, buying authority, current POS/payments stack and whether the Worldpay relationship is enterprise or franchise-level. | V59: Partial; Worldpay source list + RBB ecosystem research | W59: US DIRECT | X59: US | Y59: Casual Dining — Barbecue | Z59: Yes | AG59: ABM WP Target Account List.xlsx — ABM Target Accounts | AH59: Brand / chain | AI59: Brand footprint not yet verified | AJ59: Needs research | AK59: Unconfirmed — ask Worldpay | AL59: Who at Worldpay owns this relationship, what merchant IDs/legal entities are in scope, and is coverage enterprise, franchisee, or a single site?
A60: 56 | B60: Unranked | C60: Friendly Ice Cream #7776 | O60: Added from Worldpay ABM backbook; no verified active buying event. | P60: Worldpay relationship reported; incumbent technology lifecycle not yet verified. | Q60: Qualification required | R60: Entity validation before pursuit | S60: Confirm entity identity and central buying authority before investing pursuit time; park if this is a single-location merchant. | V60: Partial; Worldpay source list + RBB ecosystem research | W60: US DIRECT | X60: US | Y60: Family Dining / Dessert | Z60: Yes | AG60: ABM WP Target Account List.xlsx — ABM Target Accounts | AH60: Legal entity / franchisee / site record | AI60: WP merchant/entity footprint—not safe to infer from brand | AJ60: Needs WP confirmation | AK60: Unconfirmed — ask Worldpay | AL60: Who at Worldpay owns this relationship, what merchant IDs/legal entities are in scope, and is coverage enterprise, franchisee, or a single site?
A61: 57 | B61: Unranked | C61: Hwy 55 Burgers Shakes & F | O61: Added from Worldpay ABM backbook; no verified active buying event. | P61: Worldpay relationship reported; incumbent technology lifecycle not yet verified. | Q61: Qualification required | R61: Qualification / relationship mapping | S61: Validate corporate scale, buying authority, current POS/payments stack and whether the Worldpay relationship is enterprise or franchise-level. | V61: Partial; Worldpay source list + RBB ecosystem research | W61: US DIRECT | X61: US | Y61: Fast Casual — Burger | Z61: Yes | AG61: ABM WP Target Account List.xlsx — ABM Target Accounts | AH61: Brand / chain | AI61: Brand footprint not yet verified | AJ61: Needs research | AK61: Unconfirmed — ask Worldpay | AL61: Who at Worldpay owns this relationship, what merchant IDs/legal entities are in scope, and is coverage enterprise, franchisee, or a single site?
A62: 58 | B62: Unranked | C62: Tijuana Flats | F62: 91 | O62: Added from Worldpay ABM backbook; no verified active buying event. | P62: Worldpay relationship reported; incumbent technology lifecycle not yet verified. | Q62: Qualification required | R62: Entity validation before pursuit | S62: Confirm entity identity and central buying authority before investing pursuit time; park if this is a single-location merchant. | T62: Loyalty: PAR Technology (Punchh) | V62: Meeting-ready; Worldpay source list + RBB ecosystem research | W62: US DIRECT | X62: US | Y62: Fast Casual — Mexican | Z62: No | AA62: N | AB62: Attrition | AG62: ABM WP Target Account List.xlsx — ABM Target Accounts | AH62: Brand / chain | AI62: Brand/system footprint from existing RBB research | AJ62: Medium | AK62: Unconfirmed — ask Worldpay | AL62: Who at Worldpay owns this relationship, what merchant IDs/legal entities are in scope, and is coverage enterprise, franchisee, or a single site?
A63: 59 | B63: Unranked | C63: Shoneys | F63: 57 | O63: Added from Worldpay ABM backbook; no verified active buying event. | P63: Worldpay relationship reported; incumbent technology lifecycle not yet verified. | Q63: Qualification required | R63: Qualification / relationship mapping | S63: Validate corporate scale, buying authority, current POS/payments stack and whether the Worldpay relationship is enterprise or franchise-level. | V63: Meeting-ready; Worldpay source list + RBB ecosystem research | W63: US DIRECT | X63: US | Y63: Family Dining | Z63: Yes | AG63: ABM WP Target Account List.xlsx — ABM Target Accounts | AH63: Brand / chain | AI63: Brand/system footprint from existing RBB research | AJ63: Medium | AK63: Unconfirmed — ask Worldpay | AL63: Who at Worldpay owns this relationship, what merchant IDs/legal entities are in scope, and is coverage enterprise, franchisee, or a single site?
A64: 60 | B64: Unranked | C64: Frischs | O64: Added from Worldpay ABM backbook; no verified active buying event. | P64: Worldpay relationship reported; incumbent technology lifecycle not yet verified. | Q64: Qualification required | R64: Qualification / relationship mapping | S64: Validate corporate scale, buying authority, current POS/payments stack and whether the Worldpay relationship is enterprise or franchise-level. | V64: Partial; Worldpay source list + RBB ecosystem research | W64: US DIRECT | X64: US | Y64: Family Dining / Burger | Z64: Yes | AG64: ABM WP Target Account List.xlsx — ABM Target Accounts | AH64: Brand / chain | AI64: Brand footprint not yet verified | AJ64: Needs research | AK64: Unconfirmed — ask Worldpay | AL64: Who at Worldpay owns this relationship, what merchant IDs/legal entities are in scope, and is coverage enterprise, franchisee, or a single site?
A65: 61 | B65: Unranked | C65: Chuy'S | F65: 104 | O65: Added from Worldpay ABM backbook; no verified active buying event. Technomic rank 110; ~104 units. Mexican account from Worldpay backbook. | P65: Worldpay relationship reported; incumbent technology lifecycle not yet verified. | Q65: Qualification required | R65: Enterprise cross-sell / platform qualification | S65: Confirm Worldpay RM, processing scope and renewal dates; map enterprise technology owner and POS/payments decision window. | T65: Back Office: PAR Technology (Data Central) | V65: Meeting-ready; Worldpay source list + RBB ecosystem research | W65: US DIRECT | X65: US | Y65: Casual Dining — Mexican | Z65: Yes | AG65: ABM WP Target Account List.xlsx — ABM Target Accounts | AH65: Brand / chain | AI65: Brand/system footprint from existing RBB research | AJ65: Medium | AK65: Unconfirmed — ask Worldpay | AL65: Who at Worldpay owns this relationship, what merchant IDs/legal entities are in scope, and is coverage enterprise, franchisee, or a single site?
A66: 62 | B66: Unranked | C66: Fuddruckers | F66: 52 | O66: Added from Worldpay ABM backbook; no verified active buying event. | P66: Worldpay relationship reported; incumbent technology lifecycle not yet verified. | Q66: Qualification required | R66: Qualification / relationship mapping | S66: Validate corporate scale, buying authority, current POS/payments stack and whether the Worldpay relationship is enterprise or franchise-level. | T66: back_office_operations: Crunchtime | V66: Meeting-ready; Worldpay source list + RBB ecosystem research | W66: US DIRECT | X66: US | Y66: Fast Casual — Burger | Z66: Yes | AG66: ABM WP Target Account List.xlsx — ABM Target Accounts | AH66: Brand / chain | AI66: Brand/system footprint from existing RBB research | AJ66: Medium | AK66: Unconfirmed — ask Worldpay | AL66: Who at Worldpay owns this relationship, what merchant IDs/legal entities are in scope, and is coverage enterprise, franchisee, or a single site?
A67: 63 | B67: Unranked | C67: Gold Star Chili | F67: 59 | O67: Added from Worldpay ABM backbook; no verified active buying event. | P67: Worldpay relationship reported; incumbent technology lifecycle not yet verified. | Q67: Qualification required | R67: Qualification / relationship mapping | S67: Validate corporate scale, buying authority, current POS/payments stack and whether the Worldpay relationship is enterprise or franchise-level. | T67: POS: PAR Technology (Brink); pos: PAR Technology | V67: Meeting-ready; Worldpay source list + RBB ecosystem research | W67: US DIRECT | X67: US | Y67: QSR — Chili / Sandwich | Z67: Yes | AG67: ABM WP Target Account List.xlsx — ABM Target Accounts | AH67: Brand / chain | AI67: Brand/system footprint from existing RBB research | AJ67: Medium | AK67: Unconfirmed — ask Worldpay | AL67: Who at Worldpay owns this relationship, what merchant IDs/legal entities are in scope, and is coverage enterprise, franchisee, or a single site?
A68: 64 | B68: Unranked | C68: Bennigan'S | F68: 6 | O68: Added from Worldpay ABM backbook; no verified active buying event. | P68: Worldpay relationship reported; incumbent technology lifecycle not yet verified. | Q68: Qualification required | R68: Qualification / relationship mapping | S68: Validate corporate scale, buying authority, current POS/payments stack and whether the Worldpay relationship is enterprise or franchise-level. | V68: Partial; Worldpay source list + RBB ecosystem research | W68: US DIRECT | X68: US | Y68: Casual Dining | Z68: Yes | AG68: ABM WP Target Account List.xlsx — ABM Target Accounts | AH68: Brand / chain | AI68: Brand/system footprint from existing RBB research | AJ68: Medium | AK68: Unconfirmed — ask Worldpay | AL68: Who at Worldpay owns this relationship, what merchant IDs/legal entities are in scope, and is coverage enterprise, franchisee, or a single site?
A69: 65 | B69: Unranked | C69: La Madeleine | F69: 91 | O69: Added from Worldpay ABM backbook; no verified active buying event. Technomic rank 213; ~91 units. Full-Service Dining account from Worldpay backbook. | P69: Worldpay relationship reported; incumbent technology lifecycle not yet verified. | Q69: Qualification required | R69: Enterprise cross-sell / platform qualification | S69: Confirm Worldpay RM, processing scope and renewal dates; map enterprise technology owner and POS/payments decision window. | T69: Online Ordering: Olo | V69: Meeting-ready; Worldpay source list + RBB ecosystem research | W69: US DIRECT | X69: US | Y69: Fast Casual — Bakery Café | Z69: Yes | AG69: ABM WP Target Account List.xlsx — ABM Target Accounts | AH69: Brand / chain | AI69: Brand/system footprint from existing RBB research | AJ69: Medium | AK69: Unconfirmed — ask Worldpay | AL69: Who at Worldpay owns this relationship, what merchant IDs/legal entities are in scope, and is coverage enterprise, franchisee, or a single site?
A70: 66 | B70: Unranked | C70: Uno'S | F70: 100 | O70: Added from Worldpay ABM backbook; no verified active buying event. | P70: Worldpay relationship reported; incumbent technology lifecycle not yet verified. | Q70: Qualification required | R70: Qualification / relationship mapping | S70: Validate corporate scale, buying authority, current POS/payments stack and whether the Worldpay relationship is enterprise or franchise-level. | V70: Partial; Worldpay source list + RBB ecosystem research | W70: US DIRECT | X70: US | Y70: Casual Dining — Pizza | Z70: Yes | AG70: ABM WP Target Account List.xlsx — ABM Target Accounts | https://unos.com/about/ | AH70: Brand / chain | AI70: Global brand footprint | AJ70: High | AK70: Unconfirmed — ask Worldpay | AL70: Who at Worldpay owns this relationship, what merchant IDs/legal entities are in scope, and is coverage enterprise, franchisee, or a single site?
A71: 67 | B71: Unranked | C71: Luby'S Restaurants | O71: Added from Worldpay ABM backbook; no verified active buying event. | P71: Worldpay relationship reported; incumbent technology lifecycle not yet verified. | Q71: Qualification required | R71: Qualification / relationship mapping | S71: Validate corporate scale, buying authority, current POS/payments stack and whether the Worldpay relationship is enterprise or franchise-level. | V71: Entity validation needed; Worldpay source list + RBB ecosystem research | W71: US DIRECT | X71: US | Y71: Cafeteria / Family Dining | Z71: Yes | AG71: ABM WP Target Account List.xlsx — ABM Target Accounts | AH71: Brand / chain | AI71: Brand footprint not yet verified | AJ71: Needs research | AK71: Unconfirmed — ask Worldpay | AL71: Who at Worldpay owns this relationship, what merchant IDs/legal entities are in scope, and is coverage enterprise, franchisee, or a single site?
A72: 68 | B72: Unranked | C72: Scramblers | F72: 28 | O72: Added from Worldpay ABM backbook; no verified active buying event. | P72: Worldpay relationship reported; incumbent technology lifecycle not yet verified. | Q72: Qualification required | R72: Qualification / relationship mapping | S72: Validate corporate scale, buying authority, current POS/payments stack and whether the Worldpay relationship is enterprise or franchise-level. | V72: Partial; Worldpay source list + RBB ecosystem research | W72: US DIRECT | X72: US | Y72: Family Dining / Breakfast | Z72: Yes | AG72: ABM WP Target Account List.xlsx — ABM Target Accounts | AH72: Brand / chain | AI72: Brand/system footprint from existing RBB research | AJ72: Medium | AK72: Unconfirmed — ask Worldpay | AL72: Who at Worldpay owns this relationship, what merchant IDs/legal entities are in scope, and is coverage enterprise, franchisee, or a single site?
A73: 69 | B73: Unranked | C73: Tom & Chee | F73: 7 | O73: Added from Worldpay ABM backbook; no verified active buying event. | P73: Worldpay relationship reported; incumbent technology lifecycle not yet verified. | Q73: Qualification required | R73: Qualification / relationship mapping | S73: Validate corporate scale, buying authority, current POS/payments stack and whether the Worldpay relationship is enterprise or franchise-level. | V73: Partial; Worldpay source list + RBB ecosystem research | W73: US DIRECT | X73: US | Y73: Fast Casual — Sandwich | Z73: Yes | AG73: ABM WP Target Account List.xlsx — ABM Target Accounts | AH73: Brand / chain | AI73: Brand/system footprint from existing RBB research | AJ73: Medium | AK73: Unconfirmed — ask Worldpay | AL73: Who at Worldpay owns this relationship, what merchant IDs/legal entities are in scope, and is coverage enterprise, franchisee, or a single site?
A74: 70 | B74: Unranked | C74: Ted'S Montana Grill, Inc. | O74: Added from Worldpay ABM backbook; no verified active buying event. | P74: Worldpay relationship reported; incumbent technology lifecycle not yet verified. | Q74: Qualification required | R74: Entity validation before pursuit | S74: Confirm entity identity and central buying authority before investing pursuit time; park if this is a single-location merchant. | V74: Entity validation needed; Worldpay source list + RBB ecosystem research | W74: US DIRECT | X74: US | Y74: Casual Dining — Steakhouse | Z74: Yes | AG74: ABM WP Target Account List.xlsx — ABM Target Accounts | AH74: Legal entity / franchisee / site record | AI74: WP merchant/entity footprint—not safe to infer from brand | AJ74: Needs WP confirmation | AK74: Unconfirmed — ask Worldpay | AL74: Who at Worldpay owns this relationship, what merchant IDs/legal entities are in scope, and is coverage enterprise, franchisee, or a single site?
A75: 71 | B75: Unranked | C75: Dibella'S | O75: Added from Worldpay ABM backbook; no verified active buying event. | P75: Worldpay relationship reported; incumbent technology lifecycle not yet verified. | Q75: Qualification required | R75: Qualification / relationship mapping | S75: Validate corporate scale, buying authority, current POS/payments stack and whether the Worldpay relationship is enterprise or franchise-level. | V75: Entity validation needed; Worldpay source list + RBB ecosystem research | W75: US DIRECT | X75: US | Y75: Fast Casual — Sandwich | Z75: Yes | AG75: ABM WP Target Account List.xlsx — ABM Target Accounts | AH75: Brand / chain | AI75: Brand footprint not yet verified | AJ75: Needs research | AK75: Unconfirmed — ask Worldpay | AL75: Who at Worldpay owns this relationship, what merchant IDs/legal entities are in scope, and is coverage enterprise, franchisee, or a single site?
A76: 72 | B76: Unranked | C76: J&B Restaurant Partner Of | O76: Added from Worldpay ABM backbook; no verified active buying event. | P76: Worldpay relationship reported; incumbent technology lifecycle not yet verified. | Q76: Qualification required | R76: Entity validation before pursuit | S76: Confirm entity identity and central buying authority before investing pursuit time; park if this is a single-location merchant. | V76: Partial; Worldpay source list + RBB ecosystem research | W76: US DIRECT | X76: US | Y76: Family Dining | Z76: Yes | AG76: ABM WP Target Account List.xlsx — ABM Target Accounts | AH76: Brand / chain | AI76: Brand footprint not yet verified | AJ76: Needs research | AK76: Unconfirmed — ask Worldpay | AL76: Who at Worldpay owns this relationship, what merchant IDs/legal entities are in scope, and is coverage enterprise, franchisee, or a single site?
A77: 73 | B77: Unranked | C77: Latrelle'S Galley Lp | O77: Added from Worldpay ABM backbook; no verified active buying event. | P77: Worldpay relationship reported; incumbent technology lifecycle not yet verified. | Q77: Qualification required | R77: Qualification / relationship mapping | S77: Validate corporate scale, buying authority, current POS/payments stack and whether the Worldpay relationship is enterprise or franchise-level. | V77: Partial; Worldpay source list + RBB ecosystem research | W77: US DIRECT | X77: US | Y77: Airport / Contract Foodservice | Z77: Yes | AG77: ABM WP Target Account List.xlsx — ABM Target Accounts | AH77: Legal entity / franchisee / site record | AI77: WP merchant/entity footprint—not safe to infer from brand | AJ77: Needs WP confirmation | AK77: Unconfirmed — ask Worldpay | AL77: Who at Worldpay owns this relationship, what merchant IDs/legal entities are in scope, and is coverage enterprise, franchisee, or a single site?
A78: 74 | B78: Unranked | C78: Houlihan'S Restaurants Inc | O78: Added from Worldpay ABM backbook; no verified active buying event. | P78: Worldpay relationship reported; incumbent technology lifecycle not yet verified. | Q78: Qualification required | R78: Entity validation before pursuit | S78: Confirm entity identity and central buying authority before investing pursuit time; park if this is a single-location merchant. | V78: Entity validation needed; Worldpay source list + RBB ecosystem research | W78: US DIRECT | X78: US | Y78: Casual Dining | Z78: Yes | AG78: ABM WP Target Account List.xlsx — ABM Target Accounts | AH78: Legal entity / franchisee / site record | AI78: WP merchant/entity footprint—not safe to infer from brand | AJ78: Needs WP confirmation | AK78: Unconfirmed — ask Worldpay | AL78: Who at Worldpay owns this relationship, what merchant IDs/legal entities are in scope, and is coverage enterprise, franchisee, or a single site?
A79: 75 | B79: Unranked | C79: Norsan Restaurants Inc | O79: Added from Worldpay ABM backbook; no verified active buying event. | P79: Worldpay relationship reported; incumbent technology lifecycle not yet verified. | Q79: Qualification required | R79: Entity validation before pursuit | S79: Confirm entity identity and central buying authority before investing pursuit time; park if this is a single-location merchant. | V79: Partial; Worldpay source list + RBB ecosystem research | W79: US DIRECT | X79: US | Y79: Restaurant Group / Franchisee | Z79: No | AB79: Attrition | AG79: ABM WP Target Account List.xlsx — ABM Target Accounts | AH79: Legal entity / franchisee / site record | AI79: WP merchant/entity footprint—not safe to infer from brand | AJ79: Needs WP confirmation | AK79: Unconfirmed — ask Worldpay | AL79: Who at Worldpay owns this relationship, what merchant IDs/legal entities are in scope, and is coverage enterprise, franchisee, or a single site?
A80: 76 | B80: Unranked | C80: Winghouse | O80: Added from Worldpay ABM backbook; no verified active buying event. | P80: Worldpay relationship reported; incumbent technology lifecycle not yet verified. | Q80: Qualification required | R80: Entity validation before pursuit | S80: Confirm entity identity and central buying authority before investing pursuit time; park if this is a single-location merchant. | V80: Entity validation needed; Worldpay source list + RBB ecosystem research | W80: US DIRECT | X80: US | Y80: Casual Dining — Sports Bar | Z80: Yes | AB80: SMB | AG80: ABM WP Target Account List.xlsx — ABM Target Accounts | AH80: Brand / chain | AI80: Brand footprint not yet verified | AJ80: Needs research | AK80: Unconfirmed — ask Worldpay | AL80: Who at Worldpay owns this relationship, what merchant IDs/legal entities are in scope, and is coverage enterprise, franchisee, or a single site?
A81: 77 | B81: Unranked | C81: Creole Cuisine Restaurant | O81: Added from Worldpay ABM backbook; no verified active buying event. | P81: Worldpay relationship reported; incumbent technology lifecycle not yet verified. | Q81: Qualification required | R81: Qualification / relationship mapping | S81: Validate corporate scale, buying authority, current POS/payments stack and whether the Worldpay relationship is enterprise or franchise-level. | V81: Partial; Worldpay source list + RBB ecosystem research | W81: US DIRECT | X81: US | Y81: Restaurant Group / Platform | Z81: Yes | AG81: ABM WP Target Account List.xlsx — ABM Target Accounts | AH81: Restaurant group / platform | AI81: WP merchant/entity footprint—not safe to infer from brand | AJ81: Needs WP confirmation | AK81: Unconfirmed — ask Worldpay | AL81: Who at Worldpay owns this relationship, what merchant IDs/legal entities are in scope, and is coverage enterprise, franchisee, or a single site?
A82: 78 | B82: Unranked | C82: La Carreta Group Inc | O82: Added from Worldpay ABM backbook; no verified active buying event. | P82: Worldpay relationship reported; incumbent technology lifecycle not yet verified. | Q82: Qualification required | R82: Entity validation before pursuit | S82: Confirm entity identity and central buying authority before investing pursuit time; park if this is a single-location merchant. | V82: Entity validation needed; Worldpay source list + RBB ecosystem research | W82: US DIRECT | X82: US | Y82: Restaurant Group / Franchisee | Z82: Yes | AG82: ABM WP Target Account List.xlsx — ABM Target Accounts | AH82: Legal entity / franchisee / site record | AI82: WP merchant/entity footprint—not safe to infer from brand | AJ82: Needs WP confirmation | AK82: Unconfirmed — ask Worldpay | AL82: Who at Worldpay owns this relationship, what merchant IDs/legal entities are in scope, and is coverage enterprise, franchisee, or a single site?
A83: 79 | B83: Unranked | C83: Jake N Joes | O83: Added from Worldpay ABM backbook; no verified active buying event. | P83: Worldpay relationship reported; incumbent technology lifecycle not yet verified. | Q83: Qualification required | R83: Qualification / relationship mapping | S83: Validate corporate scale, buying authority, current POS/payments stack and whether the Worldpay relationship is enterprise or franchise-level. | V83: Partial; Worldpay source list + RBB ecosystem research | W83: US DIRECT | X83: US | Y83: Casual Dining — Sports Bar | Z83: Yes | AG83: ABM WP Target Account List.xlsx — ABM Target Accounts | AH83: Brand / chain | AI83: Brand footprint not yet verified | AJ83: Needs research | AK83: Unconfirmed — ask Worldpay | AL83: Who at Worldpay owns this relationship, what merchant IDs/legal entities are in scope, and is coverage enterprise, franchisee, or a single site?
A84: 80 | B84: Unranked | C84: Chateau Restaurant | O84: Added from Worldpay ABM backbook; no verified active buying event. | P84: Worldpay relationship reported; incumbent technology lifecycle not yet verified. | Q84: Qualification required | R84: Qualification / relationship mapping | S84: Validate corporate scale, buying authority, current POS/payments stack and whether the Worldpay relationship is enterprise or franchise-level. | V84: Partial; Worldpay source list + RBB ecosystem research | W84: US DIRECT | X84: US | Y84: Casual Dining — Italian | Z84: Yes | AG84: ABM WP Target Account List.xlsx — ABM Target Accounts | AH84: Brand / chain | AI84: Brand footprint not yet verified | AJ84: Needs research | AK84: Unconfirmed — ask Worldpay | AL84: Who at Worldpay owns this relationship, what merchant IDs/legal entities are in scope, and is coverage enterprise, franchisee, or a single site?
A85: 81 | B85: Unranked | C85: Cyclone Anaya | O85: Added from Worldpay ABM backbook; no verified active buying event. | P85: Worldpay relationship reported; incumbent technology lifecycle not yet verified. | Q85: Qualification required | R85: Qualification / relationship mapping | S85: Validate corporate scale, buying authority, current POS/payments stack and whether the Worldpay relationship is enterprise or franchise-level. | V85: Partial; Worldpay source list + RBB ecosystem research | W85: US DIRECT | X85: US | Y85: Casual Dining — Mexican | Z85: Yes | AG85: ABM WP Target Account List.xlsx — ABM Target Accounts | AH85: Brand / chain | AI85: Brand footprint not yet verified | AJ85: Needs research | AK85: Unconfirmed — ask Worldpay | AL85: Who at Worldpay owns this relationship, what merchant IDs/legal entities are in scope, and is coverage enterprise, franchisee, or a single site?
A86: 82 | B86: Unranked | C86: Jeff Ruby | O86: Added from Worldpay ABM backbook; no verified active buying event. | P86: Worldpay relationship reported; incumbent technology lifecycle not yet verified. | Q86: Qualification required | R86: Qualification / relationship mapping | S86: Validate corporate scale, buying authority, current POS/payments stack and whether the Worldpay relationship is enterprise or franchise-level. | V86: Partial; Worldpay source list + RBB ecosystem research | W86: US DIRECT | X86: US | Y86: Fine Dining — Steakhouse | Z86: Yes | AG86: ABM WP Target Account List.xlsx — ABM Target Accounts | AH86: Brand / chain | AI86: Brand footprint not yet verified | AJ86: Needs research | AK86: Unconfirmed — ask Worldpay | AL86: Who at Worldpay owns this relationship, what merchant IDs/legal entities are in scope, and is coverage enterprise, franchisee, or a single site?
A87: 83 | B87: Unranked | C87: Mark'S Feed Store | O87: Added from Worldpay ABM backbook; no verified active buying event. | P87: Worldpay relationship reported; incumbent technology lifecycle not yet verified. | Q87: Qualification required | R87: Qualification / relationship mapping | S87: Validate corporate scale, buying authority, current POS/payments stack and whether the Worldpay relationship is enterprise or franchise-level. | V87: Partial; Worldpay source list + RBB ecosystem research | W87: US DIRECT | X87: US | Y87: Casual Dining — Barbecue | Z87: Yes | AG87: ABM WP Target Account List.xlsx — ABM Target Accounts | AH87: Brand / chain | AI87: Brand footprint not yet verified | AJ87: Needs research | AK87: Unconfirmed — ask Worldpay | AL87: Who at Worldpay owns this relationship, what merchant IDs/legal entities are in scope, and is coverage enterprise, franchisee, or a single site?
A88: 84 | B88: Unranked | C88: Cocula Restaurant | O88: Added from Worldpay ABM backbook; no verified active buying event. | P88: Worldpay relationship reported; incumbent technology lifecycle not yet verified. | Q88: Qualification required | R88: Qualification / relationship mapping | S88: Validate corporate scale, buying authority, current POS/payments stack and whether the Worldpay relationship is enterprise or franchise-level. | V88: Partial; Worldpay source list + RBB ecosystem research | W88: US DIRECT | X88: US | Y88: Casual Dining — Mexican | Z88: Yes | AG88: ABM WP Target Account List.xlsx — ABM Target Accounts | AH88: Brand / chain | AI88: Brand footprint not yet verified | AJ88: Needs research | AK88: Unconfirmed — ask Worldpay | AL88: Who at Worldpay owns this relationship, what merchant IDs/legal entities are in scope, and is coverage enterprise, franchisee, or a single site?
A89: 85 | B89: Unranked | C89: David'S Pizza | O89: Added from Worldpay ABM backbook; no verified active buying event. | P89: Worldpay relationship reported; incumbent technology lifecycle not yet verified. | Q89: Qualification required | R89: Qualification / relationship mapping | S89: Validate corporate scale, buying authority, current POS/payments stack and whether the Worldpay relationship is enterprise or franchise-level. | V89: Partial; Worldpay source list + RBB ecosystem research | W89: US DIRECT | X89: US | Y89: Pizza | Z89: Yes | AG89: ABM WP Target Account List.xlsx — ABM Target Accounts | AH89: Brand / chain | AI89: Brand footprint not yet verified | AJ89: Needs research | AK89: Unconfirmed — ask Worldpay | AL89: Who at Worldpay owns this relationship, what merchant IDs/legal entities are in scope, and is coverage enterprise, franchisee, or a single site?
A90: 86 | B90: Unranked | C90: Gibsons Llc | O90: Added from Worldpay ABM backbook; no verified active buying event. | P90: Worldpay relationship reported; incumbent technology lifecycle not yet verified. | Q90: Qualification required | R90: Entity validation before pursuit | S90: Confirm entity identity and central buying authority before investing pursuit time; park if this is a single-location merchant. | V90: Partial; Worldpay source list + RBB ecosystem research | W90: US DIRECT | X90: US | Y90: Fine Dining — Steakhouse | Z90: Yes | AG90: ABM WP Target Account List.xlsx — ABM Target Accounts | AH90: Legal entity / franchisee / site record | AI90: WP merchant/entity footprint—not safe to infer from brand | AJ90: Needs WP confirmation | AK90: Unconfirmed — ask Worldpay | AL90: Who at Worldpay owns this relationship, what merchant IDs/legal entities are in scope, and is coverage enterprise, franchisee, or a single site?
A91: 87 | B91: Unranked | C91: Sam Choy'S | O91: Added from Worldpay ABM backbook; no verified active buying event. | P91: Worldpay relationship reported; incumbent technology lifecycle not yet verified. | Q91: Qualification required | R91: Qualification / relationship mapping | S91: Validate corporate scale, buying authority, current POS/payments stack and whether the Worldpay relationship is enterprise or franchise-level. | V91: Partial; Worldpay source list + RBB ecosystem research | W91: US DIRECT | X91: US | Y91: Casual Dining — Hawaiian | Z91: Yes | AG91: ABM WP Target Account List.xlsx — ABM Target Accounts | AH91: Brand / chain | AI91: Brand footprint not yet verified | AJ91: Needs research | AK91: Unconfirmed — ask Worldpay | AL91: Who at Worldpay owns this relationship, what merchant IDs/legal entities are in scope, and is coverage enterprise, franchisee, or a single site?
A92: 88 | B92: Unranked | C92: Tibby New Orleans Kitchen | O92: Added from Worldpay ABM backbook; no verified active buying event. | P92: Worldpay relationship reported; incumbent technology lifecycle not yet verified. | Q92: Qualification required | R92: Qualification / relationship mapping | S92: Validate corporate scale, buying authority, current POS/payments stack and whether the Worldpay relationship is enterprise or franchise-level. | V92: Partial; Worldpay source list + RBB ecosystem research | W92: US DIRECT | X92: US | Y92: Casual Dining — Cajun / Creole | Z92: Yes | AG92: ABM WP Target Account List.xlsx — ABM Target Accounts | AH92: Brand / chain | AI92: Brand footprint not yet verified | AJ92: Needs research | AK92: Unconfirmed — ask Worldpay | AL92: Who at Worldpay owns this relationship, what merchant IDs/legal entities are in scope, and is coverage enterprise, franchisee, or a single site?
... A107: 103 | B107: Unranked | C107: Off The Wagon | O107: Added from Worldpay ABM backbook; no verified active buying event. | P107: Worldpay relationship reported; incumbent technology lifecycle not yet verified. | Q107: Qualification required | R107: Entity validation before pursuit | S107: Confirm entity identity and central buying authority before investing pursuit time; park if this is a single-location merchant. | V107: Partial; Worldpay source list + RBB ecosystem research | W107: US DIRECT | X107: US | Y107: Casual Dining / Bar | Z107: No | AG107: ABM WP Target Account List.xlsx — ABM Target Accounts | AH107: Brand / chain | AI107: Brand footprint not yet verified | AJ107: Needs research | AK107: Unconfirmed — ask Worldpay | AL107: Who at Worldpay owns this relationship, what merchant IDs/legal entities are in scope, and is coverage enterprise, franchisee, or a single site?
A108: 104 | B108: Unranked | C108: Oyster House | F108: 6 | O108: Added from Worldpay ABM backbook; no verified active buying event. | P108: Worldpay relationship reported; incumbent technology lifecycle not yet verified. | Q108: Qualification required | R108: Entity validation before pursuit | S108: Confirm entity identity and central buying authority before investing pursuit time; park if this is a single-location merchant. | V108: Partial; Worldpay source list + RBB ecosystem research | W108: US DIRECT | X108: US | Y108: Full-Service Dining | Z108: No | AG108: ABM WP Target Account List.xlsx — ABM Target Accounts | AH108: Brand / chain | AI108: Brand/system footprint from existing RBB research | AJ108: Medium | AK108: Unconfirmed — ask Worldpay | AL108: Who at Worldpay owns this relationship, what merchant IDs/legal entities are in scope, and is coverage enterprise, franchisee, or a single site?
A109: 105 | B109: Unranked | C109: Robek S #289 | O109: Added from Worldpay ABM backbook; no verified active buying event. | P109: Worldpay relationship reported; incumbent technology lifecycle not yet verified. | Q109: Qualification required | R109: Entity validation before pursuit | S109: Confirm entity identity and central buying authority before investing pursuit time; park if this is a single-location merchant. | V109: Partial; Worldpay source list + RBB ecosystem research | W109: US DIRECT | X109: US | Y109: Franchisee — Juice / Smoothie | Z109: No | AG109: ABM WP Target Account List.xlsx — ABM Target Accounts | AH109: Legal entity / franchisee / site record | AI109: WP merchant/entity footprint—not safe to infer from brand | AJ109: Needs WP confirmation | AK109: Unconfirmed — ask Worldpay | AL109: Who at Worldpay owns this relationship, what merchant IDs/legal entities are in scope, and is coverage enterprise, franchisee, or a single site?
A110: 106 | B110: Unranked | C110: Sc 10024, Llc | O110: Added from Worldpay ABM backbook; no verified active buying event. | P110: Worldpay relationship reported; incumbent technology lifecycle not yet verified. | Q110: Qualification required | R110: Entity validation before pursuit | S110: Confirm entity identity and central buying authority before investing pursuit time; park if this is a single-location merchant. | V110: Partial; Worldpay source list + RBB ecosystem research | W110: US DIRECT | X110: US | Y110: Merchant / Franchisee Entity | Z110: No | AG110: ABM WP Target Account List.xlsx — ABM Target Accounts | AH110: Legal entity / franchisee / site record | AI110: WP merchant/entity footprint—not safe to infer from brand | AJ110: Needs WP confirmation | AK110: Unconfirmed — ask Worldpay | AL110: Who at Worldpay owns this relationship, what merchant IDs/legal entities are in scope, and is coverage enterprise, franchisee, or a single site?
A111: 107 | B111: Unranked | C111: Subway Tryan | O111: Added from Worldpay ABM backbook; no verified active buying event. | P111: Worldpay relationship reported; incumbent technology lifecycle not yet verified. | Q111: Qualification required | R111: Entity validation before pursuit | S111: Confirm entity identity and central buying authority before investing pursuit time; park if this is a single-location merchant. | V111: Partial; Worldpay source list + RBB ecosystem research | W111: US DIRECT | X111: US | Y111: Franchisee — Sandwich | Z111: No | AG111: ABM WP Target Account List.xlsx — ABM Target Accounts | AH111: Legal entity / franchisee / site record | AI111: WP merchant/entity footprint—not safe to infer from brand | AJ111: Needs WP confirmation | AK111: Unconfirmed — ask Worldpay | AL111: Who at Worldpay owns this relationship, what merchant IDs/legal entities are in scope, and is coverage enterprise, franchisee, or a single site?
A112: 108 | B112: Unranked | C112: Ten Star Enterprises #9 | O112: Added from Worldpay ABM backbook; no verified active buying event. | P112: Worldpay relationship reported; incumbent technology lifecycle not yet verified. | Q112: Qualification required | R112: Entity validation before pursuit | S112: Confirm entity identity and central buying authority before investing pursuit time; park if this is a single-location merchant. | V112: Partial; Worldpay source list + RBB ecosystem research | W112: US DIRECT | X112: US | Y112: Merchant / Franchisee Entity | Z112: No | AG112: ABM WP Target Account List.xlsx — ABM Target Accounts | AH112: Legal entity / franchisee / site record | AI112: WP merchant/entity footprint—not safe to infer from brand | AJ112: Needs WP confirmation | AK112: Unconfirmed — ask Worldpay | AL112: Who at Worldpay owns this relationship, what merchant IDs/legal entities are in scope, and is coverage enterprise, franchisee, or a single site?
A113: 109 | B113: Unranked | C113: The Gin Mill | O113: Added from Worldpay ABM backbook; no verified active buying event. | P113: Worldpay relationship reported; incumbent technology lifecycle not yet verified. | Q113: Qualification required | R113: Entity validation before pursuit | S113: Confirm entity identity and central buying authority before investing pursuit time; park if this is a single-location merchant. | V113: Partial; Worldpay source list + RBB ecosystem research | W113: US DIRECT | X113: US | Y113: Casual Dining / Bar | Z113: No | AG113: ABM WP Target Account List.xlsx — ABM Target Accounts | AH113: Brand / chain | AI113: Brand footprint not yet verified | AJ113: Needs research | AK113: Unconfirmed — ask Worldpay | AL113: Who at Worldpay owns this relationship, what merchant IDs/legal entities are in scope, and is coverage enterprise, franchisee, or a single site?
A114: 110 | B114: Unranked | C114: The Stumble Inn | O114: Added from Worldpay ABM backbook; no verified active buying event. | P114: Worldpay relationship reported; incumbent technology lifecycle not yet verified. | Q114: Qualification required | R114: Entity validation before pursuit | S114: Confirm entity identity and central buying authority before investing pursuit time; park if this is a single-location merchant. | V114: Partial; Worldpay source list + RBB ecosystem research | W114: US DIRECT | X114: US | Y114: Casual Dining / Bar | Z114: No | AG114: ABM WP Target Account List.xlsx — ABM Target Accounts | AH114: Brand / chain | AI114: Brand footprint not yet verified | AJ114: Needs research | AK114: Unconfirmed — ask Worldpay | AL114: Who at Worldpay owns this relationship, what merchant IDs/legal entities are in scope, and is coverage enterprise, franchisee, or a single site?
A115: 111 | B115: Unranked | C115: Avi Foodsystems | O115: Added from Worldpay ABM backbook; no verified active buying event. | P115: Worldpay relationship reported; incumbent technology lifecycle not yet verified. | Q115: Qualification required | R115: Qualification / relationship mapping | S115: Validate corporate scale, buying authority, current POS/payments stack and whether the Worldpay relationship is enterprise or franchise-level. | V115: Partial; Worldpay source list + RBB ecosystem research | W115: US DIRECT | X115: US | Y115: Contract Foodservice | Z115: Yes | AG115: ABM WP Target Account List.xlsx — ABM Target Accounts | AH115: Brand / chain | AI115: Brand footprint not yet verified | AJ115: Needs research | AK115: Unconfirmed — ask Worldpay | AL115: Who at Worldpay owns this relationship, what merchant IDs/legal entities are in scope, and is coverage enterprise, franchisee, or a single site?
...

Sheet Stack Intelligence
A1: Technology Stack Intelligence — 2026-08-14
A2: Vendor names are separated from verified deployment status. 'Unknown' means not yet verified, not whitespace.
A4: Account | B4: RM | C4: POS | D4: Payments / Gateway | E4: Digital / Ordering | F4: Loyalty / CRM | G4: Back Office / Labor / Inventory | H4: Kiosk / DMB | I4: KDS / Kitchen | J4: Drive-Thru | K4: Hardware | L4: Lifecycle | M4: Deployment Health | N4: Known Layers | O4: Unknown Layers | P4: Coverage % | Q4: Primary Opportunity | R4: Next Verification
A5: WENDY'S INTERNATIONAL INC | B5: Stacie Davis | C5: NCR Aloha | D5: ACI | E5: Yes | F5: Unknown | G5: Unknown | H5: Yes | I5: Unknown | J5: Unknown | K5: Ingenico, Variable | L5: Active decision / final stage | M5: 5 | N5: 4 | O5: 0.55555556 | P5: 0.55555556 | Q5: POS + payments platform capture | R5: War-room the decision: confirm owner, evaluation criteria, final meeting, commercials, product scope, franchise rollout and competitive gaps.
A6: DEL TACO LLC | B6: Maggie Lenhart | C6: NCR | D6: NCR Connected Payments | E6: OLO corporate | F6: Unknown | G6: Unknown | H6: Bite (Express) | I6: Unknown | J6: Unknown | K6: Worldpay extension; Yadav ownership-change integration window | L6: Strong access; sourcing event not confirmed | M6: 5 | N6: 4 | O6: 0.55555556 | P6: 0.44444444 | Q6: POS/payments + multi-brand consolidation | R6: Finish extension, consolidate leads, map Yadav governance and confirm sourcing event
A7: Dutch Bros | B7: Maggie Lenhart | C7: Genius (user intelligence); Xenial legacy baseline | D7: Verifone SCA Gateway | E7: Olo Order and Pay | F7: Paytronix / Dutch Rewards | G7: Unknown | H7: Unknown | I7: Unknown | J7: Core operating channel; vendor layer unknown | K7: Verifone e285 (Xenial iPads) | L7: Installed customer / expansion | M7: 5 | N7: 4 | O7: 0.55555556 | P7: 0.66666667 | Q7: Protect and expand Genius footprint | R7: Confirm Genius products, installed locations, adoption, support health, contract dates, attach rate and expansion path.
A8: Focus Brands (GoTo Foods) | B8: Brian Wood | C8: Qu (deploying) | D8: FreedomPay | E8: Olo / Qu integrations | F8: Unknown | G8: Qu integrates with third-party BOH; incumbent unknown | H8: DMB incumbent unknown | I8: Unknown | J8: Unknown | K8: Unknown | L8: Qu established since 2024 | M8: 3 | N8: 6 | O8: 0.33333333 | P8: 0.55555556 | Q8: DMB + multi-brand visual estate; payments defense | R8: Map DMB/CMS, screens, refresh timing and buying center by brand.
A9: SUBWAY | B9: Stacie Davis | C9: Proprietary POS | D9: FreedomPay | E9: Yes | F9: Unknown | G9: Unknown | H9: Genius KDS reported internally; exact sites/status unverified | I9: Unknown | J9: Unknown | K9: Fragmented global/franchise estate; existing Genius scope unresolved | L9: Product, ownership, locations and deployment status unverified | M9: 5 | N9: 4 | O9: 0.55555556 | P9: 0.55555556 | Q9: Verify existing Genius KDS relationship before any additional adjacency | R9: Confirm product owner, sites, status, commitments and sponsor
A10: FIVE GUYS | B10: Avery Churchwell | C10: PAR Brink (U.S.); NCR (EMEA) | D10: Worldpay; limited Global Payments EMEA; PAR Pay threat | E10: Olo Ordering + Engage | F10: Olo GDP/Marketing (not traditional points loyalty) | G10: CrunchTime (inventory, labor, ops) | H10: LineTen | I10: Unknown | J10: Unknown | K10: PAR renewal/evaluation window plausible; formal process and dates unconfirmed | L10: No verified failure; EMEA support gap requires validation | M10: 7 | N10: 2 | O10: 0.77777778 | P10: 0.77777778 | Q10: Pre-RFP shaping + internal transaction-metered POS feasibility | R10: Confirm evaluation type, renewal/notice dates, scope, sponsor and global requirements
A11: CHOICE HOTELS | B11: Brian Wood | C11: Shift4 | D11: Mixed acquirers; active Worldpay gateway/acquiring RFP | E11: Yes | F11: Unknown | G11: Unknown | H11: Unknown | I11: Unknown | J11: Unknown | K11: Unknown | L11: Deconversion incomplete; active win-back RFP | M11: 3 | N11: 6 | O11: 0.33333333 | P11: 0.22222222 | Q11: Payments win-back + hotel restaurant/DMB discovery | R11: Confirm RFP stage, retained properties, executive sponsor and venue technology scope.
A12: THE STEAK N SHAKE CO | B12: Maggie Lenhart | C12: NCR | D12: NCR Connected Payments | E12: Olo- moving to direct Express cert with NovaTab | F12: Unknown | G12: Unknown | H12: Kiosk vendor transition; integration problems | I12: Unknown | J12: Unknown | K12: Unknown | L12: Kiosk and mobile transition | M12: 4 | N12: 5 | O12: 0.44444444 | P12: 0.44444444 | Q12: Kiosk recovery + DMB/drive-thru/payments adjacency | R12: Identify kiosk vendor, certification issue, reporting gap, owners and remediation dates.
A13: FREDDY'S FROZEN CUSTARD LLC | B13: Avery Churchwell | C13: PAR Brink via RDS | D13: PAR Brink | E13: Olo / Olo Pay | F13: Unknown | G13: Creative Realities; Neon entry reported, unverified | H13: Unknown | I13: Unknown | J13: Unknown | K13: Protected PAR/RDS account; CIO reportedly reinforcing PAR | L13: No open event; RDS controls access | M13: 5 | N13: 4 | O13: 0.55555556 | P13: 0.44444444 | Q13: RDS-led modular value review only | R13: Prove RDS pilot and account protections before any Freddy's value discussion
A14: EAT'N PARK HOSPITALITY GRP INC | B14: Avery Churchwell | C14: FreedomPay, Tillster, Olo | D14: Oracle Simphony, PayMyTab, Catertrax | E14: Olo, Tillster (wallets), Nextep | F14: Unknown | G14: Unknown | H14: Unknown | I14: Unknown | J14: Unknown | K14: Desk 3500s, T650c | L14: Mixed / transitioning | M14: 4 | N14: 5 | O14: 0.44444444 | P14: 0.44444444 | Q14: Consolidation and payments | R14: Separate stacks by concept and validate Oracle/FreedomPay/Tillster/Olo/Nextep ownership.
A15: CRACKER BARREL OLD COUNTRY STORE, INC. | B15: Brian Wood | C15: RAFT 610 for POS, Express for OLO ISV for mobile, and eComm is on VAP. Moving to Oracle Symphony | D15: FreedomPay | E15: Yes | F15: Unknown | G15: Unknown | H15: Unknown | I15: Unknown | J15: Unknown | K15: Unknown | L15: Deploying / transition | M15: 3 | N15: 6 | O15: 0.33333333 | P15: 0.33333333 | Q15: Adjacent stack and deployment support | R15: Confirm rollout completion, FreedomPay scope, operational issues and remaining adjacent gaps.
A16: MILLLER'S ALE HOUSE | B16: Avery Churchwell | C16: NCR Connected Payments, Ziosk | D16: NCR, Ziosk | E16: OloPay | F16: Unknown | G16: Unknown | H16: Unknown | I16: Unknown | J16: Unknown | K16: Swipe Simple B250 & NCR Terminals | L16: Established POS; recent digital payment change | M16: 4 | N16: 5 | O16: 0.44444444 | P16: 0.44444444 | Q16: In-store POS/payments and guest experience | R16: Confirm lost scope, NCR renewal, Ziosk footprint and remaining payments opportunity.
... A34: FESTIVA REAL ESTATE HOLDINGS | B34: Brian Wood | C34: Shift4 & other | D34: Shift4 & other | E34: Yes | F34: Unknown | G34: Unknown | H34: Unknown | I34: Unknown | J34: Unknown | K34: Unknown | L34: Established / unclear | M34: 3 | N34: 6 | O34: 0.33333333 | P34: 0.33333333 | Q34: Payments discovery | R34: Resolve entity relationship and current payment estate before pursuit.
A35: POLLO CAMPERO | B35: Unassigned / Worldpay | C35: Oracle Simphony migration; NCR Aloha legacy | D35: Fiserv in-store; Olo Pay/Stripe digital | E35: Olo | F35: Current loyalty vendor unknown | G35: Unknown | H35: DMB incumbent/dissatisfaction reported | I35: Unknown | J35: Unknown | K35: Mixed estate / potential RFI | L35: Scope, decision openness and deadlines unverified | M35: 5 | N35: 4 | O35: 0.55555556 | P35: RFI qualification + international platform/payments/DMB | Q35: Obtain NDA/RFI and validate estate by country | R35: Confirm sponsor, deadlines, Oracle status, payment scope and DMB requirements
A36: RDS FIVE-UNIT REBRAND PILOT | B36: RDS / Darren Heinze | C36: To be determined | D36: Worldpay/Genius candidate | E36: Unknown | F36: Unknown | G36: Unknown | H36: Digital menu boards in evaluation | I36: Unknown | J36: Drive-thru sites | K36: Clean-slate rebrand / conversion | L36: Customer facts and commercial model unverified | M36: 4 | N36: 5 | O36: 0.44444444 | P36: RDS-led pilot and reseller proof | Q36: Confirm full phased-stack scope | R36: Confirm entity, authority, dates, budget, incumbent contracts and account-protection terms

Sheet Evidence Ledger
A1: Evidence Ledger — refreshed 2026-09-04
A2: Evidence type and confidence are explicit. User intelligence is high-priority field evidence but is not relabeled as public verification.
A4: Account | B4: Technology Layer | C4: Event Type | D4: Event Date | E4: Source / Publisher | F4: Evidence Summary | G4: Source URL or Reference | H4: Confidence | I4: Current-State Interpretation | J4: Research Date
A5: WENDY'S INTERNATIONAL INC | B5: Baseline stack | C5: Worldpay source | E5: Internal source | F5: Worldpay reports POS=NCR Aloha; ISV/payments=ACI; ecommerce=Yes. | G5: Worldpay_30_Account_Capture_Plan_v1.xlsx — Worldpay Source Snapshot | H5: Medium | I5: Baseline; requires current verification | J5: 2026-07-20
A6: WENDY'S INTERNATIONAL INC | B6: Field update | C6: User intelligence | D6: 46223 | E6: User-supplied | F6: Wendy’s is making a POS decision next week; Genius is in the mix. | G6: User field intelligence supplied for this analysis on 2026-07-20 | H6: High (user intelligence) | I6: Preserve separately from public verification | J6: 2026-07-20
A7: DEL TACO LLC | B7: Baseline stack | C7: Worldpay source | E7: Internal source | F7: Worldpay reports POS=NCR; ISV/payments=NCR Connected Payments; ecommerce=OLO corporate. | G7: Worldpay_30_Account_Capture_Plan_v1.xlsx — Worldpay Source Snapshot | H7: Medium | I7: Baseline; requires current verification | J7: 2026-07-20
A8: DEL TACO LLC | B8: Field update | C8: User intelligence | D8: 46223 | E8: User-supplied | F8: Del Taco has leads floating around Global Payments and status is needed. | G8: User field intelligence supplied for this analysis on 2026-07-20 | H8: High (user intelligence) | I8: Preserve separately from public verification | J8: 2026-07-20
A9: Dutch Bros | B9: Baseline stack | C9: Worldpay source | E9: Internal source | F9: Worldpay reports POS=Xenial Cloud POS; ISV/payments=Verifone SCA Gateway; ecommerce=OloPay, Braintree, Paytronix. | G9: Worldpay_30_Account_Capture_Plan_v1.xlsx — Worldpay Source Snapshot | H9: Medium | I9: Baseline; requires current verification | J9: 2026-07-20
A10: Dutch Bros | B10: Field update | C10: User intelligence | D10: 46223 | E10: User-supplied | F10: Dutch Bros is already a Genius customer. | G10: User field intelligence supplied for this analysis on 2026-07-20 | H10: High (user intelligence) | I10: Preserve separately from public verification | J10: 2026-07-20
A11: Focus Brands (GoTo Foods) | B11: Baseline stack | C11: Worldpay source | E11: Internal source | F11: Worldpay reports POS=FreedomPay (in-store), OLO (online), Monkey Media (catering), moving all to Qu; ISV/payments=FreedomPay; ecommerce=Yes. | G11: Worldpay_30_Account_Capture_Plan_v1.xlsx — Worldpay Source Snapshot | H11: Medium | I11: Baseline; requires current verification | J11: 2026-07-20
A12: Focus Brands (GoTo Foods) | B12: Field update | C12: User intelligence | D12: 46223 | E12: User-supplied | F12: Focus/GoTo Foods is a recent Qu win but deployment is taking longer than expected. | G12: User field intelligence supplied for this analysis on 2026-07-20 | H12: High (user intelligence) | I12: Preserve separately from public verification | J12: 2026-07-20
A13: SUBWAY | B13: Baseline stack | C13: Worldpay source | E13: Internal source | F13: Worldpay reports POS=Proprietary; ISV/payments=FreedomPay; ecommerce=Yes. | G13: Worldpay_30_Account_Capture_Plan_v1.xlsx — Worldpay Source Snapshot | H13: Medium | I13: Baseline; requires current verification | J13: 2026-07-20
A14: FIVE GUYS | B14: Baseline stack | C14: Worldpay source | E14: Internal source | F14: Worldpay reports POS=Par, Verifone SCA, Olo; ISV/payments=PAR; ecommerce=Olo. | G14: Worldpay_30_Account_Capture_Plan_v1.xlsx — Worldpay Source Snapshot | H14: Medium | I14: Baseline; requires current verification | J14: 2026-07-20
A15: FIVE GUYS | B15: Field update | C15: User intelligence | D15: 46223 | E15: User-supplied | F15: Five Guys is a very happy CrunchTime user; PAR signed a three-year POS extension about 2.25 years ago. | G15: User field intelligence supplied for this analysis on 2026-07-20 | H15: High (user intelligence) | I15: Preserve separately from public verification | J15: 2026-07-20
A16: CHOICE HOTELS | B16: Baseline stack | C16: Worldpay source | E16: Internal source | F16: Worldpay reports POS=Shift4; ISV/payments=unknown; ecommerce=Yes. | G16: Worldpay_30_Account_Capture_Plan_v1.xlsx — Worldpay Source Snapshot | H16: Medium | I16: Baseline; requires current verification | J16: 2026-07-20
A17: THE STEAK N SHAKE CO | B17: Baseline stack | C17: Worldpay source | E17: Internal source | F17: Worldpay reports POS=NCR; ISV/payments=NCR Connected Payments; ecommerce=Olo- moving to direct Express cert with NovaTab. | G17: Worldpay_30_Account_Capture_Plan_v1.xlsx — Worldpay Source Snapshot | H17: Medium | I17: Baseline; requires current verification | J17: 2026-07-20
A18: FREDDY'S FROZEN CUSTARD LLC | B18: Baseline stack | C18: Worldpay source | E18: Internal source | F18: Worldpay reports POS=PAR Brink (VAR -Verifone Classic); ISV/payments=PAR Brink; ecommerce=OloPay. | G18: Worldpay_30_Account_Capture_Plan_v1.xlsx — Worldpay Source Snapshot | H18: Medium | I18: Baseline; requires current verification | J18: 2026-07-20
A19: FREDDY'S FROZEN CUSTARD LLC | B19: Field update | C19: User intelligence | D19: 46223 | E19: User-supplied | F19: Freddy's is a PAR customer sold through RDS. | G19: User field intelligence supplied for this analysis on 2026-07-20 | H19: High (user intelligence) | I19: Preserve separately from public verification | J19: 2026-07-20
A20: EAT'N PARK HOSPITALITY GRP INC | B20: Baseline stack | C20: Worldpay source | E20: Internal source | F20: Worldpay reports POS=FreedomPay, Tillster, Olo; ISV/payments=Oracle Simphony, PayMyTab, Catertrax; ecommerce=Olo, Tillster (wallets), Nextep. | G20: Worldpay_30_Account_Capture_Plan_v1.xlsx — Worldpay Source Snapshot | H20: Medium | I20: Baseline; requires current verification | J20: 2026-07-20
A21: CRACKER BARREL OLD COUNTRY STORE, INC. | B21: Baseline stack | C21: Worldpay source | E21: Internal source | F21: Worldpay reports POS=RAFT 610 for POS, Express for OLO ISV for mobile, and eComm is on VAP. Moving to Oracle Symphony; ISV/payments=FreedomPay; ecommerce=Yes. | G21: Worldpay_30_Account_Capture_Plan_v1.xlsx — Worldpay Source Snapshot | H21: Medium | I21: Baseline; requires current verification | J21: 2026-07-20
A22: MILLLER'S ALE HOUSE | B22: Baseline stack | C22: Worldpay source | E22: Internal source | F22: Worldpay reports POS=NCR Connected Payments, Ziosk; ISV/payments=NCR, Ziosk; ecommerce=OloPay. | G22: Worldpay_30_Account_Capture_Plan_v1.xlsx — Worldpay Source Snapshot | H22: Medium | I22: Baseline; requires current verification | J22: 2026-07-20
A23: LAROSA'S INC | B23: Baseline stack | C23: Worldpay source | E23: Internal source | F23: Worldpay reports POS=Point of Sale.Cloud; ISV/payments=Mainstreet Monetray, TriPOS; ecommerce=Same as instore. | G23: Worldpay_30_Account_Capture_Plan_v1.xlsx — Worldpay Source Snapshot | H23: Medium | I23: Baseline; requires current verification | J23: 2026-07-20
A24: CHURCHS CHICKEN 558 | B24: Baseline stack | C24: Worldpay source | E24: Internal source | F24: Worldpay reports POS=QuPOS; ISV/payments=Aurus; ecommerce=Olo. | G24: Worldpay_30_Account_Capture_Plan_v1.xlsx — Worldpay Source Snapshot | H24: Medium | I24: Baseline; requires current verification | J24: 2026-07-20
A25: GOLDEN CORRAL | B25: Baseline stack | C25: Worldpay source | E25: Internal source | F25: Worldpay reports POS=QuPOS; ISV/payments=Aurus; ecommerce=Olo. | G25: Worldpay_30_Account_Capture_Plan_v1.xlsx — Worldpay Source Snapshot | H25: Medium | I25: Baseline; requires current verification | J25: 2026-07-20
A26: Red Robin | B26: Baseline stack | C26: Worldpay source | E26: Internal source | F26: Worldpay reports POS=Ziosk, NCR Aloha and Olo for eCom; ISV/payments=NCR, Ziosk; ecommerce=Monkey Media, Olo, Bounteous (wallet). | G26: Worldpay_30_Account_Capture_Plan_v1.xlsx — Worldpay Source Snapshot | H26: Medium | I26: Baseline; requires current verification | J26: 2026-07-20
A27: BOB EVANS RESTAURANTS, LLC | B27: Baseline stack | C27: Worldpay source | E27: Internal source | F27: Worldpay reports POS=NCR Aloha/Connected Payments; ISV/payments=NCR Connected Payments; ecommerce=Yes. | G27: Worldpay_30_Account_Capture_Plan_v1.xlsx — Worldpay Source Snapshot | H27: Medium | I27: Baseline; requires current verification | J27: 2026-07-20
A28: GRAETERS | B28: Baseline stack | C28: Worldpay source | E28: Internal source | F28: Worldpay reports POS=Brink; ISV/payments=Brink Software; ecommerce=Olo. | G28: Worldpay_30_Account_Capture_Plan_v1.xlsx — Worldpay Source Snapshot | H28: Medium | I28: Baseline; requires current verification | J28: 2026-07-20
A29: GRAETERS | B29: Field update | C29: User intelligence | D29: 46223 | E29: User-supplied | F29: Graeter's is a PAR customer but not PAR Enterprise. | G29: User field intelligence supplied for this analysis on 2026-07-20 | H29: High (user intelligence) | I29: Preserve separately from public verification | J29: 2026-07-20
A30: STARBUCKS CORPORATION | B30: Baseline stack | C30: Worldpay source | E30: Internal source | F30: Worldpay reports POS=VF PWC; ISV/payments=unknown; ecommerce=Yes. | G30: Worldpay_30_Account_Capture_Plan_v1.xlsx — Worldpay Source Snapshot | H30: Medium | I30: Baseline; requires current verification | J30: 2026-07-20
A31: LITTLE CAESARS ENTERPRISE INC | B31: Baseline stack | C31: Worldpay source | E31: Internal source | F31: Worldpay reports POS=CaesarVision; ISV/payments=CaesarVision (via Verifone SCA); ecommerce=CaesarVision (via eProtect). | G31: Worldpay_30_Account_Capture_Plan_v1.xlsx — Worldpay Source Snapshot | H31: Medium | I31: Baseline; requires current verification | J31: 2026-07-20
A32: PAPA JOHN'S USA, INC. | B32: Baseline stack | C32: Worldpay source | E32: Internal source | F32: Worldpay reports POS=Mainstreet Monetra; ISV/payments=Mainstreet Monetra; ecommerce=Yes. | G32: Worldpay_30_Account_Capture_Plan_v1.xlsx — Worldpay Source Snapshot | H32: Medium | I32: Baseline; requires current verification | J32: 2026-07-20
A33: BLACK BEAR DINER | B33: Baseline stack | C33: Worldpay source | E33: Internal source | F33: Worldpay reports POS=Toast / Olo; ISV/payments=Toast; ecommerce=Olo. | G33: Worldpay_30_Account_Capture_Plan_v1.xlsx — Worldpay Source Snapshot | H33: Medium | I33: Baseline; requires current verification | J33: 2026-07-20
A34: DOMINO'S PIZZA | B34: Baseline stack | C34: Worldpay source | E34: Internal source | F34: Worldpay reports POS=Proprietary; ISV/payments=ACI/Cybersource; ecommerce=Yes. | G34: Worldpay_30_Account_Capture_Plan_v1.xlsx — Worldpay Source Snapshot | H34: Medium | I34: Baseline; requires current verification | J34: 2026-07-20
A35: FIREHOUSE RESTAURANT | B35: Baseline stack | C35: Worldpay source | E35: Internal source | F35: Worldpay reports POS=Toast; ISV/payments=Toast; ecommerce=Yes, CP No. | G35: Worldpay_30_Account_Capture_Plan_v1.xlsx — Worldpay Source Snapshot | H35: Medium | I35: Baseline; requires current verification | J35: 2026-07-20
A36: BOYNE USA INC | B36: Baseline stack | C36: Worldpay source | E36: Internal source | F36: Worldpay reports POS=FreedomPay; ISV/payments=Agilysys, RTP; ecommerce=Flaik. | G36: Worldpay_30_Account_Capture_Plan_v1.xlsx — Worldpay Source Snapshot | H36: Medium | I36: Baseline; requires current verification | J36: 2026-07-20
A37: SLIM CHICKENS | B37: Baseline stack | C37: Worldpay source | E37: Internal source | F37: Worldpay reports POS=PAR Brink (VAR - Verifone Classic) and Olo; ISV/payments=PAR Brink; ecommerce=Olo. | G37: Worldpay_30_Account_Capture_Plan_v1.xlsx — Worldpay Source Snapshot | H37: Medium | I37: Baseline; requires current verification | J37: 2026-07-20
A38: Barbara B Mann PAH | B38: Baseline stack | C38: Worldpay source | E38: Internal source | F38: Worldpay reports POS=Cybersource; ISV/payments=unknown; ecommerce=Yes. | G38: Worldpay_30_Account_Capture_Plan_v1.xlsx — Worldpay Source Snapshot | H38: Medium | I38: Baseline; requires current verification | J38: 2026-07-20
A39: STATION CASINO | B39: Baseline stack | C39: Worldpay source | E39: Internal source | F39: Worldpay reports POS=FreedomPay; ISV/payments=Agilysys; ecommerce=OnDemand. | G39: Worldpay_30_Account_Capture_Plan_v1.xlsx — Worldpay Source Snapshot | H39: Medium | I39: Baseline; requires current verification | J39: 2026-07-20
A40: LATRELLES MANAGEMENT CORP (Bullritos) | B40: Baseline stack | C40: Worldpay source | E40: Internal source | F40: Worldpay reports POS=NCR Aloha/Connected Payments; ISV/payments=NCR Aloha; ecommerce=unknown. | G40: Worldpay_30_Account_Capture_Plan_v1.xlsx — Worldpay Source Snapshot | H40: Medium | I40: Baseline; requires current verification | J40: 2026-07-20
A41: FESTIVA REAL ESTATE HOLDINGS | B41: Baseline stack | C41: Worldpay source | E41: Internal source | F41: Worldpay reports POS=Shift4 & other; ISV/payments=Shift4 & other; ecommerce=Yes. | G41: Worldpay_30_Account_Capture_Plan_v1.xlsx — Worldpay Source Snapshot | H41: Medium | I41: Baseline; requires current verification | J41: 2026-07-20
A42: Focus Brands (GoTo Foods) | B42: POS | C42: Selection | D42: 45351 | E42: Qu press release | F42: Selected Qu as single POS platform across all seven brands. | G42: https://www.qubeyond.com/resource-center/goto-foods-selects-qu-as-its-single-pos-platform-across-all-seven-brands | H42: High | I42: Deploying | J42: 2026-07-20
A43: Focus Brands (GoTo Foods) | B43: POS | C43: Deployment milestone | D43: 45931 | E43: Qu event recap | F43: GoTo Foods CTO reported more than 2,000 Qu installs; exact event date should be treated as publication-period evidence. | G43: https://www.qubeyond.com/lessons-from-restaurant-leaders-who-know-their-brands/ | H43: Medium | I43: Deploying; field intelligence reports delay | J43: 2026-07-20
A44: PAPA JOHN'S USA, INC. | B44: POS / Back Office | C44: Selection | D44: 46034 | E44: PAR press release | F44: Selected PAR POS and PAR OPS across about 3,200 U.S. restaurants; full rollout planned by end of 2027. | G44: https://partech.com/news-coverage/papa-johns-partners-with-par-technology-to-power-pos-and-ops-transformation-across-3200-u-s-restaurants/ | H44: High | I44: Newly selected / deploying | J44: 2026-07-20
A45: FIVE GUYS | B45: POS | C45: Original selection | D45: 42005 | E45: Trade coverage of PAR announcement | F45: Five Guys selected PAR Brink POS and associated hardware/services after franchisee-led evaluation. | G45: https://www.fastcasual.com/news/why-five-guys-selected-new-pos-solution-2/ | H45: Medium | I45: Mature incumbent | J45: 2026-07-20
A46: FIVE GUYS | B46: Back Office | C46: Customer case study | D46: 45701 | E46: Crunchtime | F46: Crunchtime describes a relationship originating around 2015 and expanded to 1,900+ locations; strong operating outcomes. | G46: https://www.crunchtime.com/blog/ops-excellence-awards-finalist-spotlight-five-guys | H46: High | I46: Entrenched and positive | J46: 2026-07-20
A47: FIVE GUYS | B47: Digital / Guest Data | C47: Expansion | E47: Olo case study | F47: Longtime Olo ordering customer expanded to GDP and Marketing across 1,500 locations. | G47: https://www.olo.com/case-studies/five-guys-engage | H47: High | I47: Entrenched and expanding | J47: 2026-07-20
A48: Dutch Bros | B48: Digital Ordering / Payments | C48: Selection | D48: 45419 | E48: Olo press release | F48: Selected Olo Order and Pay for nationwide rollout, initially across 850+ locations. | G48: https://investors.olo.com/news/news-details/2024/Dutch-Bros-Partners-with-Olo-to-Offer-Mobile-App-Ordering-and-Payment/default.aspx | H48: High | I48: Established | J48: 2026-07-20
A49: Dutch Bros | B49: Loyalty / CRM | C49: Customer case study | E49: Paytronix case study | F49: Dutch Rewards app and loyalty experience run on Paytronix. | G49: https://www.paytronix.com/hubfs/media/dutch_bros_case-study_v3.pdf | H49: High | I49: Established | J49: 2026-07-20
A50: CHURCHS CHICKEN 558 | B50: POS | C50: Selection | D50: 44245 | E50: Qu / Business Wire release | F50: Selected Qu as enterprise POS for approximately 1,000 U.S. locations. | G50: https://www.businesswire.com/news/home/20210218005023/en/Churchs-Chicken-Selects-Qu-POS-as-Part-of-Global-Technology-Stack-Refresh | H50: High | I50: Established | J50: 2026-07-20
A51: SLIM CHICKENS | B51: Digital Ordering | C51: Original launch | D51: 42736 | E51: Olo case study | F51: Launched Olo Ordering in 2017, added Dispatch, Rails and Switchboard, then Sync in 2022. | G51: https://www.olo.com/case-studies/slim-chickens | H51: High | I51: Entrenched and expanding | J51: 2026-07-20
A52: FREDDY'S FROZEN CUSTARD LLC | B52: POS | C52: Current customer evidence | D52: 45436 | E52: PAR customer announcement | F52: PAR identifies Freddy’s as a Brink POS customer. | G52: https://partech.com/2024/05/24/congratulations-to-par-customers-2024-fast-casual-movers-and-shakers-honorees/ | H52: High | I52: Established | J52: 2026-07-20
A53: BLACK BEAR DINER | B53: Digital / Catering | C53: Current customer evidence | E53: Olo case-study directory | F53: Olo lists Black Bear Diner as a catering customer story. | G53: https://www.olo.com/case-studies | H53: Medium | I53: Current public evidence | J53: 2026-07-20
A54: CRACKER BARREL OLD COUNTRY STORE, INC. | B54: Digital / Catering | C54: Current customer evidence | E54: Olo case-study directory | F54: Olo lists Cracker Barrel as a Catering+ customer story. | G54: https://www.olo.com/case-studies | H54: Medium | I54: Current public evidence | J54: 2026-07-20
A55: FREDDY'S FROZEN CUSTARD LLC | B55: Digital / Catering | C55: Current customer evidence | E55: Olo case-study directory | F55: Olo lists Freddy’s as a Catering+ customer story. | G55: https://www.olo.com/case-studies | H55: Medium | I55: Current public evidence | J55: 2026-07-20
A56: SUBWAY | B56: POS | C56: Deployment report | D56: 46149 | E56: Payments Dive | F56: Reported Genius adoption at about 2,500 Subway stores; requires internal confirmation of scope and status. | G56: https://www.paymentsdive.com/news/global-payments-touts-genius-gains/819560/ | H56: Medium | I56: Partial deployment / expansion | J56: 2026-07-20
A57: Portfolio | B57: Genius product scope | C57: Product launch | D57: 45793 | E57: Global Payments press release | F57: Genius launched as unified POS platform; restaurant edition launched first. | G57: https://investors.globalpayments.com/news-events/press-releases/detail/473/global-payments-launches-new-genius-pos-platform | H57: High | I57: Current product baseline | J57: 2026-07-20
A58: Portfolio | B58: Operating model | C58: Leadership feedback | D58: 46237 | E58: Ryan Hildebrand JPR | F58: Keep Blue Sheets; add Refine stage, RM economics, event access, account history and a payments capability map. | G58: system/account_intelligence/2026-08-03-ryan-hildebrand-worldpay-development-plan-feedback.md | H58: High | I58: Update the master-plan operating cadence | J58: 46248
A59: SUBWAY | B59: Genius scope | C59: Internal leadership feedback | D59: 46237 | E59: Ryan Hildebrand JPR | F59: Proprietary POS plus a reported global Genius KDS deployment conflicts with the prior DMB interpretation. | G59: system/account_intelligence/2026-08-03-ryan-hildebrand-worldpay-development-plan-feedback.md | H59: High internal / scope unverified | I59: Replace DMB assumption; keep conflict urgent | J59: 46248
A60: FIVE GUYS | B60: Buying event | C60: Field validation | D60: 46245 | E60: Jeff Staley JPR + independent checks | F60: Capability evaluation is plausible, but no formal RFP was found; MJ Worsham remains active and influential. | G60: system/account_intelligence/2026-08-11-jeff-staley-jpr-intelligence.md | H60: Mixed / independently checked | I60: Treat RFP and spring 2027 timing as unconfirmed | J60: 46248
A61: FIVE GUYS | B61: Commercial model | C61: Internal concept | D61: 46244 | E61: Worldpay/Genius executive concept | F61: Transaction-metered POS is an internal feasibility concept and is not approved for customer presentation. | G61: system/account_intelligence/2026-08-10-worldpay-transaction-funded-pos-executive-summary.md | H61: High internal | I61: Secure sponsorship and feasibility approval first | J61: 46248
A62: DEL TACO LLC | B62: Ownership | C62: Verified public event | D62: 46013 | E62: Jack in the Box investor release | F62: Yadav Enterprises completed the acquisition; active technology shopping remains unconfirmed. | G62: https://investors.jackinthebox.com/news/news-details/2025/Jack-in-the-Box-Inc--Completes-Sale-of-Del-Taco-Holdings-Inc-/default.aspx | H62: High | I62: Use ownership change for neutral discovery | J62: 46248
A63: FREDDY'S FROZEN CUSTARD LLC | B63: Channel / leadership | C63: RDS field intelligence | D63: 46247 | E63: Darren Heinze JPR | F63: RDS is deeply embedded; the new CIO reportedly favors PAR; Todd committed to no direct outreach. | G63: tmp/jpr-2026-08-13/2026-08-13-darren-heinze-rds-jpr-intelligence.md | H63: High field / decision unverified | I63: Downgrade to protected RDS watchlist | J63: 46248
A64: RDS FIVE-UNIT REBRAND PILOT | B64: Channel pilot | C64: RDS field intelligence | D64: 46247 | E64: Darren Heinze JPR | F64: Five former Taco Cabana sites are rebranding and evaluating a clean-slate stack/DMB; customer details require confirmation. | G64: tmp/jpr-2026-08-13/2026-08-13-darren-heinze-rds-jpr-intelligence.md | H64: High field / documentation required | I64: Qualify as the preferred near-term channel pilot | J64: 46248
A65: SLIM CHICKENS | B65: Channel rule | C65: RDS field intelligence | D65: 46247 | E65: Darren Heinze JPR | F65: Remain RDS-led; no direct outreach and no new buying event surfaced. | G65: tmp/jpr-2026-08-13/2026-08-13-darren-heinze-rds-jpr-intelligence.md | H65: High field | I65: Keep as relationship-map account | J65: 46248
A66: PAPA JOHN'S USA, INC. | B66: POS / Back Office | C66: PAR earnings evidence | D66: 46240 | E66: PAR Q2 2026 earnings materials | F66: Development milestones achieved; implementation expected later in 2026. Linux dependency is separate unverified field intelligence. | G66: https://partech.com/investor-relations/ | H66: High public / field detail unverified | I66: Monitor deployment and validate technical dependency | J66: 46248
A67: Portfolio | B67: Competitive pattern | C67: PAR earnings evidence | D67: 46240 | E67: PAR Q2 2026 earnings call | F67: PAR uses POS/loyalty beachheads, multi-product bundles and mandatory payments attachment on ordering wins. | G67: https://partech.com/investor-relations/ | H67: High company-reported | I67: Add platform/payment-attachment defense to account plans | J67: 46248
A68: POLLO CAMPERO | B68: POS / payments / DMB | C68: Internal account brief | D68: 46244 | E68: Pollo Campero account brief | F68: Oracle migration, NCR legacy, Fiserv in-store, Olo Pay/Stripe digital and potential RFI/DMB issues require qualification. | G68: system/account_intelligence/2026-08-10-pollo-campero-comprehensive-account-brief.md | H68: Strong internal / procurement unconfirmed | I68: Add as emerging opportunity with bid/no-bid gates | J68: 46248
A69: CHOICE HOTELS | B69: Gateway / acquiring | C69: Evidence aging | D69: 46248 | E69: Master-plan review | F69: July active-RFP intelligence now requires a current-stage and deadline refresh. | G69: Worldpay master-plan review 2026-08-14 | H69: Review finding | I69: Do not retain 'active RFP' without refresh | J69: 46248
... A74: LITTLE CAESARS ENTERPRISE INC | B74: Relationship access | C74: RM field update | D74: 46269.5 | E74: Avery Churchwell | F74: Three follow-up items remained unanswered after roughly 1.5 weeks, although Avery participated in a technical-support call with the account earlier that week. | G74: Avery Churchwell account update call, 2026-09-04 | H74: High (RM interaction) | I74: Use the support interaction to recover responsiveness and consolidate open requests. | J74: 46269.5
A85: DEL TACO LLC | C85: vendor_relationship_formed | D85: 2019-09-10 | F85: Del Taco Partners With Postmates To Bring Mexican And American Favorites Directly To Your Door - PR Newswire. Del Taco Partners With Postmates To Bring Mexican And American Favorites Directly To Your Door - PR Newswire | H85: RBB-detected | J85: 2026-09-02

Sheet Conflict Register
A1: Conflict & Verification Register — 2026-08-14
A2: Conflicts are preserved until resolved; newer evidence does not erase the historical source.
A4: Account | B4: Issue | C4: Incoming / Legacy View | D4: Newer Evidence | E4: Evidence Type | F4: Resolution Action | G4: Status
A5: PAPA JOHN'S USA, INC. | B5: Stale Worldpay opportunity | C5: Worldpay: evaluating gateway/POS | D5: PAR selected Jan. 12, 2026; rollout through 2027 | E5: Verified public fact | F5: Supersede open POS opportunity; monitor deployment and adjacency | G5: RESOLVED
A6: Focus Brands (GoTo Foods) | B6: Scope and deployment health | C6: Worldpay: moving all to Qu | D6: Qu confirms seven-brand POS selection; >2,000 installs; user reports rollout delay | E6: Verified + user intelligence | F6: Validate rollout pace and sources of delay without overstating failure | G6: OPEN
A7: WENDY'S INTERNATIONAL INC | B7: Ownership boundary | C7: Worldpay: NCR Aloha; user reported active decision | D7: Not an opportunity owned by Todd | E7: User correction | F7: Retain for intelligence only; no Todd pursuit action | G7: EXCLUDED
A8: DEL TACO LLC | B8: Duplicate/unowned leads | C8: Worldpay: NCR/Olo stack | D8: User: leads exist across Global Payments | E8: User intelligence | F8: Inventory and merge leads; assign owner and next action | G8: URGENT
A9: Dutch Bros | B9: Ownership boundary | C9: Worldpay: Xenial POS; user: existing Genius customer | D9: Managed by a Global Payments account manager; not Todd-owned | E9: User correction + public context | F9: Retain for intelligence only; account manager owns activity | G9: EXCLUDED
A10: FREDDY'S FROZEN CUSTARD LLC | B10: Channel posture and buying event | C10: P2 adjacency/international opportunity | D10: RDS-protected account; new CIO reportedly reinforcing PAR; no direct outreach | E10: High RDS field intelligence | F10: Downgrade to watchlist; prove the smaller RDS pilot first | G10: REFRAMED
A11: GRAETERS | B11: Product edition | C11: Worldpay: Brink | D11: User: PAR, but not Enterprise | E11: User intelligence | F11: Confirm SKU, reseller and enterprise migration fit | G11: OPEN
A12: FIVE GUYS | B12: Buying-event certainty and timing | C12: Spring 2027 RFP assumed; MJ departure reported | D12: Capability evaluation plausible; no formal RFP found; MJ remains active | E12: Field intelligence + independent check | F12: Confirm evaluation type, expiration/notice dates, sponsor, scope and decision criteria | G12: URGENT
A13: SUBWAY | B13: Genius product scope | C13: Prior record alternated between partial Genius POS and DMB | D13: Ryan reports proprietary POS plus global Genius KDS deployment; exact sites/status remain unverified | E13: Internal leadership intelligence | F13: Confirm product owner, KDS sites, deployment status, commitments and sponsor | G13: URGENT
A14: CHOICE HOTELS | B14: RFP status aging | C14: Active RFP reported in July | D14: No August stage/deadline refresh found | E14: RM intelligence aging | F14: Confirm current stage, dates, sponsor and retained estate | G14: URGENT
A15: PAPA JOHN'S USA, INC. | B15: Linux technical dependency | C15: PAR rollout tracked; no technical dependency recorded | D15: RDS claims Linux build is required; public sources do not confirm | E15: Confidential field intelligence | F15: Validate with technical/product owners; do not persist as fact | G15: OPEN
... A17: RDS FIVE-UNIT REBRAND PILOT | B17: Customer identity and authority | C17: Not present in prior portfolio | D17: Clean-slate rebrand offered as pilot; entity, concept and authority unconfirmed | E17: High channel field intelligence | F17: Document entity, authority, dates, budget, scope and protection terms | G17: URGENT

Sheet RM Portfolio
A1: RM Portfolio Briefings — 2026-09-04
A2: Opportunity counts exclude Wendy's and Dutch Bros. Protected channel accounts remain governed by RDS engagement rules.
A4: RM | B4: Opportunity Accounts | C4: P1 Accounts | D4: Average Score | E4: Top Ranked Accounts | F4: Trigger Summary | G4: Workshop Focus | H4: Required Output
A5: Avery Churchwell | B5: 11 | C5: 1 | D5: 57.1 | E5: FIVE GUYS, Red Robin, EAT'N PARK, MILLER'S ALE HOUSE, BLACK BEAR | F5: Five Guys outreach governance/FSTEC opening | Slim Chickens RDS-led FSTEC contact | Little Caesars follow-up stall | Red Robin reassessment | G5: Centralize Five Guys outreach with Avery/Todd; coordinate Slim Chickens and Freddy's through RDS; recover Little Caesars follow-ups; qualify Red Robin timing. | H5: Named owner and coordinated contact plan for each account; FSTEC connection plan; verified buying trigger, renewal dates and dated next action.
A6: Brian Wood | B6: 8 | C6: 1 | D6: 59.6 | E6: GoTo Foods, CHOICE HOTELS, PAPA JOHN'S, CRACKER BARREL, BOB EVANS | F6: GoTo platform/payment defense | Choice RFP refresh | Papa Johns rollout watch | G6: GoTo DMB map; Choice status refresh; Papa Johns adjacency and implementation monitoring | H6: Named account owner, current scope, decision dates, buying-center map and warm introduction.
A7: Maggie Lenhart | B7: 6 | C7: 1 | D7: 65.2 | E7: DEL TACO, STEAK N SHAKE, CHURCH'S, LAROSA'S, GOLDEN CORRAL | F7: Del Taco extension/Yadav event | Steak 'n Shake remediation | Church's decision unresolved | G7: Complete Del Taco extension and lead consolidation; establish dated kiosk remediation | H7: Verified buying event, owner map, technical issue owners and customer introduction.
A8: Stacie Davis | B8: 3 | C8: 1 | D8: 63 | E8: SUBWAY, STARBUCKS, DOMINO'S | F8: Subway KDS scope conflict | Starbucks share recovery | Domino's reference posture | G8: Resolve Subway product/sites/owner before any new positioning | H8: Confirmed Genius KDS scope, customer sponsor, commitments and next relationship.
A9: RDS / Darren Heinze | B9: 1 | C9: 0 | D9: 74 | E9: RDS FIVE-UNIT REBRAND PILOT | F9: Clean-slate pilot; protected-account operating model | G9: Document entity, scope, economics, support, protections and case-study rights | H9: Qualified customer facts, signed engagement rules and a dated pilot plan.
A10: Unassigned / Worldpay | B10: 1 | C10: 0 | D10: 72 | E10: POLLO CAMPERO | F10: Potential RFI; Oracle migration; split payment stack | G10: Assign owner, obtain NDA/RFI and apply bid/no-bid gates | H10: Named owner, procurement documents, timeline, country scope and decision openness.

Sheet Scoring Model
A1: Portfolio Scoring Model — 2026-08-14
A2: Score 1–5, then Refine after every material signal. Unknown is not whitespace; unverified triggers must not be scored as active decisions.
A4: Dimension | B4: Weight | C4: 1 = Low | D4: 3 = Medium | E4: 5 = High | F4: Interpretation
A5: Strategic Value | B5: 0.2 | C5: Small/low leverage | D5: Meaningful footprint | E5: Transformational scale | F5: Account size, tier, franchise leverage
A6: Active Buying Trigger | B6: 0.2 | C6: No trigger | D6: Research/discovery signal | E6: Active decision or internal lead | F6: Time-sensitive commercial motion
A7: Relationship / Access | B7: 0.15 | C7: No path | D7: Named RM/internal route | E7: Active customer access | F7: Ability to influence outcome
A8: Incumbent Lifecycle | B8: 0.15 | C8: New/locked | D8: Established or unclear | E8: Decision window/aging | F8: Switchability, not just age
A9: Deployment Health | B9: 0.1 | C9: Healthy/positive | D9: Unknown/mixed | E9: Material issue reported | F9: Crack signal or implementation need
A10: Adjacent Whitespace | B10: 0.15 | C10: Stack entrenched | D10: Some gaps | E10: Many verified/qualifiable gaps | F10: Unknown is not automatically whitespace
A11: Internal Coordination | B11: 0.05 | C11: Simple | D11: Several owners | E11: Urgent cross-team alignment | F11: Need to merge leads/owners/actions
A13: Formula
A14: Total Score | B14: SUM of each (dimension score ÷ 5 × dimension weight)
A15: Priority Bands | B15: P1 ≥ 78 | P2 65–77.9 | P3 < 65

Sheet Worldpay Source Snapshot
A1: Merchant | B1: DIrect ID | C1: Superchain/Corp Chain | D1: Franchise Code | E1: National Bank | F1: CP/Ecom | G1: Owner | H1: Vertical | I1: 2022 Jan-Sep | J1: 2022 Forecast | K1: Tier | L1: # of Locations | M1: % Corporated Owned | N1: % Franchise Owned. | O1: Int'l? | P1: RM | Q1: CSM | R1: PCO? | S1: Franchise Relationship Manager | T1: Notes | U1: POS | V1: ISV | W1: Terminals | X1: Kiosk | Y1: Ecommerce-Worldpay | Z1: Ecommerce-Other | AA1: Tier Adj (Susan) | AB1: Vertical Adj (James) | AC1: Tier Adj (James) | AD1: James | AE1: Notes.1 | AF1: Missing | AG1: Unnamed: 32 | AH1: Unnamed: 33 | AI1: Unnamed: 34 | AJ1: Unnamed: 35 | AK1: Unnamed: 36 | AL1: Unnamed: 37 | AM1: Unnamed: 38 | AN1: Unnamed: 39 | AO1: Unnamed: 40 | AP1: Unnamed: 41 | AQ1: Unnamed: 42 | AR1: Unnamed: 43 | AS1: Unnamed: 44
A2: Barbara B Mann PAH | F2: CP | G2: Susan | H2: Hospitality | J2: 398196 | K2: Tier 2 | O2: No | P2: Brian Wood | Q2: Ashlee Strete | U2: Cybersource | Y2: Yes | Z2: No
A3: BLACK BEAR DINER | B3: DRCT - 000639- VREL | C3: S000000058 | D3: BLCKBR | F3: CP | G3: Susan | H3: Hospitality | I3: 249980.04 | J3: 333306.72 | K3: Tier 2 | L3: 217 | M3: 0.6 | N3: 0.4 | O3: 0 | P3: Avery Churchwell | Q3: Michelle Weddington | R3: Melissa Douglas | S3: Gaynor Baker | T3: CP is moving to Toast, will likely move to unmanaged | U3: Toast / Olo | V3: Toast | W3: Toast | Y3: Olo
A4: BOB EVANS RESTAURANTS, LLC | C4: 000131 | F4: CP | G4: Susan | H4: Hospitality | I4: 310354.07 | J4: 413805.43 | K4: Tier 2 | L4: 450 | M4: 1 | N4: 0 | O4: No | P4: Brian Wood | Q4: Ashlee Strete | R4: Melissa Douglas | U4: NCR Aloha/Connected Payments | V4: NCR Connected Payments | Y4: Yes | Z4: No
A5: BOYNE USA INC | B5: DRCT - 000723- VREL | C5: SCBYNHGLDS | F5: CP | G5: Susan | H5: Hospitality | I5: 252196.4 | J5: 336261.87 | K5: Tier 2 | L5: 17 | M5: 1 | N5: 0 | O5: 0.05 | P5: Avery Churchwell | Q5: Michelle Weddington | R5: Melissa Douglas | T5: 1 Canadian location | U5: FreedomPay | V5: Agilysys, RTP | W5: Swipe Simple B250 & FB Terminals | X5: Mashgin | Y5: Flaik | AF5: MISSING
A6: CHOICE HOTELS | D6: CH2019 | F6: CP | G6: Susan | H6: Hospitality | I6: 1422373.6 | J6: 1896498.1 | K6: Tier 2 | M6: 0 | N6: 1 | O6: No | P6: Brian Wood | Q6: Michelle Weddington | T6: Deconverting | U6: Shift4 | Y6: Yes | Z6: No
A7: CHURCHS CHICKEN 558 | B7: DRCT - 006011- VREL | C7: S000002085, S000002083, SC0CHURCHA | D7: CHRCKN | E7: N000089 | F7: CP | G7: Susan | H7: Hospitality | I7: 658127.71 | J7: 877503.61 | K7: Tier 2 | L7: 832 | M7: 0.2 | N7: 0.8 | P7: Maggie Lenhart | Q7: Michelle Weddington | R7: Melissa Douglas | S7: Gaynor Baker | U7: QuPOS | V7: Aurus | W7: Lane 3000 | X7: Pilot with Bite (Express) | Y7: Olo
A8: CRACKER BARREL OLD COUNTRY STORE, INC. | C8: 0F6695, 0XX626 | F8: CP | G8: Susan | H8: Hospitality | I8: 775765.35 | J8: 1034353.8 | K8: Tier 2 | L8: 600 | M8: 1 | N8: 0 | O8: No | P8: Brian Wood | Q8: Michelle Weddington | R8: Melissa Douglas | T8: In Conversion for new POS with FP | U8: RAFT 610 for POS, Express for OLO ISV for mobile, and eComm is on VAP. Moving to Oracle Symphony | V8: FreedomPay | Y8: Yes | Z8: No
A9: DEL TACO LLC | B9: DRCT - 006020- VREL | C9: S000001636 | D9: DLTACO | F9: CP | G9: Susan | H9: Hospitality | I9: 559666.28 | J9: 746221.7 | K9: Tier 2 | L9: 537 | M9: 0.3 | N9: 0.7 | P9: Maggie Lenhart | Q9: Michelle Weddington | R9: Melissa Douglas | S9: Gaynor Baker | U9: NCR | V9: NCR Connected Payments | X9: Bite (Express) | Y9: OLO corporate | Z9: We don't have all Franchise locations. Multiple acquirers utilized. OloPay
A10: DOMINO'S PIZZA | B10: DRCT - 001429- VREL | C10: SCNDMNOPZA | E10: NDMNPZA | F10: CP | G10: Susan | H10: Hospitality | I10: 6034262.6 | J10: 8045683.5 | K10: Tier 1 | L10: 7000 | M10: 0.05 | N10: 0.95 | O10: Yes | P10: Stacie Davis | Q10: Greg Cappel | R10: Melissa Douglas | S10: Gaynor Baker | U10: Proprietary | V10: ACI/Cybersource | W10: Ingenico, Variable | X10: Yes | Y10: Yes
A11: Dutch Bros | B11: DRCT - 007676- VREL | C11: S000005309 | D11: DUTCHB | E11: N001348 | F11: CP | G11: Susan | H11: Hospitality | J11: 1400000 | K11: Tier 1 | L11: 1316 | M11: 0.72 | N11: 0.28 | P11: Maggie Lenhart | Q11: Michelle Weddington | R11: Melissa Douglas | S11: Gaynor Baker | U11: Xenial Cloud POS | V11: Verifone SCA Gateway | W11: Verifone e285 (Xenial iPads) | Z11: OloPay, Braintree, Paytronix
A12: EAT'N PARK HOSPITALITY GRP INC | B12: DRCT - 00073880 | C12: 72452 | F12: CP | G12: Susan | H12: Hospitality | I12: 235629.41 | J12: 314172.54 | K12: Tier 2 | L12: 137 | M12: 1 | N12: 0 | O12: 0 | P12: Avery Churchwell | Q12: Ashlee Strete | R12: Melissa Douglas | T12: Four concepts under EAPK - VAR is based on concept. Parkhurst was on IP but is converting to Core | U12: FreedomPay, Tillster, Olo | V12: Oracle Simphony, PayMyTab, Catertrax | W12: Desk 3500s, T650c | Y12: Olo, Tillster (wallets), Nextep
A13: FESTIVA REAL ESTATE HOLDINGS | C13: SCFESTIVAG | F13: CP | G13: Susan | H13: Hospitality | I13: 383181.43 | J13: 510908.58 | K13: Tier 2 | O13: No | P13: Brian Wood | Q13: Michelle Weddington | T13: Formerly part of Choice Hotels | U13: Shift4 & other | V13: Shift4 & other | Y13: Yes | Z13: No
A14: FIREHOUSE RESTAURANT | C14: SCFHSUBSCO | D14: FHSUBS | E14: NFHSUBS | F14: CP | G14: Susan | H14: Hospitality | I14: 646798.6 | J14: 862398.13 | K14: Tier 2 | L14: 1200 | M14: 0.1 | N14: 0.9 | O14: No | P14: Brian Wood | Q14: Greg Cappel | R14: Melissa Douglas | S14: Gaynor Baker | T14: GC in-store eGiftify via Toast | U14: Toast | V14: Toast | Y14: Yes, CP No | Z14: No
A15: FIVE GUYS | B15: DRCT - 001783- VREL | C15: S5GUYSFRAN/ 0M9131 | D15: 5GUYS | E15: NB5GUYS | F15: CP | G15: Susan | H15: Hospitality | I15: 1965606.7 | J15: 2620809 | K15: Tier 1 | L15: 1500 | M15: 0.4 | N15: 0.6 | O15: 0 | P15: Avery Churchwell | Q15: Ashlee Strete | R15: Melissa Douglas | S15: Anne-Marie Cloutier | T15: Int'l stores, not with WP | U15: Par, Verifone SCA, Olo | V15: PAR | W15: M400s | X15: LineTen | Y15: Olo
A16: Focus Brands (GoTo Foods) | D16: ANTANN - Auntie Anne's CARVEL - Carvel CINBON – Cinnabon CSWIRL – Cinnabon Swirl JAMBA - Jamba MCADEL - McAlister's MOESSW - Moe's SCHLKY - Schlotzsky's | E16: NCARVEL - Carvel NANTANN - Auntie Anne's NCINBON - Cinnabon CCSWIRL - Cinnabon Swirl N0JAMBA - Jamba NMCADEL - McAlister's NMOESSW - Moe's NSCHLKY - Schlotzsky's | F16: CP | G16: Susan | H16: Hospitality | I16: 493273.22 | J16: 657697.62 | K16: Tier 2 | L16: 2600 | N16: YES | O16: No | P16: Brian Wood | Q16: Ashlee Strete | R16: Melissa Douglas | S16: Anne-Marie Cloutier | T16: FreedomPay | U16: FreedomPay (in-store), OLO (online), Monkey Media (catering), moving all to Qu | V16: FreedomPay | X16: 8 MIDs have Verifone | Y16: Yes | Z16: No | AS16: 110000000
A17: FREDDY'S FROZEN CUSTARD LLC | B17: DRCT - 001867- VREL | C17: S000000027 | D17: FREFRO | E17: N001420 | F17: CP | G17: Susan | H17: Hospitality | I17: 261286.77 | J17: 348382.37 | K17: Tier 2 | L17: 500 | M17: 0.1 | N17: 0.9 | O17: 0 | P17: Avery Churchwell | Q17: Deb Cunningham | R17: Melissa Douglas | T17: Beginning to move to franchise pod | U17: PAR Brink (VAR -Verifone Classic) | V17: PAR Brink | W17: P400s and E285 | Z17: OloPay
A18: GOLDEN CORRAL | B18: DRCT - 006011- VREL | C18: SCGDCRFRAN, SCGOLDENCR, SCGDCRHOME | D18: GOLCOR | E18: NGOLCOR | F18: CP | G18: Susan | H18: Hospitality | I18: 752621.45 | J18: 1003495.3 | K18: Tier 2 | L18: 640 | M18: 0.01 | N18: 0.99 | P18: Maggie Lenhart | Q18: Michelle Weddington | R18: Melissa Douglas | S18: Gaynor Baker | U18: QuPOS | V18: Aurus | Y18: Olo
A19: GRAETERS | B19: DRCT - 002101- VREL | C19: S000006768 | F19: CP | G19: Susan | H19: Hospitality | I19: 283860.71 | J19: 378480.95 | K19: Tier 2 | L19: 67 | M19: 1 | N19: 0 | P19: Maggie Lenhart | Q19: Ashlee Strete | R19: Melissa Douglas | U19: Brink | V19: Brink Software | Y19: Olo
A20: LAROSA'S INC | B20: DRCT - 002844- VREL | C20: SCLAROSAZZ | F20: CP | G20: Susan | H20: Hospitality | I20: 364928.69 | J20: 486571.59 | K20: Tier 2 | L20: 76 | M20: 0.26 | N20: 0.74 | P20: Maggie Lenhart | Q20: Ashlee Strete | R20: Melissa Douglas | U20: Point of Sale.Cloud | V20: Mainstreet Monetray, TriPOS | W20: Varies-majority are non-EMV through Montera | Y20: Same as instore
A21: LATRELLES MANAGEMENT CORP (Bullritos) | B21: DRCT - 010312- VREL | C21: S0LATRELLE | F21: CP | G21: Susan | H21: Hospitality | I21: 241138.57 | J21: 321518.09 | K21: Tier 2 | L21: 35 | M21: 1 | N21: 0 | O21: 0 | P21: Avery Churchwell | Q21: Michelle Weddington | R21: Melissa Douglas | U21: NCR Aloha/Connected Payments | V21: NCR Aloha
A22: LITTLE CAESARS ENTERPRISE INC | B22: DRCT - 002926- VREL | C22: SCLITCSARS/ 071106 | D22: LCEI | E22: NLITCSR | F22: CP | G22: Susan | H22: Hospitality | I22: 4946098.5 | J22: 6594798 | K22: Tier 1 | L22: 4200 | M22: 0.1 | N22: 0.9 | O22: 0 | P22: Avery Churchwell | Q22: Ashlee Strete | R22: Sam Merkle | S22: Anne-Marie Cloutier | T22: Int'l stores, not with WP | U22: CaesarVision | V22: CaesarVision (via Verifone SCA) | W22: M400s and P400s | X22: Mashgin | Y22: CaesarVision (via eProtect)
A23: MILLLER'S ALE HOUSE | B23: DRCT - 00235448 | C23: 02131A | F23: CP | G23: Susan | H23: Hospitality | I23: 182432 | J23: 243243 | K23: Tier 2 | L23: 112 | M23: 1 | N23: 0 | O23: 0 | P23: Avery Churchwell | Q23: Michelle Weddington | R23: Melissa Douglas | T23: CNP has moved to Olo direct | U23: NCR Connected Payments, Ziosk | V23: NCR, Ziosk | W23: Swipe Simple B250 & NCR Terminals | Z23: OloPay
A24: PAPA JOHN'S USA, INC. | C24: SCPAPACORP/0T3849 | D24: PAPAJN & PAPCAD | E24: NPAPASJ, NPAPCAD | F24: CP | G24: Susan | H24: Hospitality | I24: 2382458.3 | J24: 3176611.1 | K24: Tier 1 | L24: 3300 | M24: 0.15 | N24: 0.85 | O24: Yes | P24: Brian Wood | Q24: Ashlee Strete | R24: Melissa Douglas | S24: Anne-Marie Cloutier | T24: Evaluating Gateway/POS options | U24: Mainstreet Monetra | V24: Mainstreet Monetra | W24: Ingenico Lane 3000/ipp320/Lane 3600 | Y24: Yes | Z24: No
